Workbook
Name MATRICE: #REF!
Name MATRICE1: #REF!
Name MATRICE1: #REF!
Name MATRICEB: #REF!
Name MATRICEB: #REF!

Sheet ENTREE
A1: CODE | B1: Étiquettes de lignes | C1: quantite | D1: date entrée | E1: Vérif sage entrée | F1: vérif sage sortie
A2: FIXCARTEIMMARSAT | B2: CARTE IMMARSAT | C2: 5 | D2: 08/05/25 au 24/02/26 | E2: =VLOOKUP(A2,Tableau2[[Code Article]:[DATE INVENTAIRE]],11,FALSE) -> 46224
A3: TGSMCBL78F500ERK | B3: """ FEEDER CABLE 7/8"""" 500M (01 DRUM OF 500M) """ | C3: 393 | D3: 14/01/25 au 09/12/25 | E3: =VLOOKUP(A3,Tableau2[[Code Article]:[DATE INVENTAIRE]],11,FALSE) -> 46224
A4: TGSMPROUDUL20ERK | B4: "DUL 20 01, Digital Unit" | C4: 1 | D4: 45785 | E4: =VLOOKUP(A4,Tableau2[[Code Article]:[DATE INVENTAIRE]],11,FALSE) -> 46219 | F4: =VLOOKUP(A4,SORTIE!$A$2:$C$456,3,FALSE) -> #N/A
A5: TGSMPRUDUS411ERC | B5: "DUS 41 01,Digital unit" | C5: 2 | D5: 17/07/25 au 28/08/25 | E5: =VLOOKUP(A5,Tableau2[[Code Article]:[DATE INVENTAIRE]],11,FALSE) -> 46218
A6: TGSMPROUDUW31ERC | B6: "DUW, 31 01 Digital Unit" | C6: 31 | D6: 22/05/25 au 03/03/26 | E6: =VLOOKUP(A6,Tableau2[[Code Article]:[DATE INVENTAIRE]],11,FALSE) -> 46224
A7: TGSMTRCRUS1B3ERC | B7: "TRANSCEIVER/RRUS 01 B3,Radio | C7: 11 | D7: 20/03/25 au 05/03/26 | E7: =VLOOKUP(A7,Tableau2[[Code Article]:[DATE INVENTAIRE]],11,FALSE) -> 46216
A8: TGSMTRCRUS1B8ERC | B8: "TRANSCEIVER/RRUS 01B8,Radio U | C8: 95 | D8: 45776 | E8: =VLOOKUP(A8,Tableau2[[Code Article]:[DATE INVENTAIRE]],11,FALSE) -> 46224
A9: TGSMANTQB1L3HERC | B9: //QUAD BAND (1L+3H) | C9: 13 | D9: 45951 | E9: =VLOOKUP(A9,Tableau2[[Code Article]:[DATE INVENTAIRE]],11,FALSE) -> 46219 | F9: =VLOOKUP(A9,SORTIE!$A$2:$C$456,3,FALSE) -> 3
A10: TGSMANTTB1L2HERC | B10: //TRIBAND (1L+2H)_6880308NG | C10: 8 | D10: 45951 | E10: =VLOOKUP(A10,Tableau2[[Code Article]:[DATE INVENTAIRE]],11,FALSE) -> 46224
A11: TGSMANTM0678HERC | B11: 0.6 COMPACT ANTENNA 7/8 GHZ | C11: 224 | D11: 45988 | E11: =VLOOKUP(A11,Tableau2[[Code Article]:[DATE INVENTAIRE]],11,FALSE) -> 46224
A12: TGSMANT127G11ERC | B12: 1.2M DIA. PARABOLIC ANTENNA (V | C12: 66 | D12: 08/04/25 au 21/08/25 | E12: =VLOOKUP(A12,Tableau2[[Code Article]:[DATE INVENTAIRE]],11,FALSE) -> 46224
A13: TGSMANTM1278HERC | B13: 1.2M DIA. PARABOLIC ANTENNA 15GHZ | C13: 23 | D13: 13/05/25 au 06/11/25 | E13: =VLOOKUP(A13,Tableau2[[Code Article]:[DATE INVENTAIRE]],11,FALSE) -> 46224
A14: NMXTCBL16GN51XXX | B14: 16mm2, GNYE, (vert/jaune)5m, 1 lug with 2 M6 holes,_RPM1192062/5 | C14: 67 | D14: 45776 | E14: =VLOOKUP(A14,Tableau2[[Code Article]:[DATE INVENTAIRE]],11,FALSE) -> 46219 | F14: =VLOOKUP(A14,SORTIE!$A$2:$C$456,3,FALSE) -> #N/A
A15: NMXTCBL16GN31XXX | B15: 16mm2, GNYE, 3m_GROUNDING _RPM1192062/3 | C15: 39 | D15: 45951 | E15: =VLOOKUP(A15,Tableau2[[Code Article]:[DATE INVENTAIRE]],11,FALSE) -> 46219 | F15: =VLOOKUP(A15,SORTIE!$A$2:$C$456,3,FALSE) -> 39
A16: NMXTCDCAF363XXXX | B16: 1M DE CDC ACROFIL | C16: 1 | D16: 45951 | E16: =VLOOKUP(A16,Tableau2[[Code Article]:[DATE INVENTAIRE]],11,FALSE) -> 46219 | F16: =VLOOKUP(A16,SORTIE!$A$2:$C$456,3,FALSE) -> #N/A
A17: TGSMCRT1UDCDUERC | B17: 1U DCDU (Use SP-BMG 907 158/1 for spare_BMG907158/1 | C17: 1 | D17: 45785 | E17: =VLOOKUP(A17,Tableau2[[Code Article]:[DATE INVENTAIRE]],11,FALSE) -> 46224
A18: NMXTGLTPL2525XXX | B18: 2,5M DE GOULOTTE | C18: 7 | D18: 13/05/25 au 06/11/25 | E18: =VLOOKUP(A18,Tableau2[[Code Article]:[DATE INVENTAIRE]],11,FALSE) -> 46219 | F18: =VLOOKUP(A18,SORTIE!$A$2:$C$456,3,FALSE) -> 7
A19: TGSMTJARLL70UERC | B19: 2F LC-LC SM | C19: 405 | D19: 30/01/25 au 06/11/25 | E19: =VLOOKUP(A19,Tableau2[[Code Article]:[DATE INVENTAIRE]],11,FALSE) -> 46224
A20: TGSMCBL2FLL50ERC | B20: 2F LC(FullAXS)-LC SM 100M_RPM2531633/100M | C20: 878 | D20: 09/01/25 au 24/03/26 | E20: =VLOOKUP(A20,Tableau2[[Code Article]:[DATE INVENTAIRE]],11,FALSE) -> 46224
A21: NMXTCBLALC216XXX | B21: 2x16 mm2 UL LSOH Alu Cu screen TFL492326 500m | C21: 806 | D21: 45776 | E21: =VLOOKUP(A21,Tableau2[[Code Article]:[DATE INVENTAIRE]],11,FALSE) -> 46219 | F21: =VLOOKUP(A21,SORTIE!$A$2:$C$456,3,FALSE) -> 578
A22: NMXTCBLDC2X16XXX | B22: 2x16 sqmm_TFL492326/0 | C22: 39 | D22: 45951 | E22: =VLOOKUP(A22,Tableau2[[Code Article]:[DATE INVENTAIRE]],11,FALSE) -> 46219 | F22: =VLOOKUP(A22,SORTIE!$A$2:$C$456,3,FALSE) -> 36
A23: TGSMCBL2X6M5MERC | B23: 2x6mm2 (10AWG) 600V 90C UL 5m | C23: 2 | D23: 45951 | E23: =VLOOKUP(A23,Tableau2[[Code Article]:[DATE INVENTAIRE]],11,FALSE) -> 46224
A24: NMXTCBLDP2X6MERC | B24: 2x6mm2 DC Power Cable No CPR No UL | C24: 8540 | D24: 45988 | E24: =VLOOKUP(A24,Tableau2[[Code Article]:[DATE INVENTAIRE]],11,FALSE) -> 46224
A25: TMXTREBD3EGENXXX | B25: 36110 MAINSTREET | C25: 1 | D25: 08/04/25 au 21/08/25 | E25: =VLOOKUP(A25,Tableau2[[Code Article]:[DATE INVENTAIRE]],11,FALSE) -> 46216
A26: NANOSIMS | B26: 4FF NANO JAVA SAT SIM CARO | C26: 88 | D26: 13/05/25 au 06/11/25 | E26: =VLOOKUP(A26,Tableau2[[Code Article]:[DATE INVENTAIRE]],11,FALSE) -> 46219 | F26: =VLOOKUP(A26,SORTIE!$A$2:$C$456,3,FALSE) -> 88
A27: NMXTTUBSUPBALXXX | B27: TUBES SUPPORT | C27: 4 | D27: 45776 | E27: =VLOOKUP(A27,Tableau2[[Code Article]:[DATE INVENTAIRE]],11,FALSE) -> 46219 | F27: =VLOOKUP(A27,SORTIE!$A$2:$C$456,3,FALSE) -> #N/A
A28: TGSMANT06PPB2XXX | B28: 6-Port Antenna LB/2HB 2.7m_84510866 | C28: 99 | D28: 45951 | E28: =VLOOKUP(A28,Tableau2[[Code Article]:[DATE INVENTAIRE]],11,FALSE) -> 46224
A29: FIXTCUIPOTBOIS9MXXX | B29: 9M 140/160MM WOODEN POLES | C29: 14 | D29: 45951 | E29: =VLOOKUP(A29,Tableau2[[Code Article]:[DATE INVENTAIRE]],11,FALSE) -> 46219 | F29: =VLOOKUP(A29,SORTIE!$A$2:$C$456,3,FALSE) -> #N/A
A30: SIM DROP ABONNE | B30: ABONNE DROP 128K JAVA | C30: 1 | D30: 45785 | E30: =VLOOKUP(A30,Tableau2[[Code Article]:[DATE INVENTAIRE]],11,FALSE) -> 46219 | F30: =VLOOKUP(A30,SORTIE!$A$2:$C$456,3,FALSE) -> 1
A31: ISHLACCLAMTUBERC | B31: ACCESSOIRE LAMPE | C31: 1 | D31: 17/07/25 au 28/08/25 | E31: =VLOOKUP(A31,Tableau2[[Code Article]:[DATE INVENTAIRE]],11,FALSE) -> 46219 | F31: =VLOOKUP(A31,SORTIE!$A$2:$C$456,3,FALSE) -> 1
A32: TMXTACCRCK42UXXX | B32: ACCESSOIRE RACK | C32: 14 | D32: 22/05/25 au 03/03/26 | E32: =VLOOKUP(A32,Tableau2[[Code Article]:[DATE INVENTAIRE]],11,FALSE) -> 46219 | F32: =VLOOKUP(A32,SORTIE!$A$2:$C$456,3,FALSE) -> #N/A
A33: TGSMACU01XXXXERK | B33: ACCU 01 | C33: 1 | D33: 45776 | E33: =VLOOKUP(A33,Tableau2[[Code Article]:[DATE INVENTAIRE]],11,FALSE) -> 46219 | F33: =VLOOKUP(A33,SORTIE!$A$2:$C$456,3,FALSE) -> #N/A
A34: NMXTBAT12V210NSB | B34: ACCUMULATOR/NSB RED 210 (4x12V) 210Ah BKC90106/155 | C34: 16 | D34: 45951 | E34: =VLOOKUP(A34,Tableau2[[Code Article]:[DATE INVENTAIRE]],11,FALSE) -> 46224
A35: TMXTREBD3EGENXXX | B35: ADAPTEUR | C35: 262 | D35: 45951 | E35: =VLOOKUP(A35,Tableau2[[Code Article]:[DATE INVENTAIRE]],11,FALSE) -> 46216
A36: TFHXCHSADR25ESGM | B36: ADR 2500 EXTRA | C36: 11 | D36: 45988 | E36: =VLOOKUP(A36,Tableau2[[Code Article]:[DATE INVENTAIRE]],11,FALSE) -> 46219 | F36: =VLOOKUP(A36,SORTIE!$A$2:$C$456,3,FALSE) -> #N/A
A37: TMXTFANADR155SGM | B37: ADR-SAGEM 155C | C37: 15 | D37: 08/04/25 au 21/08/25 | E37: =VLOOKUP(A37,Tableau2[[Code Article]:[DATE INVENTAIRE]],11,FALSE) -> 46218
A38: MPRT0000042620XXX | B38: AFFICHE 40X60CM | C38: 2084 | D38: 13/05/25 au 06/11/25 | E38: =VLOOKUP(A38,Tableau2[[Code Article]:[DATE INVENTAIRE]],11,FALSE) -> 46224
A39: MPRT000004123XXX | B39: AFFICHE 90X40CM | C39: 101 | D39: 45776 | E39: =VLOOKUP(A39,Tableau2[[Code Article]:[DATE INVENTAIRE]],11,FALSE) -> 46224
A40: MGDIAGRAPH001XXX | B40: AGRAPHEUSE | C40: 2 | D40: 45951 | E40: =VLOOKUP(A40,Tableau2[[Code Article]:[DATE INVENTAIRE]],11,FALSE) -> 46216
A41: TC08CBLALABOXHAW | B41: ALARM PANEL | C41: 1 | D41: 45951 | E41: =VLOOKUP(A41,Tableau2[[Code Article]:[DATE INVENTAIRE]],11,FALSE) -> 46224
A42: TMXTDTCINCENDXXX | B42: ALARME INCENDIE | C42: 32 | D42: 45776 | E42: =VLOOKUP(A42,Tableau2[[Code Article]:[DATE INVENTAIRE]],11,FALSE) -> 46224
A43: TIPMRTR7705XXALC | B43: ALCATEL- LUCENT I-10G-U | C43: 79 | D43: 45951 | E43: =VLOOKUP(A43,Tableau2[[Code Article]:[DATE INVENTAIRE]],11,FALSE) -> 46218
A44: TMXTPCDTCHMOTXXX | B44: AMORTISSEURS | C44: 2 | D44: 45951 | E44: =VLOOKUP(A44,Tableau2[[Code Article]:[DATE INVENTAIRE]],11,FALSE) -> 46225
A45: QUINLUMAE274WXXX | B45: AMPOULE | C45: 14 | D45: 45988 | E45: =VLOOKUP(A45,Tableau2[[Code Article]:[DATE INVENTAIRE]],11,FALSE) -> 46219 | F45: =VLOOKUP(A45,SORTIE!$A$2:$C$456,3,FALSE) -> #N/A
A46: TMXTPCDTCHMOTXXX | B46: AMPOULES | C46: 8 | D46: 08/04/25 au 21/08/25 | E46: =VLOOKUP(A46,Tableau2[[Code Article]:[DATE INVENTAIRE]],11,FALSE) -> 46225
A47: AMOIFAICHAXXXXXX | B47: ANCIENNE CHAISES BAR HS | C47: 109 | D47: 13/05/25 au 06/11/25 | E47: =VLOOKUP(A47,Tableau2[[Code Article]:[DATE INVENTAIRE]],11,FALSE) -> 46224
A48: TFHMSUPANB237ERC | B48: Ant Side Strut B 2.4/3.0/3.7 | C48: 12 | D48: 45776 | E48: =VLOOKUP(A48,Tableau2[[Code Article]:[DATE INVENTAIRE]],11,FALSE) -> 46219 | F48: =VLOOKUP(A48,SORTIE!$A$2:$C$456,3,FALSE) -> 10
A49: TGSMANT3BX790ERK | B49: ANT_PENTA_AMPHENOL | C49: 17 | D49: 45951 | E49: =VLOOKUP(A49,Tableau2[[Code Article]:[DATE INVENTAIRE]],11,FALSE) -> 46224
A50: TGSMANT0378HPERC | B50: ANT0 3.0 7/8 HP | C50: 2 | D50: 45951 | E50: =VLOOKUP(A50,Tableau2[[Code Article]:[DATE INVENTAIRE]],11,FALSE) -> 46219 | F50: =VLOOKUP(A50,SORTIE!$A$2:$C$456,3,FALSE) -> 2
A51: TGSMANT2178HPERK | B51: ANT2 1.8 7/8 HP | C51: 145 | D51: 04/09/25 au 12/02/26 | E51: =VLOOKUP(A51,Tableau2[[Code Article]:[DATE INVENTAIRE]],11,FALSE) -> 46224
A52: TFHMANT30315HERC | B52: ANTENNE 3 A 0.3 15 HP_BFZ62231/3S05H | C52: 46 | D52: 25/03/25 au 23/12/25 | E52: =VLOOKUP(A52,Tableau2[[Code Article]:[DATE INVENTAIRE]],11,FALSE) -> 46224
A53: TGSMANT21278HERC | B53: ANT3 A 1.2 7/8 HP_BFZ62234/3S02H | C53: 250 | D53: 13/05/25 au 06/11/25 | E53: =VLOOKUP(A53,Tableau2[[Code Article]:[DATE INVENTAIRE]],11,FALSE) -> 46224
A54: TGSMANT31L126ERC | B54: ANTENNA 3000 1L 1M 2.6M/XXPol Panel 790 960/1710 2690 65¦/65¦ 17/18.5dBi 0¦ 10¦/0¦ 6¦T | C54: 5 | D54: 45785 | E54: =VLOOKUP(A54,Tableau2[[Code Article]:[DATE INVENTAIRE]],11,FALSE) -> 46224
A55: TGSMANTDBC2HXERC | B55: ANTENNA DUAL COLUMN BAND 2H_6177108NG | C55: 58 | D55: 09/01/2025 au 18/09/25 | E55: =VLOOKUP(A55,Tableau2[[Code Article]:[DATE INVENTAIRE]],11,FALSE) -> 46224
A56: TFHXSUPAN1218XXX | B56: ANTENNA SUPPORT FOR 120CM/180CM | C56: 13 | D56: 16/01/25 au 30/12/25 | E56: =VLOOKUP(A56,Tableau2[[Code Article]:[DATE INVENTAIRE]],11,FALSE) -> 46219 | F56: =VLOOKUP(A56,SORTIE!$A$2:$C$456,3,FALSE) -> #N/A
A57: TGSMANTTC3HXXERC | B57: ANTENNA TRIPLE COLUMN 3H_6177488G | C57: 15 | D57: 14/01/25 au 09/12/25 | E57: =VLOOKUP(A57,Tableau2[[Code Article]:[DATE INVENTAIRE]],11,FALSE) -> 46224
A58: TGSMANTM0915HERC | B58: ANTENNA/ANTm 0.9 15 HP/HPX | C58: 42 | D58: 45937 | E58: =VLOOKUP(A58,Tableau2[[Code Article]:[DATE INVENTAIRE]],11,FALSE) -> 46224
A59: TGSMANT2478HPERK | B59: ANTENNE 2.4 | C59: 55 | D59: 13/05/25 au 21/08/25 | E59: =VLOOKUP(A59,Tableau2[[Code Article]:[DATE INVENTAIRE]],11,FALSE) -> 46224
A60: MDIV000000354XXX | B60: ANTENNE 2STUCK LAT 56 DUO SET | C60: 1 | D60: 09/01/25 au 24/02/26 | E60: =VLOOKUP(A60,Tableau2[[Code Article]:[DATE INVENTAIRE]],11,FALSE) -> 46224
A61: ANTINDOORHUAWEI | B61: ANTENNE CDMA | C61: 3 | D61: 16/01/25 au 24/03/26 | E61: =VLOOKUP(A61,Tableau2[[Code Article]:[DATE INVENTAIRE]],11,FALSE) -> 46224
A62: TGSMANT3BX790ERK | B62: ANTENNE Triple band antenna,XX | C62: 40 | D62: 16/01/25 au 10/04/25 | E62: =VLOOKUP(A62,Tableau2[[Code Article]:[DATE INVENTAIRE]],11,FALSE) -> 46224
A63: ISPTISPANT519120UBI | B63: ANTENNE UBIQUITI | C63: 9 | D63: 22/05/25 au 03/03/26 | E63: =VLOOKUP(A63,Tableau2[[Code Article]:[DATE INVENTAIRE]],11,FALSE) -> 46218
A64: TGSMANTDB8790ERC | B64: ANTENNE X/X-pol,790-960/1710-2170MHz,65/65deg,17.5/19.5dBiMET0-8 | C64: 9 | D64: 08/05/25 au 24/02/26 | E64: =VLOOKUP(A64,Tableau2[[Code Article]:[DATE INVENTAIRE]],11,FALSE) -> 46224
A65: TGSMANTSB1790ERK | B65: ANTENNE X-pol.790-960MHz,65deg | C65: 57 | D65: 11/03/25 au 12/06/25 | E65: =VLOOKUP(A65,Tableau2[[Code Article]:[DATE INVENTAIRE]],11,FALSE) -> 46224
A66: TGSMANTSECDBDERK | B66: ANTENNES SECTORIELLES DOUBLE | C66: 27 | D66: 45951 | E66: =VLOOKUP(A66,Tableau2[[Code Article]:[DATE INVENTAIRE]],11,FALSE) -> 46224
A67: TGSMANTSECSBDERK | B67: ANTENNES SECTORIELLES SINGLE | C67: 100 | D67: 45988 | E67: =VLOOKUP(A67,Tableau2[[Code Article]:[DATE INVENTAIRE]],11,FALSE) -> 46224
A68: TMXTACSUAPPROUBT | B68: AP AC MESH PRO | C68: 20 | D68: 10/04/25 et 06/05/25 | E68: =VLOOKUP(A68,Tableau2[[Code Article]:[DATE INVENTAIRE]],11,FALSE) -> 46219
A69: MPLV000002824XXX | B69: ARCHE GONFLABLE ANIMATION-500X350 CM DIAM 80 CM-JUIN 2023 | C69: 58 | D69: 46084 | E69: =VLOOKUP(A69,Tableau2[[Code Article]:[DATE INVENTAIRE]],11,FALSE) -> 46219 | F69: =VLOOKUP(A69,SORTIE!$A$2:$C$456,3,FALSE) -> #N/A
A70: AMOIARM2PRT2XXXX | B70: ARMOIRE | C70: 41 | D70: 05/02/25 au 19/05/26 | E70: =VLOOKUP(A70,Tableau2[[Code Article]:[DATE INVENTAIRE]],11,FALSE) -> 46218
A71: FIXTCUIARM06X112GEK | B71: ARMOIRE DE RUE (SR) | C71: 9 | D71: 16/01/25 au 30/12/25 | E71: =VLOOKUP(A71,Tableau2[[Code Article]:[DATE INVENTAIRE]],11,FALSE) -> 46216
A72: TGSMACCGBFBBSERC | B72: ASSEMBLED PARTS/Generic base frame | C72: 2 | D72: 14/01/25 au 09/12/25 | E72: =VLOOKUP(A72,Tableau2[[Code Article]:[DATE INVENTAIRE]],11,FALSE) -> 46219 | F72: =VLOOKUP(A72,SORTIE!$A$2:$C$456,3,FALSE) -> #N/A
A73: TMXTREBD3EGENXXX | B73: ASTEC 23160 | C73: 1 | D73: 45937 | E73: =VLOOKUP(A73,Tableau2[[Code Article]:[DATE INVENTAIRE]],11,FALSE) -> 46216
A74: TMXTREBD3EGENXXX | B74: ASTEC E132002 | C74: 1 | D74: 13/05/25 au 21/08/25 | E74: =VLOOKUP(A74,Tableau2[[Code Article]:[DATE INVENTAIRE]],11,FALSE) -> 46216
A75: WIPC409HD | B75: AZTECH | C75: 39 | D75: 09/01/25 au 24/02/26 | E75: =VLOOKUP(A75,Tableau2[[Code Article]:[DATE INVENTAIRE]],11,FALSE) -> 46224
A76: TMXTACCPOUBELXXX | B76: BAC A ORDURE | C76: 2 | D76: 16/01/25 au 24/03/26 | E76: =VLOOKUP(A76,Tableau2[[Code Article]:[DATE INVENTAIRE]],11,FALSE) -> 46224
A77: FRNBBACRANGXXXX | B77: BAC A PAPIER | C77: 8 | D77: 16/01/25 au 10/04/25 | E77: =VLOOKUP(A77,Tableau2[[Code Article]:[DATE INVENTAIRE]],11,FALSE) -> 46224
A78: TMXTBACHEPROTXXX | B78: BACHE | C78: 40 | D78: 22/05/25 au 03/03/26 | E78: =VLOOKUP(A78,Tableau2[[Code Article]:[DATE INVENTAIRE]],11,FALSE) -> 46216
A79: MPLV000004019XXX | B79: FLAG | C79: 89 | D79: 08/05/25 au 24/02/26 | E79: =VLOOKUP(A79,Tableau2[[Code Article]:[DATE INVENTAIRE]],11,FALSE) -> 46224
A80: MGDI000004052XXX | B80: BANDEAU | C80: 19 | D80: 11/03/25 au 12/06/25 | E80: =VLOOKUP(A80,Tableau2[[Code Article]:[DATE INVENTAIRE]],11,FALSE) -> 46216
A81: MDIV000004172XXX | B81: BARIL BLEU 250L | C81: 4 | D81: 45951 | E81: =VLOOKUP(A81,Tableau2[[Code Article]:[DATE INVENTAIRE]],11,FALSE) -> 46216
A82: OUTILTECBARMINLO | B82: BARRE A MINE | C82: 1 | D82: 45988 | E82: =VLOOKUP(A82,Tableau2[[Code Article]:[DATE INVENTAIRE]],11,FALSE) -> 46219 | F82: =VLOOKUP(A82,SORTIE!$A$2:$C$456,3,FALSE) -> #N/A
A83: TMXTPCDTCHMOTXXX | B83: BARRE DE TORSION | C83: 1 | D83: 10/04/25 et 06/05/25 | E83: =VLOOKUP(A83,Tableau2[[Code Article]:[DATE INVENTAIRE]],11,FALSE) -> 46225
A84: IGCVCFCBF6301XXX | B84: BASE FRAME | C84: 22 | D84: 46084 | E84: =VLOOKUP(A84,Tableau2[[Code Article]:[DATE INVENTAIRE]],11,FALSE) -> 46216
A85: TGSMCRTBB5212ERC | B85: Baseband 5212 Digital Unit KDU137925 41 | C85: 2 | D85: 30/01/25 au 18/02/25 | E85: =VLOOKUP(A85,Tableau2[[Code Article]:[DATE INVENTAIRE]],11,FALSE) -> 46216
A86: TGSMPROBB5216ERC | B86: BASEBAND 5216 | C86: 3 | D86: 13/02/25 au 10/04/25 | E86: =VLOOKUP(A86,Tableau2[[Code Article]:[DATE INVENTAIRE]],11,FALSE) -> 46216
A87: TGSMCRTBB6620ERC | B87: BASEBAND 6620 | C87: 10 | D87: 03/04/25 au 22/05/25 | E87: =VLOOKUP(A87,Tableau2[[Code Article]:[DATE INVENTAIRE]],11,FALSE) -> 46216
A88: NMXTBAT12V100NRD | B88: BATTERIE NARADA 12V100AH | C88: 135 | D88: 29/04/25 au 03/02/26 | E88: =VLOOKUP(A88,Tableau2[[Code Article]:[DATE INVENTAIRE]],11,FALSE) -> 46224
A89: NMXTBAT12V12APWR | B89: BATTERIE 12V 12Ah POWERSAFE | C89: 4 | D89: 45694 | E89: =VLOOKUP(A89,Tableau2[[Code Article]:[DATE INVENTAIRE]],11,FALSE) -> 46224
A90: NMXTBAT12V190XXX | B90: BATTERIE 12V 190AH | C90: 40 | D90: 16/01/25 au 30/12/25 | E90: =VLOOKUP(A90,Tableau2[[Code Article]:[DATE INVENTAIRE]],11,FALSE) -> 46219
A91: NMXTBAT12V59ANRS | B91: BATTERIE 12V 59Ah NORTH STAR | C91: 4 | D91: 14/01/25 au 09/12/25 | E91: =VLOOKUP(A91,Tableau2[[Code Article]:[DATE INVENTAIRE]],11,FALSE) -> 46224
A92: NMXTBAT12V05AXXX | B92: BATTERIE 12V 5AH | C92: 36 | D92: 45937 | E92: =VLOOKUP(A92,Tableau2[[Code Article]:[DATE INVENTAIRE]],11,FALSE) -> 46224
A93: NMXTBAT12V150XXX | B93: BATTERIE 12V150AH | C93: 36 | D93: 13/05/25 au 21/08/25 | E93: =VLOOKUP(A93,Tableau2[[Code Article]:[DATE INVENTAIRE]],11,FALSE) -> 46224
A94: NMXTBAT1500AHXXX | B94: BATTERIE 1500AH (EOS1500) | C94: 48 | D94: 09/01/25 au 24/02/26 | E94: =VLOOKUP(A94,Tableau2[[Code Article]:[DATE INVENTAIRE]],11,FALSE) -> 46224
A95: NMXTBAT2V500ASLE | B95: BATTERIE 2V380AH | C95: 24 | D95: 16/01/25 au 24/03/26 | E95: =VLOOKUP(A95,Tableau2[[Code Article]:[DATE INVENTAIRE]],11,FALSE) -> 46224
A96: NMXTBAT6V200AXXX | B96: BATTERIE 6V 200AH (EL-S4-0002) | C96: 192 | D96: 16/01/25 au 10/04/25 | E96: =VLOOKUP(A96,Tableau2[[Code Article]:[DATE INVENTAIRE]],11,FALSE) -> 46224
A97: NMXTBAT12V170ERC | B97: BATTERIE MARATHON 12V 180AH | C97: 24 | D97: 22/05/25 au 03/03/26 | E97: =VLOOKUP(A97,Tableau2[[Code Article]:[DATE INVENTAIRE]],11,FALSE) -> 46224
A98: NMXTBAT2V70PZXXX | B98: BATTERIE NARADA OPzS490 | C98: 215 | D98: 08/05/25 au 24/02/26 | E98: =VLOOKUP(A98,Tableau2[[Code Article]:[DATE INVENTAIRE]],11,FALSE) -> 46224
A99: NMXTBAT12V100PWR | B99: BATTERIE NORTH STAR 12V100AH | C99: 47 | D99: 11/03/25 au 12/06/25 | E99: =VLOOKUP(A99,Tableau2[[Code Article]:[DATE INVENTAIRE]],11,FALSE) -> 46218
A100: NMXTBAT48V100NSB | B100: BATTERIE SET 48V/100Ah NSB Silver FT - BKC90161/1 | C100: 96 | D100: 45951 | E100: =VLOOKUP(A100,Tableau2[[Code Article]:[DATE INVENTAIRE]],11,FALSE) -> 46224
...

Sheet ARTICLES SAGE
A1: Code Article | B1: descriptions | C1: STOCK FIN DECEMBRE 2024 SAGE | D1: SKU | E1: Entrée 01 Janv 2025 au 10 juillet 2026 | F1: sortie 01 Janv 2025 au 10 juillet 2026 | G1: stock final au 10 juillet 2026 | H1: inventaire juillet 2026 | I1: écart (I-J) | J1: Explications des Ecarts | K1: DATE INVENTAIRE | L1: ENTREE LE 23/07/26 AU 14/07/26 | M1: SORTIE 23/07/26 AU 14/10/26
A2: TGSMANTX3B806XXX | B2: Antenna triple band Antenna XX | C2: 3 | D2: PIE | E2: 0 | F2: 0 | G2: =Tableau2[[#This Row],[STOCK FIN DECEMBRE 2024 SAGE]]+Tableau2[[#This Row],[Entrée 01 Janv 2025 au 10 juillet 2026]]-Tableau2[[#This Row],[sortie 01 Janv 2025 au 10 juillet 2026]] -> 3 | I2: =Tableau2[[#This Row],[inventaire juillet 2026 ]]-Tableau2[[#This Row],[stock final au 10 juillet 2026]] -> -3 | K2: 46224 | L2: =VLOOKUP(Tableau2[[#This Row],[Code Article]],'ENTREE APRES INV'!A1:F1010,6,0) -> #N/A | M2: =VLOOKUP(Tableau2[[#This Row],[Code Article]],'SORTIE APRES INV'!A1:D411,4,0) -> #N/A
A3: TCDMCBLPDRW14XXX | B3: Power Distribution Rack,W14A3Z | C3: 3 | D3: PIE | E3: 0 | F3: 0 | G3: =Tableau2[[#This Row],[STOCK FIN DECEMBRE 2024 SAGE]]+Tableau2[[#This Row],[Entrée 01 Janv 2025 au 10 juillet 2026]]-Tableau2[[#This Row],[sortie 01 Janv 2025 au 10 juillet 2026]] -> 3 | H3: 3 | I3: =Tableau2[[#This Row],[inventaire juillet 2026 ]]-Tableau2[[#This Row],[stock final au 10 juillet 2026]] -> 0 | K3: 46224 | L3: =VLOOKUP(Tableau2[[#This Row],[Code Article]],'ENTREE APRES INV'!A2:F1011,6,0) -> #N/A | M3: =VLOOKUP(Tableau2[[#This Row],[Code Article]],'SORTIE APRES INV'!A2:D412,4,0) -> #N/A
A4: TCUIBMX56PVIDGEK | B4: Bmx 56 paires (vide) | C4: 2 | D4: PIE | E4: =VLOOKUP(Tableau2[[#This Row],[Code Article]],ENTREE!A59:C755,3,FALSE) -> 9 | F4: 0 | G4: =Tableau2[[#This Row],[STOCK FIN DECEMBRE 2024 SAGE]]+Tableau2[[#This Row],[Entrée 01 Janv 2025 au 10 juillet 2026]]-Tableau2[[#This Row],[sortie 01 Janv 2025 au 10 juillet 2026]] -> 11 | H4: 11 | I4: =Tableau2[[#This Row],[inventaire juillet 2026 ]]-Tableau2[[#This Row],[stock final au 10 juillet 2026]] -> 0 | K4: 46216 | L4: =VLOOKUP(Tableau2[[#This Row],[Code Article]],'ENTREE APRES INV'!A3:F1012,6,0) -> #N/A | M4: =VLOOKUP(Tableau2[[#This Row],[Code Article]],'SORTIE APRES INV'!A3:D413,4,0) -> #N/A
A5: TGSMANTXPL84XERK | B5: ANTENNA XPOL C-PANEL 806-960/8 | C5: 2 | D5: PIE | E5: 0 | F5: =+SORTIE!C47 -> 2 | G5: =Tableau2[[#This Row],[STOCK FIN DECEMBRE 2024 SAGE]]+Tableau2[[#This Row],[Entrée 01 Janv 2025 au 10 juillet 2026]]-Tableau2[[#This Row],[sortie 01 Janv 2025 au 10 juillet 2026]] -> 0 | I5: =Tableau2[[#This Row],[inventaire juillet 2026 ]]-Tableau2[[#This Row],[stock final au 10 juillet 2026]] -> 0 | K5: 46224 | L5: =VLOOKUP(Tableau2[[#This Row],[Code Article]],'ENTREE APRES INV'!A4:F1013,6,0) -> #N/A | M5: =VLOOKUP(Tableau2[[#This Row],[Code Article]],'SORTIE APRES INV'!A4:D414,4,0) -> #N/A
A6: TGSMANTDBC2HXERC | B6: ANTENNA DUAL COLUMN BAND 2H_61 | C6: 9 | D6: PIE | E6: =+ENTREE!C55 -> 58 | F6: =+SORTIE!C46 -> 58 | G6: =Tableau2[[#This Row],[STOCK FIN DECEMBRE 2024 SAGE]]+Tableau2[[#This Row],[Entrée 01 Janv 2025 au 10 juillet 2026]]-Tableau2[[#This Row],[sortie 01 Janv 2025 au 10 juillet 2026]] -> 9 | H6: 9 | I6: =Tableau2[[#This Row],[inventaire juillet 2026 ]]-Tableau2[[#This Row],[stock final au 10 juillet 2026]] -> 0 | K6: 46224 | L6: =VLOOKUP(Tableau2[[#This Row],[Code Article]],'ENTREE APRES INV'!A5:F1014,6,0) -> #N/A | M6: =VLOOKUP(Tableau2[[#This Row],[Code Article]],'SORTIE APRES INV'!A5:D415,4,0) -> #N/A
A7: TCUIPEKR5XXXXGEK | B7: Peca R5 | C7: 1 | D7: PIE | E7: =+ENTREE!C683 -> 34 | F7: 0 | G7: =Tableau2[[#This Row],[STOCK FIN DECEMBRE 2024 SAGE]]+Tableau2[[#This Row],[Entrée 01 Janv 2025 au 10 juillet 2026]]-Tableau2[[#This Row],[sortie 01 Janv 2025 au 10 juillet 2026]] -> 35 | H7: 35 | I7: =Tableau2[[#This Row],[inventaire juillet 2026 ]]-Tableau2[[#This Row],[stock final au 10 juillet 2026]] -> 0 | K7: 46224 | L7: =VLOOKUP(Tableau2[[#This Row],[Code Article]],'ENTREE APRES INV'!A6:F1015,6,0) -> #N/A | M7: =VLOOKUP(Tableau2[[#This Row],[Code Article]],'SORTIE APRES INV'!A6:D416,4,0) -> #N/A
A8: TFOXCBLS2FMUAPHO | B8: CABLE 2FO SM MULTI-USAGE G657 | C8: 258 | D8: PIE | E8: =VLOOKUP(Tableau2[[#This Row],[Code Article]],ENTREE!A68:C780,3,FALSE) -> 837 | F8: =VLOOKUP(Tableau2[[#This Row],[Code Article]],SORTIE!A75:C580,3,FALSE) -> 1095 | G8: =Tableau2[[#This Row],[STOCK FIN DECEMBRE 2024 SAGE]]+Tableau2[[#This Row],[Entrée 01 Janv 2025 au 10 juillet 2026]]-Tableau2[[#This Row],[sortie 01 Janv 2025 au 10 juillet 2026]] -> 0 | I8: =Tableau2[[#This Row],[inventaire juillet 2026 ]]-Tableau2[[#This Row],[stock final au 10 juillet 2026]] -> 0 | K8: 46224 | L8: =VLOOKUP(Tableau2[[#This Row],[Code Article]],'ENTREE APRES INV'!A7:F1016,6,0) -> #N/A | M8: =VLOOKUP(Tableau2[[#This Row],[Code Article]],'SORTIE APRES INV'!A7:D417,4,0) -> #N/A
A9: TGSMANT06PPB2XXX | B9: 6-Port Antenna LB/2HB 2,7m 845 | C9: 47 | D9: PIE | E9: 86 | F9: 133 | G9: =Tableau2[[#This Row],[STOCK FIN DECEMBRE 2024 SAGE]]+Tableau2[[#This Row],[Entrée 01 Janv 2025 au 10 juillet 2026]]-Tableau2[[#This Row],[sortie 01 Janv 2025 au 10 juillet 2026]] -> 0 | I9: =Tableau2[[#This Row],[inventaire juillet 2026 ]]-Tableau2[[#This Row],[stock final au 10 juillet 2026]] -> 0 | K9: 46224 | L9: =VLOOKUP(Tableau2[[#This Row],[Code Article]],'ENTREE APRES INV'!A8:F1017,6,0) -> #N/A | M9: =VLOOKUP(Tableau2[[#This Row],[Code Article]],'SORTIE APRES INV'!A8:D418,4,0) -> #N/A
A10: TCS3RCKOSS2XXXXX | B10: Rack OSS2 | C10: 1 | D10: PIE | E10: 0 | F10: 0 | G10: =Tableau2[[#This Row],[STOCK FIN DECEMBRE 2024 SAGE]]+Tableau2[[#This Row],[Entrée 01 Janv 2025 au 10 juillet 2026]]-Tableau2[[#This Row],[sortie 01 Janv 2025 au 10 juillet 2026]] -> 1 | H10: 1 | I10: =Tableau2[[#This Row],[inventaire juillet 2026 ]]-Tableau2[[#This Row],[stock final au 10 juillet 2026]] -> 0 | K10: 46224 | L10: =VLOOKUP(Tableau2[[#This Row],[Code Article]],'ENTREE APRES INV'!A9:F1018,6,0) -> #N/A | M10: =VLOOKUP(Tableau2[[#This Row],[Code Article]],'SORTIE APRES INV'!A9:D419,4,0) -> #N/A
A11: TCUICBL98X056GEK | B11: Câble 98-056-6 | C11: 254 | D11: PIE | E11: 158 | F11: 0 | G11: =Tableau2[[#This Row],[STOCK FIN DECEMBRE 2024 SAGE]]+Tableau2[[#This Row],[Entrée 01 Janv 2025 au 10 juillet 2026]]-Tableau2[[#This Row],[sortie 01 Janv 2025 au 10 juillet 2026]] -> 412 | H11: 412 | I11: =Tableau2[[#This Row],[inventaire juillet 2026 ]]-Tableau2[[#This Row],[stock final au 10 juillet 2026]] -> 0 | K11: 46216 | L11: =VLOOKUP(Tableau2[[#This Row],[Code Article]],'ENTREE APRES INV'!A10:F1019,6,0) -> #N/A | M11: =VLOOKUP(Tableau2[[#This Row],[Code Article]],'SORTIE APRES INV'!A10:D420,4,0) -> #N/A
A12: TCUICBLNEO599GEK | B12: Câble néoprène 5/99 | C12: 7657 | D12: PIE | E12: =VLOOKUP(Tableau2[[#This Row],[Code Article]],ENTREE!A2:C588,3,FALSE) -> 14650 | F12: =VLOOKUP(Tableau2[[#This Row],[Code Article]],SORTIE!A3:C386,3,FALSE) -> 22307 | G12: =Tableau2[[#This Row],[STOCK FIN DECEMBRE 2024 SAGE]]+Tableau2[[#This Row],[Entrée 01 Janv 2025 au 10 juillet 2026]]-Tableau2[[#This Row],[sortie 01 Janv 2025 au 10 juillet 2026]] -> 0 | H12: 0 | I12: =Tableau2[[#This Row],[inventaire juillet 2026 ]]-Tableau2[[#This Row],[stock final au 10 juillet 2026]] -> 0 | K12: 46224 | L12: =VLOOKUP(Tableau2[[#This Row],[Code Article]],'ENTREE APRES INV'!A11:F1020,6,0) -> 50 | M12: =VLOOKUP(Tableau2[[#This Row],[Code Article]],'SORTIE APRES INV'!A11:D421,4,0) -> #N/A
A13: TFHXCBLCONTNCNEK | B13: CONNECTEUR | C13: 8 | D13: PIE | E13: 1074 | F13: =VLOOKUP(Tableau2[[#This Row],[Code Article]],SORTIE!A4:C387,3,FALSE) -> 1532 | G13: =Tableau2[[#This Row],[STOCK FIN DECEMBRE 2024 SAGE]]+Tableau2[[#This Row],[Entrée 01 Janv 2025 au 10 juillet 2026]]-Tableau2[[#This Row],[sortie 01 Janv 2025 au 10 juillet 2026]] -> -450 | H13: 62 | I13: =Tableau2[[#This Row],[inventaire juillet 2026 ]]-Tableau2[[#This Row],[stock final au 10 juillet 2026]] -> 512 | K13: 46216 | L13: =VLOOKUP(Tableau2[[#This Row],[Code Article]],'ENTREE APRES INV'!A12:F1021,6,0) -> #N/A | M13: =VLOOKUP(Tableau2[[#This Row],[Code Article]],'SORTIE APRES INV'!A12:D422,4,0) -> #N/A
A14: TFOXCBLOP12STXXX | B14: CABLE OPTIQUE 12FO SOUS TERRAI | C14: 91 | D14: PIE | E14: =VLOOKUP(Tableau2[[#This Row],[Code Article]],ENTREE!A3:C590,3,FALSE) -> 2497 | F14: =VLOOKUP(Tableau2[[#This Row],[Code Article]],SORTIE!A5:C388,3,FALSE) -> 2588 | G14: =Tableau2[[#This Row],[STOCK FIN DECEMBRE 2024 SAGE]]+Tableau2[[#This Row],[Entrée 01 Janv 2025 au 10 juillet 2026]]-Tableau2[[#This Row],[sortie 01 Janv 2025 au 10 juillet 2026]] -> 0 | I14: =Tableau2[[#This Row],[inventaire juillet 2026 ]]-Tableau2[[#This Row],[stock final au 10 juillet 2026]] -> 0 | K14: 46224 | L14: =VLOOKUP(Tableau2[[#This Row],[Code Article]],'ENTREE APRES INV'!A13:F1022,6,0) -> #N/A | M14: =VLOOKUP(Tableau2[[#This Row],[Code Article]],'SORTIE APRES INV'!A13:D423,4,0) -> #N/A
A15: TFOXCBLR2FOXXNEX | B15: SP1799 - CABLE DE RACCORDEMENT | C15: 241 | D15: PIE | E15: 0 | F15: 0 | G15: =Tableau2[[#This Row],[STOCK FIN DECEMBRE 2024 SAGE]]+Tableau2[[#This Row],[Entrée 01 Janv 2025 au 10 juillet 2026]]-Tableau2[[#This Row],[sortie 01 Janv 2025 au 10 juillet 2026]] -> 241 | H15: 241 | I15: =Tableau2[[#This Row],[inventaire juillet 2026 ]]-Tableau2[[#This Row],[stock final au 10 juillet 2026]] -> 0 | K15: 46224 | L15: =VLOOKUP(Tableau2[[#This Row],[Code Article]],'ENTREE APRES INV'!A14:F1023,6,0) -> #N/A | M15: =VLOOKUP(Tableau2[[#This Row],[Code Article]],'SORTIE APRES INV'!A14:D424,4,0) -> #N/A
A16: TFOXOUTPM3921XXX | B16: Pince à dénuder la gaine et la | C16: 14 | D16: PIE | E16: 0 | F16: 0 | G16: =Tableau2[[#This Row],[STOCK FIN DECEMBRE 2024 SAGE]]+Tableau2[[#This Row],[Entrée 01 Janv 2025 au 10 juillet 2026]]-Tableau2[[#This Row],[sortie 01 Janv 2025 au 10 juillet 2026]] -> 14 | H16: 14 | I16: =Tableau2[[#This Row],[inventaire juillet 2026 ]]-Tableau2[[#This Row],[stock final au 10 juillet 2026]] -> 0 | K16: 46224 | L16: =VLOOKUP(Tableau2[[#This Row],[Code Article]],'ENTREE APRES INV'!A15:F1024,6,0) -> #N/A | M16: =VLOOKUP(Tableau2[[#This Row],[Code Article]],'SORTIE APRES INV'!A15:D425,4,0) -> #N/A
A17: TFOXSUPPLSPT1XXX | B17: Support plastique special pote | C17: 1 | D17: PIE | E17: 0 | F17: 0 | G17: =Tableau2[[#This Row],[STOCK FIN DECEMBRE 2024 SAGE]]+Tableau2[[#This Row],[Entrée 01 Janv 2025 au 10 juillet 2026]]-Tableau2[[#This Row],[sortie 01 Janv 2025 au 10 juillet 2026]] -> 1 | H17: 1 | I17: =Tableau2[[#This Row],[inventaire juillet 2026 ]]-Tableau2[[#This Row],[stock final au 10 juillet 2026]] -> 0 | K17: 46225 | L17: =VLOOKUP(Tableau2[[#This Row],[Code Article]],'ENTREE APRES INV'!A16:F1025,6,0) -> #N/A | M17: =VLOOKUP(Tableau2[[#This Row],[Code Article]],'SORTIE APRES INV'!A16:D426,4,0) -> #N/A
A18: TGSMACCRETU3GERC | B18: RETU for Kathrein antennas, 3GPP | C18: 9 | D18: PIE | E18: =VLOOKUP(Tableau2[[#This Row],[Code Article]],ENTREE!A5:C594,3,FALSE) -> 93 | F18: =VLOOKUP(Tableau2[[#This Row],[Code Article]],SORTIE!A8:C392,3,FALSE) -> 87 | G18: =Tableau2[[#This Row],[STOCK FIN DECEMBRE 2024 SAGE]]+Tableau2[[#This Row],[Entrée 01 Janv 2025 au 10 juillet 2026]]-Tableau2[[#This Row],[sortie 01 Janv 2025 au 10 juillet 2026]] -> 15 | H18: 15 | I18: =Tableau2[[#This Row],[inventaire juillet 2026 ]]-Tableau2[[#This Row],[stock final au 10 juillet 2026]] -> 0 | K18: 46224 | L18: =VLOOKUP(Tableau2[[#This Row],[Code Article]],'ENTREE APRES INV'!A17:F1026,6,0) -> #N/A | M18: =VLOOKUP(Tableau2[[#This Row],[Code Article]],'SORTIE APRES INV'!A17:D427,4,0) -> #N/A
A19: INFODISQUEDURXXX | B19: DISQUE DUR | C19: 19 | D19: PIE | E19: 17 | F19: =VLOOKUP(Tableau2[[#This Row],[Code Article]],SORTIE!A9:C393,3,FALSE) -> 19 | G19: =Tableau2[[#This Row],[STOCK FIN DECEMBRE 2024 SAGE]]+Tableau2[[#This Row],[Entrée 01 Janv 2025 au 10 juillet 2026]]-Tableau2[[#This Row],[sortie 01 Janv 2025 au 10 juillet 2026]] -> 17 | H19: 17 | I19: =Tableau2[[#This Row],[inventaire juillet 2026 ]]-Tableau2[[#This Row],[stock final au 10 juillet 2026]] -> 0 | K19: 46216 | L19: =VLOOKUP(Tableau2[[#This Row],[Code Article]],'ENTREE APRES INV'!A18:F1027,6,0) -> #N/A | M19: =VLOOKUP(Tableau2[[#This Row],[Code Article]],'SORTIE APRES INV'!A18:D428,4,0) -> #N/A
A20: NMXTCBLFLX022XXX | B20: Cable filotex SMBL 19x0,22 ave | C20: 12 | D20: PIE | E20: 0 | F20: 0 | G20: =Tableau2[[#This Row],[STOCK FIN DECEMBRE 2024 SAGE]]+Tableau2[[#This Row],[Entrée 01 Janv 2025 au 10 juillet 2026]]-Tableau2[[#This Row],[sortie 01 Janv 2025 au 10 juillet 2026]] -> 12 | H20: 12 | I20: =Tableau2[[#This Row],[inventaire juillet 2026 ]]-Tableau2[[#This Row],[stock final au 10 juillet 2026]] -> 0 | K20: 46216 | L20: =VLOOKUP(Tableau2[[#This Row],[Code Article]],'ENTREE APRES INV'!A19:F1028,6,0) -> #N/A | M20: =VLOOKUP(Tableau2[[#This Row],[Code Article]],'SORTIE APRES INV'!A19:D429,4,0) -> #N/A
A21: NMXTFLTAIRXXXXXX | B21: FILTRE A AIR | C21: 14 | D21: PIE | E21: 3 | F21: =VLOOKUP(Tableau2[[#This Row],[Code Article]],SORTIE!A12:C396,3,FALSE) -> 3 | G21: =Tableau2[[#This Row],[STOCK FIN DECEMBRE 2024 SAGE]]+Tableau2[[#This Row],[Entrée 01 Janv 2025 au 10 juillet 2026]]-Tableau2[[#This Row],[sortie 01 Janv 2025 au 10 juillet 2026]] -> 14 | H21: 14 | I21: =Tableau2[[#This Row],[inventaire juillet 2026 ]]-Tableau2[[#This Row],[stock final au 10 juillet 2026]] -> 0 | K21: 46217 | L21: =VLOOKUP(Tableau2[[#This Row],[Code Article]],'ENTREE APRES INV'!A20:F1029,6,0) -> #N/A | M21: =VLOOKUP(Tableau2[[#This Row],[Code Article]],'SORTIE APRES INV'!A20:D430,4,0) -> #N/A
A22: QLCEPNEUPNEUXXXX | B22: PNEU | C22: 5 | D22: PIE | E22: =VLOOKUP(Tableau2[[#This Row],[Code Article]],ENTREE!A7:C599,3,FALSE) -> 21 | F22: 0 | G22: =Tableau2[[#This Row],[STOCK FIN DECEMBRE 2024 SAGE]]+Tableau2[[#This Row],[Entrée 01 Janv 2025 au 10 juillet 2026]]-Tableau2[[#This Row],[sortie 01 Janv 2025 au 10 juillet 2026]] -> 26 | H22: 26 | I22: =Tableau2[[#This Row],[inventaire juillet 2026 ]]-Tableau2[[#This Row],[stock final au 10 juillet 2026]] -> 0 | K22: 46216 | L22: =VLOOKUP(Tableau2[[#This Row],[Code Article]],'ENTREE APRES INV'!A21:F1030,6,0) -> 1 | M22: =VLOOKUP(Tableau2[[#This Row],[Code Article]],'SORTIE APRES INV'!A21:D431,4,0) -> #N/A
A23: TFOXCBLOSSA12HAW | B23: Optical Fiber Cable,Outdoor se | C23: 2957 | D23: PIE | E23: 0 | F23: 0 | G23: =Tableau2[[#This Row],[STOCK FIN DECEMBRE 2024 SAGE]]+Tableau2[[#This Row],[Entrée 01 Janv 2025 au 10 juillet 2026]]-Tableau2[[#This Row],[sortie 01 Janv 2025 au 10 juillet 2026]] -> 2957 | H23: 2957 | I23: =Tableau2[[#This Row],[inventaire juillet 2026 ]]-Tableau2[[#This Row],[stock final au 10 juillet 2026]] -> 0 | K23: 46224 | L23: =VLOOKUP(Tableau2[[#This Row],[Code Article]],'ENTREE APRES INV'!A22:F1031,6,0) -> #N/A | M23: =VLOOKUP(Tableau2[[#This Row],[Code Article]],'SORTIE APRES INV'!A22:D432,4,0) -> #N/A
A24: TGSMACCADKWLCXXX | B24: Standard Downtilt kit (Wind lo | C24: 28 | D24: PIE | E24: =VLOOKUP(Tableau2[[#This Row],[Code Article]],ENTREE!A9:C602,3,FALSE) -> 278 | F24: 0 | G24: =Tableau2[[#This Row],[STOCK FIN DECEMBRE 2024 SAGE]]+Tableau2[[#This Row],[Entrée 01 Janv 2025 au 10 juillet 2026]]-Tableau2[[#This Row],[sortie 01 Janv 2025 au 10 juillet 2026]] -> 306 | H24: 306 | I24: =Tableau2[[#This Row],[inventaire juillet 2026 ]]-Tableau2[[#This Row],[stock final au 10 juillet 2026]] -> 0 | K24: 46225 | L24: =VLOOKUP(Tableau2[[#This Row],[Code Article]],'ENTREE APRES INV'!A23:F1032,6,0) -> #N/A | M24: =VLOOKUP(Tableau2[[#This Row],[Code Article]],'SORTIE APRES INV'!A23:D433,4,0) -> #N/A
A25: AMOIFAICHAXXXXXX | B25: CHAISE | C25: 39 | D25: PIE | E25: =VLOOKUP(Tableau2[[#This Row],[Code Article]],ENTREE!A10:C604,3,FALSE) -> 109 | F25: =VLOOKUP(Tableau2[[#This Row],[Code Article]],SORTIE!A17:C402,3,FALSE) -> 148 | G25: =Tableau2[[#This Row],[STOCK FIN DECEMBRE 2024 SAGE]]+Tableau2[[#This Row],[Entrée 01 Janv 2025 au 10 juillet 2026]]-Tableau2[[#This Row],[sortie 01 Janv 2025 au 10 juillet 2026]] -> 0 | H25: 0 | I25: =Tableau2[[#This Row],[inventaire juillet 2026 ]]-Tableau2[[#This Row],[stock final au 10 juillet 2026]] -> 0 | K25: 46224 | L25: =VLOOKUP(Tableau2[[#This Row],[Code Article]],'ENTREE APRES INV'!A24:F1033,6,0) -> #N/A | M25: =VLOOKUP(Tableau2[[#This Row],[Code Article]],'SORTIE APRES INV'!A24:D434,4,0) -> #N/A
A26: CINFRUBFAT124XXX | B26: RUBAN POUR FAX T102/104 PC 74 | C26: 2 | D26: PIE | E26: 0 | F26: 0 | G26: =Tableau2[[#This Row],[STOCK FIN DECEMBRE 2024 SAGE]]+Tableau2[[#This Row],[Entrée 01 Janv 2025 au 10 juillet 2026]]-Tableau2[[#This Row],[sortie 01 Janv 2025 au 10 juillet 2026]] -> 2 | H26: 2 | I26: =Tableau2[[#This Row],[inventaire juillet 2026 ]]-Tableau2[[#This Row],[stock final au 10 juillet 2026]] -> 0 | K26: 46224 | L26: =VLOOKUP(Tableau2[[#This Row],[Code Article]],'ENTREE APRES INV'!A25:F1034,6,0) -> #N/A | M26: =VLOOKUP(Tableau2[[#This Row],[Code Article]],'SORTIE APRES INV'!A25:D435,4,0) -> #N/A
A27: CINFSOUSSF126DEL | B27: Souris sans fil Dell WM126 | C27: 2 | D27: PIE | E27: 24 | F27: =VLOOKUP(Tableau2[[#This Row],[Code Article]],SORTIE!A18:C404,3,FALSE) -> 26 | G27: =Tableau2[[#This Row],[STOCK FIN DECEMBRE 2024 SAGE]]+Tableau2[[#This Row],[Entrée 01 Janv 2025 au 10 juillet 2026]]-Tableau2[[#This Row],[sortie 01 Janv 2025 au 10 juillet 2026]] -> 0 | H27: 0 | I27: =Tableau2[[#This Row],[inventaire juillet 2026 ]]-Tableau2[[#This Row],[stock final au 10 juillet 2026]] -> 0 | K27: 46224 | L27: =VLOOKUP(Tableau2[[#This Row],[Code Article]],'ENTREE APRES INV'!A26:F1035,6,0) -> #N/A | M27: =VLOOKUP(Tableau2[[#This Row],[Code Article]],'SORTIE APRES INV'!A26:D436,4,0) -> #N/A
A28: IBATACCCR3030XXX | B28: Carreaux 30x30 | C28: 1 | D28: PIE | E28: 0 | F28: 0 | G28: =Tableau2[[#This Row],[STOCK FIN DECEMBRE 2024 SAGE]]+Tableau2[[#This Row],[Entrée 01 Janv 2025 au 10 juillet 2026]]-Tableau2[[#This Row],[sortie 01 Janv 2025 au 10 juillet 2026]] -> 1 | H28: 1 | I28: =Tableau2[[#This Row],[inventaire juillet 2026 ]]-Tableau2[[#This Row],[stock final au 10 juillet 2026]] -> 0 | K28: 46218 | L28: =VLOOKUP(Tableau2[[#This Row],[Code Article]],'ENTREE APRES INV'!A27:F1036,6,0) -> #N/A | M28: =VLOOKUP(Tableau2[[#This Row],[Code Article]],'SORTIE APRES INV'!A27:D437,4,0) -> #N/A
A29: NMXTCBLDC2X10YYY | B29: CABLE POWER,SHIELDED 10 M DC(S | C29: 10122 | D29: PIE | E29: 30035 | F29: =VLOOKUP(Tableau2[[#This Row],[Code Article]],SORTIE!A19:C406,3,FALSE) -> 40157 | G29: =Tableau2[[#This Row],[STOCK FIN DECEMBRE 2024 SAGE]]+Tableau2[[#This Row],[Entrée 01 Janv 2025 au 10 juillet 2026]]-Tableau2[[#This Row],[sortie 01 Janv 2025 au 10 juillet 2026]] -> 0 | I29: =Tableau2[[#This Row],[inventaire juillet 2026 ]]-Tableau2[[#This Row],[stock final au 10 juillet 2026]] -> 0 | K29: 46224 | L29: =VLOOKUP(Tableau2[[#This Row],[Code Article]],'ENTREE APRES INV'!A28:F1037,6,0) -> #N/A | M29: =VLOOKUP(Tableau2[[#This Row],[Code Article]],'SORTIE APRES INV'!A28:D438,4,0) -> #N/A
A30: TFHMANT30315HERC | B30: ANTENNE 3 A 0.3 15 HPX | C30: 4 | D30: PIE | E30: =VLOOKUP(Tableau2[[#This Row],[Code Article]],ENTREE!A13:C609,3,FALSE) -> 46 | F30: =VLOOKUP(Tableau2[[#This Row],[Code Article]],SORTIE!A20:C407,3,FALSE) -> 50 | G30: =Tableau2[[#This Row],[STOCK FIN DECEMBRE 2024 SAGE]]+Tableau2[[#This Row],[Entrée 01 Janv 2025 au 10 juillet 2026]]-Tableau2[[#This Row],[sortie 01 Janv 2025 au 10 juillet 2026]] -> 0 | I30: =Tableau2[[#This Row],[inventaire juillet 2026 ]]-Tableau2[[#This Row],[stock final au 10 juillet 2026]] -> 0 | K30: 46224 | L30: =VLOOKUP(Tableau2[[#This Row],[Code Article]],'ENTREE APRES INV'!A29:F1038,6,0) -> #N/A | M30: =VLOOKUP(Tableau2[[#This Row],[Code Article]],'SORTIE APRES INV'!A29:D439,4,0) -> #N/A
A31: TFHXIDUMDP400NEK | B31: MDP-400MB-1B (iPASOKINK200, 16 | C31: 2 | D31: PIE | E31: =VLOOKUP(Tableau2[[#This Row],[Code Article]],ENTREE!A14:C610,3,FALSE) -> 4 | F31: =VLOOKUP(Tableau2[[#This Row],[Code Article]],SORTIE!A21:C408,3,FALSE) -> 5 | G31: =Tableau2[[#This Row],[STOCK FIN DECEMBRE 2024 SAGE]]+Tableau2[[#This Row],[Entrée 01 Janv 2025 au 10 juillet 2026]]-Tableau2[[#This Row],[sortie 01 Janv 2025 au 10 juillet 2026]] -> 1 | H31: 1 | I31: =Tableau2[[#This Row],[inventaire juillet 2026 ]]-Tableau2[[#This Row],[stock final au 10 juillet 2026]] -> 0 | K31: 46217 | L31: =VLOOKUP(Tableau2[[#This Row],[Code Article]],'ENTREE APRES INV'!A30:F1039,6,0) -> #N/A | M31: =VLOOKUP(Tableau2[[#This Row],[Code Article]],'SORTIE APRES INV'!A30:D440,4,0) -> #N/A
A32: TFOXCFD12SA10NET | B32: Kit drop cable 1FO preco 2 sid | C32: 167 | D32: PIE | E32: 0 | F32: 0 | G32: =Tableau2[[#This Row],[STOCK FIN DECEMBRE 2024 SAGE]]+Tableau2[[#This Row],[Entrée 01 Janv 2025 au 10 juillet 2026]]-Tableau2[[#This Row],[sortie 01 Janv 2025 au 10 juillet 2026]] -> 167 | H32: 167 | I32: =Tableau2[[#This Row],[inventaire juillet 2026 ]]-Tableau2[[#This Row],[stock final au 10 juillet 2026]] -> 0 | K32: 46217 | L32: =VLOOKUP(Tableau2[[#This Row],[Code Article]],'ENTREE APRES INV'!A31:F1040,6,0) -> #N/A | M32: =VLOOKUP(Tableau2[[#This Row],[Code Article]],'SORTIE APRES INV'!A31:D441,4,0) -> #N/A
A33: TFOXCROILOVTSFLN | B33: Croix de Lovage Taille S FOLAN | C33: 1 | D33: PIE | E33: 0 | F33: 0 | G33: =Tableau2[[#This Row],[STOCK FIN DECEMBRE 2024 SAGE]]+Tableau2[[#This Row],[Entrée 01 Janv 2025 au 10 juillet 2026]]-Tableau2[[#This Row],[sortie 01 Janv 2025 au 10 juillet 2026]] -> 1 | H33: 1 | I33: =Tableau2[[#This Row],[inventaire juillet 2026 ]]-Tableau2[[#This Row],[stock final au 10 juillet 2026]] -> 0 | K33: 46216 | L33: =VLOOKUP(Tableau2[[#This Row],[Code Article]],'ENTREE APRES INV'!A32:F1041,6,0) -> #N/A | M33: =VLOOKUP(Tableau2[[#This Row],[Code Article]],'SORTIE APRES INV'!A32:D442,4,0) -> #N/A
A34: CINFSOUFIL116DEL | B34: Souris filaire Dell MS116 | C34: 2 | D34: PIE | E34: 0 | F34: 0 | G34: =Tableau2[[#This Row],[STOCK FIN DECEMBRE 2024 SAGE]]+Tableau2[[#This Row],[Entrée 01 Janv 2025 au 10 juillet 2026]]-Tableau2[[#This Row],[sortie 01 Janv 2025 au 10 juillet 2026]] -> 2 | H34: 2 | I34: =Tableau2[[#This Row],[inventaire juillet 2026 ]]-Tableau2[[#This Row],[stock final au 10 juillet 2026]] -> 0 | K34: 46224 | L34: =VLOOKUP(Tableau2[[#This Row],[Code Article]],'ENTREE APRES INV'!A33:F1042,6,0) -> #N/A | M34: =VLOOKUP(Tableau2[[#This Row],[Code Article]],'SORTIE APRES INV'!A33:D443,4,0) -> #N/A
A35: IGCVSEMANT1M2XXX | B35: Semelle trepied 1,20m | C35: 3 | D35: PIE | E35: 0 | F35: 0 | G35: =Tableau2[[#This Row],[STOCK FIN DECEMBRE 2024 SAGE]]+Tableau2[[#This Row],[Entrée 01 Janv 2025 au 10 juillet 2026]]-Tableau2[[#This Row],[sortie 01 Janv 2025 au 10 juillet 2026]] -> 3 | H35: 3 | I35: =Tableau2[[#This Row],[inventaire juillet 2026 ]]-Tableau2[[#This Row],[stock final au 10 juillet 2026]] -> 0 | K35: 46224 | L35: =VLOOKUP(Tableau2[[#This Row],[Code Article]],'ENTREE APRES INV'!A34:F1043,6,0) -> #N/A | M35: =VLOOKUP(Tableau2[[#This Row],[Code Article]],'SORTIE APRES INV'!A34:D444,4,0) -> #N/A
A36: NMXTBAT12V12APWR | B36: BATTERIE 12V 12Ah POWERSAFE | C36: 0 | D36: PIE | E36: =VLOOKUP(Tableau2[[#This Row],[Code Article]],ENTREE!A14:C615,3,FALSE) -> 4 | F36: =VLOOKUP(Tableau2[[#This Row],[Code Article]],SORTIE!A22:C413,3,FALSE) -> 4 | G36: =Tableau2[[#This Row],[STOCK FIN DECEMBRE 2024 SAGE]]+Tableau2[[#This Row],[Entrée 01 Janv 2025 au 10 juillet 2026]]-Tableau2[[#This Row],[sortie 01 Janv 2025 au 10 juillet 2026]] -> 0 | I36: =Tableau2[[#This Row],[inventaire juillet 2026 ]]-Tableau2[[#This Row],[stock final au 10 juillet 2026]] -> 0 | K36: 46224 | L36: =VLOOKUP(Tableau2[[#This Row],[Code Article]],'ENTREE APRES INV'!A35:F1044,6,0) -> #N/A | M36: =VLOOKUP(Tableau2[[#This Row],[Code Article]],'SORTIE APRES INV'!A35:D445,4,0) -> #N/A
A37: NMXTONDOL1100XXX | B37: ONDULEUR UPSON I 1100ONLINE MO | C37: 2 | D37: PIE | E37: 0 | F37: 0 | G37: =Tableau2[[#This Row],[STOCK FIN DECEMBRE 2024 SAGE]]+Tableau2[[#This Row],[Entrée 01 Janv 2025 au 10 juillet 2026]]-Tableau2[[#This Row],[sortie 01 Janv 2025 au 10 juillet 2026]] -> 2 | I37: =Tableau2[[#This Row],[inventaire juillet 2026 ]]-Tableau2[[#This Row],[stock final au 10 juillet 2026]] -> -2 | K37: 46224 | L37: =VLOOKUP(Tableau2[[#This Row],[Code Article]],'ENTREE APRES INV'!A36:F1045,6,0) -> #N/A | M37: =VLOOKUP(Tableau2[[#This Row],[Code Article]],'SORTIE APRES INV'!A36:D446,4,0) -> #N/A
A38: TCUIPEKR4XXXXGKA | B38: Peca R4 | C38: 6 | D38: PIE | E38: 0 | F38: 0 | G38: =Tableau2[[#This Row],[STOCK FIN DECEMBRE 2024 SAGE]]+Tableau2[[#This Row],[Entrée 01 Janv 2025 au 10 juillet 2026]]-Tableau2[[#This Row],[sortie 01 Janv 2025 au 10 juillet 2026]] -> 6 | H38: 6 | I38: =Tableau2[[#This Row],[inventaire juillet 2026 ]]-Tableau2[[#This Row],[stock final au 10 juillet 2026]] -> 0 | K38: 46224 | L38: =VLOOKUP(Tableau2[[#This Row],[Code Article]],'ENTREE APRES INV'!A37:F1046,6,0) -> #N/A | M38: =VLOOKUP(Tableau2[[#This Row],[Code Article]],'SORTIE APRES INV'!A37:D447,4,0) -> #N/A
A39: TFOXCBLS1FMUAGEK | B39: CABLE 1FO MULTI-USAGE G657A2 ( | C39: 4893 | D39: PIE | E39: =VLOOKUP(Tableau2[[#This Row],[Code Article]],ENTREE!A16:C618,3,FALSE) -> 4162 | F39: =VLOOKUP(Tableau2[[#This Row],[Code Article]],SORTIE!A23:C416,3,FALSE) -> 9055 | G39: =Tableau2[[#This Row],[STOCK FIN DECEMBRE 2024 SAGE]]+Tableau2[[#This Row],[Entrée 01 Janv 2025 au 10 juillet 2026]]-Tableau2[[#This Row],[sortie 01 Janv 2025 au 10 juillet 2026]] -> 0 | I39: =Tableau2[[#This Row],[inventaire juillet 2026 ]]-Tableau2[[#This Row],[stock final au 10 juillet 2026]] -> 0 | K39: 46224 | L39: =VLOOKUP(Tableau2[[#This Row],[Code Article]],'ENTREE APRES INV'!A38:F1047,6,0) -> 100 | M39: =VLOOKUP(Tableau2[[#This Row],[Code Article]],'SORTIE APRES INV'!A38:D448,4,0) -> #N/A
A40: TFOXTETOPTIQXXXX | B40: TETE OPTIQUE | C40: 9 | D40: PIE | E40: 0 | F40: =VLOOKUP(Tableau2[[#This Row],[Code Article]],SORTIE!A23:C417,3,FALSE) -> 6 | G40: =Tableau2[[#This Row],[STOCK FIN DECEMBRE 2024 SAGE]]+Tableau2[[#This Row],[Entrée 01 Janv 2025 au 10 juillet 2026]]-Tableau2[[#This Row],[sortie 01 Janv 2025 au 10 juillet 2026]] -> 3 | H40: 3 | I40: =Tableau2[[#This Row],[inventaire juillet 2026 ]]-Tableau2[[#This Row],[stock final au 10 juillet 2026]] -> 0 | K40: 46225 | L40: =VLOOKUP(Tableau2[[#This Row],[Code Article]],'ENTREE APRES INV'!A39:F1048,6,0) -> #N/A | M40: =VLOOKUP(Tableau2[[#This Row],[Code Article]],'SORTIE APRES INV'!A39:D449,4,0) -> #N/A
A41: TGSMACCTMAB12ERC | B41: TMA B1 (2-2), 24 dB KRY112442 | C41: 9 | D41: PIE | E41: 0 | F41: 0 | G41: =Tableau2[[#This Row],[STOCK FIN DECEMBRE 2024 SAGE]]+Tableau2[[#This Row],[Entrée 01 Janv 2025 au 10 juillet 2026]]-Tableau2[[#This Row],[sortie 01 Janv 2025 au 10 juillet 2026]] -> 9 | H41: 9 | I41: =Tableau2[[#This Row],[inventaire juillet 2026 ]]-Tableau2[[#This Row],[stock final au 10 juillet 2026]] -> 0 | K41: 46225 | L41: =VLOOKUP(Tableau2[[#This Row],[Code Article]],'ENTREE APRES INV'!A40:F1049,6,0) -> #N/A | M41: =VLOOKUP(Tableau2[[#This Row],[Code Article]],'SORTIE APRES INV'!A40:D450,4,0) -> #N/A
A42: IMXTCAMVIDSURXXX | B42: CAMERA DE SURVEILLANCE | C42: 2 | D42: PIE | E42: 49 | F42: =VLOOKUP(Tableau2[[#This Row],[Code Article]],SORTIE!A26:C421,3,FALSE) -> 51 | G42: =Tableau2[[#This Row],[STOCK FIN DECEMBRE 2024 SAGE]]+Tableau2[[#This Row],[Entrée 01 Janv 2025 au 10 juillet 2026]]-Tableau2[[#This Row],[sortie 01 Janv 2025 au 10 juillet 2026]] -> 0 | I42: =Tableau2[[#This Row],[inventaire juillet 2026 ]]-Tableau2[[#This Row],[stock final au 10 juillet 2026]] -> 0 | K42: 46224 | L42: =VLOOKUP(Tableau2[[#This Row],[Code Article]],'ENTREE APRES INV'!A41:F1050,6,0) -> 3 | M42: =VLOOKUP(Tableau2[[#This Row],[Code Article]],'SORTIE APRES INV'!A41:D451,4,0) -> #N/A
A43: MPLV000001057XXX | B43: ENSEIGNE LUMINEUSE | C43: 10 | D43: PIE | E43: =VLOOKUP(Tableau2[[#This Row],[Code Article]],ENTREE!A21:C624,3,FALSE) -> 11 | F43: =VLOOKUP(Tableau2[[#This Row],[Code Article]],SORTIE!A27:C422,3,FALSE) -> 16 | G43: =Tableau2[[#This Row],[STOCK FIN DECEMBRE 2024 SAGE]]+Tableau2[[#This Row],[Entrée 01 Janv 2025 au 10 juillet 2026]]-Tableau2[[#This Row],[sortie 01 Janv 2025 au 10 juillet 2026]] -> 5 | H43: 5 | I43: =Tableau2[[#This Row],[inventaire juillet 2026 ]]-Tableau2[[#This Row],[stock final au 10 juillet 2026]] -> 0 | K43: 46217 | L43: =VLOOKUP(Tableau2[[#This Row],[Code Article]],'ENTREE APRES INV'!A42:F1051,6,0) -> #N/A | M43: =VLOOKUP(Tableau2[[#This Row],[Code Article]],'SORTIE APRES INV'!A42:D452,4,0) -> #N/A
A44: NMXTBATL0TBTRXXX | B44: LOT DE BATTERIES | C44: 0 | D44: PIE | E44: 0 | F44: 0 | G44: =Tableau2[[#This Row],[STOCK FIN DECEMBRE 2024 SAGE]]+Tableau2[[#This Row],[Entrée 01 Janv 2025 au 10 juillet 2026]]-Tableau2[[#This Row],[sortie 01 Janv 2025 au 10 juillet 2026]] -> 0 | I44: =Tableau2[[#This Row],[inventaire juillet 2026 ]]-Tableau2[[#This Row],[stock final au 10 juillet 2026]] -> 0 | K44: 46224 | L44: =VLOOKUP(Tableau2[[#This Row],[Code Article]],'ENTREE APRES INV'!A43:F1052,6,0) -> #N/A | M44: =VLOOKUP(Tableau2[[#This Row],[Code Article]],'SORTIE APRES INV'!A43:D453,4,0) -> #N/A
A45: NMXTCBL6M35YGERC | B45: CABLE SET/Grounding cable set, | C45: 6 | D45: PIE | E45: =VLOOKUP(Tableau2[[#This Row],[Code Article]],ENTREE!A21:C627,3,FALSE) -> 127 | F45: =VLOOKUP(Tableau2[[#This Row],[Code Article]],SORTIE!A27:C425,3,FALSE) -> 98 | G45: =Tableau2[[#This Row],[STOCK FIN DECEMBRE 2024 SAGE]]+Tableau2[[#This Row],[Entrée 01 Janv 2025 au 10 juillet 2026]]-Tableau2[[#This Row],[sortie 01 Janv 2025 au 10 juillet 2026]] -> 35 | H45: 35 | I45: =Tableau2[[#This Row],[inventaire juillet 2026 ]]-Tableau2[[#This Row],[stock final au 10 juillet 2026]] -> 0 | K45: 46216 | L45: =VLOOKUP(Tableau2[[#This Row],[Code Article]],'ENTREE APRES INV'!A44:F1053,6,0) -> #N/A | M45: =VLOOKUP(Tableau2[[#This Row],[Code Article]],'SORTIE APRES INV'!A44:D454,4,0) -> #N/A
A46: NMXTCBLDP2X6MERC | B46: 2x6mm2 DC Power Cable No CPR N | C46: 195 | D46: PIE | E46: =VLOOKUP(Tableau2[[#This Row],[Code Article]],ENTREE!A22:C628,3,FALSE) -> 8540 | F46: =VLOOKUP(Tableau2[[#This Row],[Code Article]],SORTIE!A28:C426,3,FALSE) -> 8735 | G46: =Tableau2[[#This Row],[STOCK FIN DECEMBRE 2024 SAGE]]+Tableau2[[#This Row],[Entrée 01 Janv 2025 au 10 juillet 2026]]-Tableau2[[#This Row],[sortie 01 Janv 2025 au 10 juillet 2026]] -> 0 | I46: =Tableau2[[#This Row],[inventaire juillet 2026 ]]-Tableau2[[#This Row],[stock final au 10 juillet 2026]] -> 0 | K46: 46224 | L46: =VLOOKUP(Tableau2[[#This Row],[Code Article]],'ENTREE APRES INV'!A45:F1054,6,0) -> #N/A | M46: =VLOOKUP(Tableau2[[#This Row],[Code Article]],'SORTIE APRES INV'!A45:D455,4,0) -> #N/A
A47: NMXTFIXADHSTDXXX | B47: Fixation adhésive standard pou | C47: 172 | D47: PIE | E47: 0 | F47: 0 | G47: =Tableau2[[#This Row],[STOCK FIN DECEMBRE 2024 SAGE]]+Tableau2[[#This Row],[Entrée 01 Janv 2025 au 10 juillet 2026]]-Tableau2[[#This Row],[sortie 01 Janv 2025 au 10 juillet 2026]] -> 172 | H47: 172 | I47: =Tableau2[[#This Row],[inventaire juillet 2026 ]]-Tableau2[[#This Row],[stock final au 10 juillet 2026]] -> 0 | K47: 46217 | L47: =VLOOKUP(Tableau2[[#This Row],[Code Article]],'ENTREE APRES INV'!A46:F1055,6,0) -> #N/A | M47: =VLOOKUP(Tableau2[[#This Row],[Code Article]],'SORTIE APRES INV'!A46:D456,4,0) -> #N/A
A48: TGSMCBL16GY5MERC | B48: Earthing cable 16mm2 5m G/Y | C48: 18 | D48: PIE | E48: =VLOOKUP(Tableau2[[#This Row],[Code Article]],ENTREE!A26:C632,3,FALSE) -> 344 | F48: =VLOOKUP(Tableau2[[#This Row],[Code Article]],SORTIE!A31:C430,3,FALSE) -> 139 | G48: =Tableau2[[#This Row],[STOCK FIN DECEMBRE 2024 SAGE]]+Tableau2[[#This Row],[Entrée 01 Janv 2025 au 10 juillet 2026]]-Tableau2[[#This Row],[sortie 01 Janv 2025 au 10 juillet 2026]] -> 223 | H48: 223 | I48: =Tableau2[[#This Row],[inventaire juillet 2026 ]]-Tableau2[[#This Row],[stock final au 10 juillet 2026]] -> 0 | K48: 46218 | L48: =VLOOKUP(Tableau2[[#This Row],[Code Article]],'ENTREE APRES INV'!A47:F1056,6,0) -> #N/A | M48: =VLOOKUP(Tableau2[[#This Row],[Code Article]],'SORTIE APRES INV'!A47:D457,4,0) -> #N/A
A49: TGSMCBLGRPM25ERC | B49: CABLE WITH CONNECTOR/Grounding | C49: 2 | D49: PIE | E49: =VLOOKUP(Tableau2[[#This Row],[Code Article]],ENTREE!A28:C634,3,FALSE) -> 32 | F49: =VLOOKUP(Tableau2[[#This Row],[Code Article]],SORTIE!A32:C432,3,FALSE) -> 32 | G49: =Tableau2[[#This Row],[STOCK FIN DECEMBRE 2024 SAGE]]+Tableau2[[#This Row],[Entrée 01 Janv 2025 au 10 juillet 2026]]-Tableau2[[#This Row],[sortie 01 Janv 2025 au 10 juillet 2026]] -> 2 | H49: 2 | I49: =Tableau2[[#This Row],[inventaire juillet 2026 ]]-Tableau2[[#This Row],[stock final au 10 juillet 2026]] -> 0 | K49: 46216 | L49: =VLOOKUP(Tableau2[[#This Row],[Code Article]],'ENTREE APRES INV'!A48:F1057,6,0) -> #N/A | M49: =VLOOKUP(Tableau2[[#This Row],[Code Article]],'SORTIE APRES INV'!A48:D458,4,0) -> #N/A
A50: TGSMPRUDUS411ERC | B50: "DUS 41 01,Digital unit" | C50: 7 | D50: PIE | E50: 2 | F50: 4 | G50: =Tableau2[[#This Row],[STOCK FIN DECEMBRE 2024 SAGE]]+Tableau2[[#This Row],[Entrée 01 Janv 2025 au 10 juillet 2026]]-Tableau2[[#This Row],[sortie 01 Janv 2025 au 10 juillet 2026]] -> 5 | H50: 5 | I50: =Tableau2[[#This Row],[inventaire juillet 2026 ]]-Tableau2[[#This Row],[stock final au 10 juillet 2026]] -> 0 | K50: 46218 | L50: =VLOOKUP(Tableau2[[#This Row],[Code Article]],'ENTREE APRES INV'!A49:F1058,6,0) -> #N/A | M50: =VLOOKUP(Tableau2[[#This Row],[Code Article]],'SORTIE APRES INV'!A49:D459,4,0) -> #N/A
A51: TGSMRAU4415B7ERC | B51: TRANSCEIVER/Radio 4415 B7;Radi | C51: 0 | D51: PIE | E51: =VLOOKUP(Tableau2[[#This Row],[Code Article]],ENTREE!A29:C637,3,FALSE) -> 3 | F51: =VLOOKUP(Tableau2[[#This Row],[Code Article]],SORTIE!A33:C435,3,FALSE) -> 3 | G51: =Tableau2[[#This Row],[STOCK FIN DECEMBRE 2024 SAGE]]+Tableau2[[#This Row],[Entrée 01 Janv 2025 au 10 juillet 2026]]-Tableau2[[#This Row],[sortie 01 Janv 2025 au 10 juillet 2026]] -> 0 | H51: 0 | I51: =Tableau2[[#This Row],[inventaire juillet 2026 ]]-Tableau2[[#This Row],[stock final au 10 juillet 2026]] -> 0 | K51: 46224 | L51: =VLOOKUP(Tableau2[[#This Row],[Code Article]],'ENTREE APRES INV'!A50:F1059,6,0) -> #N/A | M51: =VLOOKUP(Tableau2[[#This Row],[Code Article]],'SORTIE APRES INV'!A50:D460,4,0) -> #N/A
A52: TGSMRBS2206XXERK | B52: CABINET RBS2206 V1 | C52: 1 | D52: PIE | E52: 0 | F52: 0 | G52: =Tableau2[[#This Row],[STOCK FIN DECEMBRE 2024 SAGE]]+Tableau2[[#This Row],[Entrée 01 Janv 2025 au 10 juillet 2026]]-Tableau2[[#This Row],[sortie 01 Janv 2025 au 10 juillet 2026]] -> 1 | H52: 1 | I52: =Tableau2[[#This Row],[inventaire juillet 2026 ]]-Tableau2[[#This Row],[stock final au 10 juillet 2026]] -> 0 | K52: 46216 | L52: =VLOOKUP(Tableau2[[#This Row],[Code Article]],'ENTREE APRES INV'!A51:F1060,6,0) -> #N/A | M52: =VLOOKUP(Tableau2[[#This Row],[Code Article]],'SORTIE APRES INV'!A51:D461,4,0) -> #N/A
A53: IGCVCFCBF6301XXX | B53: CONFECTION BASE FRAME POUR RBS | C53: 35 | D53: PIE | E53: =VLOOKUP(Tableau2[[#This Row],[Code Article]],ENTREE!A30:C640,3,FALSE) -> 22 | F53: =VLOOKUP(Tableau2[[#This Row],[Code Article]],SORTIE!A33:C438,3,FALSE) -> 36 | G53: =Tableau2[[#This Row],[STOCK FIN DECEMBRE 2024 SAGE]]+Tableau2[[#This Row],[Entrée 01 Janv 2025 au 10 juillet 2026]]-Tableau2[[#This Row],[sortie 01 Janv 2025 au 10 juillet 2026]] -> 21 | H53: 21 | I53: =Tableau2[[#This Row],[inventaire juillet 2026 ]]-Tableau2[[#This Row],[stock final au 10 juillet 2026]] -> 0 | K53: 46216 | L53: =VLOOKUP(Tableau2[[#This Row],[Code Article]],'ENTREE APRES INV'!A52:F1061,6,0) -> #N/A | M53: =VLOOKUP(Tableau2[[#This Row],[Code Article]],'SORTIE APRES INV'!A52:D462,4,0) -> #N/A
A54: NMXTRCKCONVERXXX | B54: BAIE REDRESSEUR (RACK) CONVERG | C54: 1 | D54: PIE | E54: 0 | F54: =VLOOKUP(Tableau2[[#This Row],[Code Article]],SORTIE!A33:C439,3,FALSE) -> 1 | G54: =Tableau2[[#This Row],[STOCK FIN DECEMBRE 2024 SAGE]]+Tableau2[[#This Row],[Entrée 01 Janv 2025 au 10 juillet 2026]]-Tableau2[[#This Row],[sortie 01 Janv 2025 au 10 juillet 2026]] -> 0 | I54: =Tableau2[[#This Row],[inventaire juillet 2026 ]]-Tableau2[[#This Row],[stock final au 10 juillet 2026]] -> 0 | K54: 46224 | L54: =VLOOKUP(Tableau2[[#This Row],[Code Article]],'ENTREE APRES INV'!A53:F1062,6,0) -> #N/A | M54: =VLOOKUP(Tableau2[[#This Row],[Code Article]],'SORTIE APRES INV'!A53:D463,4,0) -> #N/A
A55: QLCELAMTU820WXXX | B55: LAMPE TUBE T8 20W | C55: 2750 | D55: PIE | E55: =VLOOKUP(Tableau2[[#This Row],[Code Article]],ENTREE!A31:C642,3,FALSE) -> 57 | F55: =VLOOKUP(Tableau2[[#This Row],[Code Article]],SORTIE!A33:C440,3,FALSE) -> 2772 | G55: =Tableau2[[#This Row],[STOCK FIN DECEMBRE 2024 SAGE]]+Tableau2[[#This Row],[Entrée 01 Janv 2025 au 10 juillet 2026]]-Tableau2[[#This Row],[sortie 01 Janv 2025 au 10 juillet 2026]] -> 35 | H55: 35 | I55: =Tableau2[[#This Row],[inventaire juillet 2026 ]]-Tableau2[[#This Row],[stock final au 10 juillet 2026]] -> 0 | K55: 46217 | L55: =VLOOKUP(Tableau2[[#This Row],[Code Article]],'ENTREE APRES INV'!A54:F1063,6,0) -> #N/A | M55: =VLOOKUP(Tableau2[[#This Row],[Code Article]],'SORTIE APRES INV'!A54:D464,4,0) -> #N/A
A56: TCUICBL74X126GEK | B56: Câble 74-112-6 | C56: 15 | D56: PIE | E56: =+ENTREE!C666 -> 3967 | F56: 0 | G56: =Tableau2[[#This Row],[STOCK FIN DECEMBRE 2024 SAGE]]+Tableau2[[#This Row],[Entrée 01 Janv 2025 au 10 juillet 2026]]-Tableau2[[#This Row],[sortie 01 Janv 2025 au 10 juillet 2026]] -> 3982 | H56: 3982 | I56: =Tableau2[[#This Row],[inventaire juillet 2026 ]]-Tableau2[[#This Row],[stock final au 10 juillet 2026]] -> 0 | K56: 46219 | L56: =VLOOKUP(Tableau2[[#This Row],[Code Article]],'ENTREE APRES INV'!A55:F1064,6,0) -> #N/A | M56: =VLOOKUP(Tableau2[[#This Row],[Code Article]],'SORTIE APRES INV'!A55:D465,4,0) -> #N/A
A57: TCUIVISVI4X25GEK | B57: VIS A BOIS 4X25 | C57: 141 | D57: PIE | E57: 0 | F57: 0 | G57: =Tableau2[[#This Row],[STOCK FIN DECEMBRE 2024 SAGE]]+Tableau2[[#This Row],[Entrée 01 Janv 2025 au 10 juillet 2026]]-Tableau2[[#This Row],[sortie 01 Janv 2025 au 10 juillet 2026]] -> 141 | H57: 141 | I57: =Tableau2[[#This Row],[inventaire juillet 2026 ]]-Tableau2[[#This Row],[stock final au 10 juillet 2026]] -> 0 | K57: 46216 | L57: =VLOOKUP(Tableau2[[#This Row],[Code Article]],'ENTREE APRES INV'!A56:F1065,6,0) -> #N/A | M57: =VLOOKUP(Tableau2[[#This Row],[Code Article]],'SORTIE APRES INV'!A56:D466,4,0) -> #N/A
A58: TFMXMDMSTPROXXXX | B58: MODEM SPEED TOUCH PRO | C58: 14 | D58: PIE | F58: =VLOOKUP(Tableau2[[#This Row],[Code Article]],SORTIE!A33:C443,3,FALSE) -> 2 | G58: =Tableau2[[#This Row],[STOCK FIN DECEMBRE 2024 SAGE]]+Tableau2[[#This Row],[Entrée 01 Janv 2025 au 10 juillet 2026]]-Tableau2[[#This Row],[sortie 01 Janv 2025 au 10 juillet 2026]] -> 12 | H58: 12 | I58: =Tableau2[[#This Row],[inventaire juillet 2026 ]]-Tableau2[[#This Row],[stock final au 10 juillet 2026]] -> 0 | K58: 46217 | L58: =VLOOKUP(Tableau2[[#This Row],[Code Article]],'ENTREE APRES INV'!A57:F1066,6,0) -> #N/A | M58: =VLOOKUP(Tableau2[[#This Row],[Code Article]],'SORTIE APRES INV'!A57:D467,4,0) -> #N/A
A59: TFOXCBLTSC60CPTN | B59: Coupon de 60 ADSS single core | C59: 33 | D59: PIE | E59: =VLOOKUP(Tableau2[[#This Row],[Code Article]],ENTREE!A35:C647,3,FALSE) -> 304 | F59: =VLOOKUP(Tableau2[[#This Row],[Code Article]],SORTIE!A33:C445,3,FALSE) -> 337 | G59: =Tableau2[[#This Row],[STOCK FIN DECEMBRE 2024 SAGE]]+Tableau2[[#This Row],[Entrée 01 Janv 2025 au 10 juillet 2026]]-Tableau2[[#This Row],[sortie 01 Janv 2025 au 10 juillet 2026]] -> 0 | I59: =Tableau2[[#This Row],[inventaire juillet 2026 ]]-Tableau2[[#This Row],[stock final au 10 juillet 2026]] -> 0 | K59: 46224 | L59: =VLOOKUP(Tableau2[[#This Row],[Code Article]],'ENTREE APRES INV'!A58:F1067,6,0) -> #N/A | M59: =VLOOKUP(Tableau2[[#This Row],[Code Article]],'SORTIE APRES INV'!A58:D468,4,0) -> #N/A
A60: TGSMACC1R5MENERC | B60: QUANTITY PACKAGE 1XRxx Min 5M | C60: 11 | D60: PIE | E60: =VLOOKUP(Tableau2[[#This Row],[Code Article]],ENTREE!A36:C648,3,FALSE) -> 234 | F60: 0 | G60: =Tableau2[[#This Row],[STOCK FIN DECEMBRE 2024 SAGE]]+Tableau2[[#This Row],[Entrée 01 Janv 2025 au 10 juillet 2026]]-Tableau2[[#This Row],[sortie 01 Janv 2025 au 10 juillet 2026]] -> 245 | H60: 245 | I60: =Tableau2[[#This Row],[inventaire juillet 2026 ]]-Tableau2[[#This Row],[stock final au 10 juillet 2026]] -> 0 | K60: 46224 | L60: =VLOOKUP(Tableau2[[#This Row],[Code Article]],'ENTREE APRES INV'!A59:F1068,6,0) -> #N/A | M60: =VLOOKUP(Tableau2[[#This Row],[Code Article]],'SORTIE APRES INV'!A59:D469,4,0) -> #N/A
A61: NMXTBATC90C5BXXX | B61: BATTERY CABLE HALOGEN FREE, 90 | C61: 28 | D61: PIE | E61: =VLOOKUP(Tableau2[[#This Row],[Code Article]],ENTREE!A36:C650,3,FALSE) -> 330 | F61: =VLOOKUP(Tableau2[[#This Row],[Code Article]],SORTIE!A33:C448,3,FALSE) -> 330 | G61: =Tableau2[[#This Row],[STOCK FIN DECEMBRE 2024 SAGE]]+Tableau2[[#This Row],[Entrée 01 Janv 2025 au 10 juillet 2026]]-Tableau2[[#This Row],[sortie 01 Janv 2025 au 10 juillet 2026]] -> 28 | H61: 28 | I61: =Tableau2[[#This Row],[inventaire juillet 2026 ]]-Tableau2[[#This Row],[stock final au 10 juillet 2026]] -> 0 | K61: 46216 | L61: =VLOOKUP(Tableau2[[#This Row],[Code Article]],'ENTREE APRES INV'!A60:F1069,6,0) -> #N/A | M61: =VLOOKUP(Tableau2[[#This Row],[Code Article]],'SORTIE APRES INV'!A60:D470,4,0) -> #N/A
A62: NMXTFLTGO2046HFI | B62: Filtre à Gasoil HIFI SM 200 46 | C62: 14 | D62: PIE | E62: 0 | F62: 2 | G62: =Tableau2[[#This Row],[STOCK FIN DECEMBRE 2024 SAGE]]+Tableau2[[#This Row],[Entrée 01 Janv 2025 au 10 juillet 2026]]-Tableau2[[#This Row],[sortie 01 Janv 2025 au 10 juillet 2026]] -> 12 | H62: 12 | I62: =Tableau2[[#This Row],[inventaire juillet 2026 ]]-Tableau2[[#This Row],[stock final au 10 juillet 2026]] -> 0 | K62: 46217 | L62: =VLOOKUP(Tableau2[[#This Row],[Code Article]],'ENTREE APRES INV'!A61:F1070,6,0) -> #N/A | M62: =VLOOKUP(Tableau2[[#This Row],[Code Article]],'SORTIE APRES INV'!A61:D471,4,0) -> #N/A
A63: OUTIACCCOFFREXXX | B63: COFFRET | C63: 3 | D63: PIE | E63: =VLOOKUP(Tableau2[[#This Row],[Code Article]],ENTREE!A36:C652,3,FALSE) -> 13 | F63: =VLOOKUP(Tableau2[[#This Row],[Code Article]],SORTIE!A34:C450,3,FALSE) -> 3 | G63: =Tableau2[[#This Row],[STOCK FIN DECEMBRE 2024 SAGE]]+Tableau2[[#This Row],[Entrée 01 Janv 2025 au 10 juillet 2026]]-Tableau2[[#This Row],[sortie 01 Janv 2025 au 10 juillet 2026]] -> 13 | H63: 13 | I63: =Tableau2[[#This Row],[inventaire juillet 2026 ]]-Tableau2[[#This Row],[stock final au 10 juillet 2026]] -> 0 | K63: 46216 | L63: =VLOOKUP(Tableau2[[#This Row],[Code Article]],'ENTREE APRES INV'!A62:F1071,6,0) -> #N/A | M63: =VLOOKUP(Tableau2[[#This Row],[Code Article]],'SORTIE APRES INV'!A62:D472,4,0) -> #N/A
A64: TCUIBMX28PVIDGEK | B64: Bmx 28 paires (vide) | C64: 3 | D64: PIE | E64: =VLOOKUP(Tableau2[[#This Row],[Code Article]],ENTREE!A36:C653,3,FALSE) -> 6 | F64: 0 | G64: =Tableau2[[#This Row],[STOCK FIN DECEMBRE 2024 SAGE]]+Tableau2[[#This Row],[Entrée 01 Janv 2025 au 10 juillet 2026]]-Tableau2[[#This Row],[sortie 01 Janv 2025 au 10 juillet 2026]] -> 9 | H64: 9 | I64: =Tableau2[[#This Row],[inventaire juillet 2026 ]]-Tableau2[[#This Row],[stock final au 10 juillet 2026]] -> 0 | K64: 46216 | L64: =VLOOKUP(Tableau2[[#This Row],[Code Article]],'ENTREE APRES INV'!A63:F1072,6,0) -> #N/A | M64: =VLOOKUP(Tableau2[[#This Row],[Code Article]],'SORTIE APRES INV'!A63:D473,4,0) -> #N/A
A65: TFOXCBLTSC50CPTN | B65: Coupon de 50 ADSS single core | C65: 50 | D65: PIE | E65: =VLOOKUP(Tableau2[[#This Row],[Code Article]],ENTREE!A36:C654,3,FALSE) -> 510 | F65: =VLOOKUP(Tableau2[[#This Row],[Code Article]],SORTIE!A34:C452,3,FALSE) -> 560 | G65: =Tableau2[[#This Row],[STOCK FIN DECEMBRE 2024 SAGE]]+Tableau2[[#This Row],[Entrée 01 Janv 2025 au 10 juillet 2026]]-Tableau2[[#This Row],[sortie 01 Janv 2025 au 10 juillet 2026]] -> 0 | I65: =Tableau2[[#This Row],[inventaire juillet 2026 ]]-Tableau2[[#This Row],[stock final au 10 juillet 2026]] -> 0 | K65: 46224 | L65: =VLOOKUP(Tableau2[[#This Row],[Code Article]],'ENTREE APRES INV'!A64:F1073,6,0) -> #N/A | M65: =VLOOKUP(Tableau2[[#This Row],[Code Article]],'SORTIE APRES INV'!A64:D474,4,0) -> #N/A
A66: TFOXCBLTSC80CPTN | B66: Coupon de 80 ADSS single core | C66: 8 | D66: PIE | E66: =VLOOKUP(Tableau2[[#This Row],[Code Article]],ENTREE!A36:C655,3,FALSE) -> 80 | F66: =VLOOKUP(Tableau2[[#This Row],[Code Article]],SORTIE!A34:C453,3,FALSE) -> 88 | G66: =Tableau2[[#This Row],[STOCK FIN DECEMBRE 2024 SAGE]]+Tableau2[[#This Row],[Entrée 01 Janv 2025 au 10 juillet 2026]]-Tableau2[[#This Row],[sortie 01 Janv 2025 au 10 juillet 2026]] -> 0 | I66: =Tableau2[[#This Row],[inventaire juillet 2026 ]]-Tableau2[[#This Row],[stock final au 10 juillet 2026]] -> 0 | K66: 46224 | L66: =VLOOKUP(Tableau2[[#This Row],[Code Article]],'ENTREE APRES INV'!A65:F1074,6,0) -> #N/A | M66: =VLOOKUP(Tableau2[[#This Row],[Code Article]],'SORTIE APRES INV'!A65:D475,4,0) -> #N/A
A67: TFOXOUTCLVFCT50IT | B67: Cliveuse FUJIKURA CT50 Technol | C67: 21 | D67: PIE | E67: 0 | F67: 0 | G67: =Tableau2[[#This Row],[STOCK FIN DECEMBRE 2024 SAGE]]+Tableau2[[#This Row],[Entrée 01 Janv 2025 au 10 juillet 2026]]-Tableau2[[#This Row],[sortie 01 Janv 2025 au 10 juillet 2026]] -> 21 | H67: 21 | I67: =Tableau2[[#This Row],[inventaire juillet 2026 ]]-Tableau2[[#This Row],[stock final au 10 juillet 2026]] -> 0 | K67: 46219 | L67: =VLOOKUP(Tableau2[[#This Row],[Code Article]],'ENTREE APRES INV'!A66:F1075,6,0) -> #N/A | M67: =VLOOKUP(Tableau2[[#This Row],[Code Article]],'SORTIE APRES INV'!A66:D476,4,0) -> #N/A
A68: TGSMACCOVLB30ERK | B68: Overlenght box 30m OIL cable | C68: 115 | D68: PIE | E68: =VLOOKUP(Tableau2[[#This Row],[Code Article]],ENTREE!A37:C656,3,FALSE) -> 1233 | F68: =VLOOKUP(Tableau2[[#This Row],[Code Article]],SORTIE!A34:C455,3,FALSE) -> 1348 | G68: =Tableau2[[#This Row],[STOCK FIN DECEMBRE 2024 SAGE]]+Tableau2[[#This Row],[Entrée 01 Janv 2025 au 10 juillet 2026]]-Tableau2[[#This Row],[sortie 01 Janv 2025 au 10 juillet 2026]] -> 0 | I68: =Tableau2[[#This Row],[inventaire juillet 2026 ]]-Tableau2[[#This Row],[stock final au 10 juillet 2026]] -> 0 | K68: 46224 | L68: =VLOOKUP(Tableau2[[#This Row],[Code Article]],'ENTREE APRES INV'!A67:F1076,6,0) -> #N/A | M68: =VLOOKUP(Tableau2[[#This Row],[Code Article]],'SORTIE APRES INV'!A67:D477,4,0) -> #N/A
A69: CINFIMPRIMANTEXX | B69: IMPRIMANTE | C69: 3 | D69: PIE | E69: =VLOOKUP(Tableau2[[#This Row],[Code Article]],ENTREE!A38:C657,3,FALSE) -> 11 | F69: =VLOOKUP(Tableau2[[#This Row],[Code Article]],SORTIE!A35:C456,3,FALSE) -> 10 | G69: =Tableau2[[#This Row],[STOCK FIN DECEMBRE 2024 SAGE]]+Tableau2[[#This Row],[Entrée 01 Janv 2025 au 10 juillet 2026]]-Tableau2[[#This Row],[sortie 01 Janv 2025 au 10 juillet 2026]] -> 4 | H69: 4 | I69: =Tableau2[[#This Row],[inventaire juillet 2026 ]]-Tableau2[[#This Row],[stock final au 10 juillet 2026]] -> 0 | K69: 46217 | L69: =VLOOKUP(Tableau2[[#This Row],[Code Article]],'ENTREE APRES INV'!A68:F1077,6,0) -> #N/A | M69: =VLOOKUP(Tableau2[[#This Row],[Code Article]],'SORTIE APRES INV'!A68:D478,4,0) -> #N/A
A70: NMXTBAT12V170ERC | B70: Batterie NS 12V170Ah | C70: 0 | D70: PIE | E70: =VLOOKUP(Tableau2[[#This Row],[Code Article]],ENTREE!A38:C657,3,FALSE) -> 24 | F70: =VLOOKUP(Tableau2[[#This Row],[Code Article]],SORTIE!A36:C457,3,FALSE) -> 26 | G70: =Tableau2[[#This Row],[STOCK FIN DECEMBRE 2024 SAGE]]+Tableau2[[#This Row],[Entrée 01 Janv 2025 au 10 juillet 2026]]-Tableau2[[#This Row],[sortie 01 Janv 2025 au 10 juillet 2026]] -> -2 | I70: =Tableau2[[#This Row],[inventaire juillet 2026 ]]-Tableau2[[#This Row],[stock final au 10 juillet 2026]] -> 2 | K70: 46224 | L70: =VLOOKUP(Tableau2[[#This Row],[Code Article]],'ENTREE APRES INV'!A69:F1078,6,0) -> #N/A | M70: =VLOOKUP(Tableau2[[#This Row],[Code Article]],'SORTIE APRES INV'!A69:D479,4,0) -> #N/A
A71: TFOXCBLPC12FOFLN | B71: CABLE Minicore PRECONNECTORISE | C71: 11 | D71: PIE | E71: 0 | F71: 0 | G71: =Tableau2[[#This Row],[STOCK FIN DECEMBRE 2024 SAGE]]+Tableau2[[#This Row],[Entrée 01 Janv 2025 au 10 juillet 2026]]-Tableau2[[#This Row],[sortie 01 Janv 2025 au 10 juillet 2026]] -> 11 | H71: 11 | I71: =Tableau2[[#This Row],[inventaire juillet 2026 ]]-Tableau2[[#This Row],[stock final au 10 juillet 2026]] -> 0 | K71: 46216 | L71: =VLOOKUP(Tableau2[[#This Row],[Code Article]],'ENTREE APRES INV'!A70:F1079,6,0) -> #N/A | M71: =VLOOKUP(Tableau2[[#This Row],[Code Article]],'SORTIE APRES INV'!A70:D480,4,0) -> #N/A
A72: TFOXCBLTSC40CPTN | B72: Coupon de 40 ADSS single core | C72: 48 | D72: PIE | E72: =VLOOKUP(Tableau2[[#This Row],[Code Article]],ENTREE!A39:C661,3,FALSE) -> 1255 | F72: =VLOOKUP(Tableau2[[#This Row],[Code Article]],SORTIE!A37:C461,3,FALSE) -> 1303 | G72: =Tableau2[[#This Row],[STOCK FIN DECEMBRE 2024 SAGE]]+Tableau2[[#This Row],[Entrée 01 Janv 2025 au 10 juillet 2026]]-Tableau2[[#This Row],[sortie 01 Janv 2025 au 10 juillet 2026]] -> 0 | I72: =Tableau2[[#This Row],[inventaire juillet 2026 ]]-Tableau2[[#This Row],[stock final au 10 juillet 2026]] -> 0 | K72: 46224 | L72: =VLOOKUP(Tableau2[[#This Row],[Code Article]],'ENTREE APRES INV'!A71:F1080,6,0) -> #N/A | M72: =VLOOKUP(Tableau2[[#This Row],[Code Article]],'SORTIE APRES INV'!A71:D481,4,0) -> #N/A
A73: TFOXPINJOKBLEXXX | B73: Pince JOKARI (Bleu) | C73: 2 | D73: PIE | E73: 0 | F73: 0 | G73: =Tableau2[[#This Row],[STOCK FIN DECEMBRE 2024 SAGE]]+Tableau2[[#This Row],[Entrée 01 Janv 2025 au 10 juillet 2026]]-Tableau2[[#This Row],[sortie 01 Janv 2025 au 10 juillet 2026]] -> 2 | H73: 2 | I73: =Tableau2[[#This Row],[inventaire juillet 2026 ]]-Tableau2[[#This Row],[stock final au 10 juillet 2026]] -> 0 | K73: 46224 | L73: =VLOOKUP(Tableau2[[#This Row],[Code Article]],'ENTREE APRES INV'!A72:F1081,6,0) -> #N/A | M73: =VLOOKUP(Tableau2[[#This Row],[Code Article]],'SORTIE APRES INV'!A72:D482,4,0) -> #N/A
A74: TGSMACCCFPC10ERK | B74: Clamps for Fiber and Power Cab | C74: 6 | D74: PIE | E74: 0 | F74: 0 | G74: =Tableau2[[#This Row],[STOCK FIN DECEMBRE 2024 SAGE]]+Tableau2[[#This Row],[Entrée 01 Janv 2025 au 10 juillet 2026]]-Tableau2[[#This Row],[sortie 01 Janv 2025 au 10 juillet 2026]] -> 6 | H74: 6 | I74: =Tableau2[[#This Row],[inventaire juillet 2026 ]]-Tableau2[[#This Row],[stock final au 10 juillet 2026]] -> 0 | K74: 46216 | L74: =VLOOKUP(Tableau2[[#This Row],[Code Article]],'ENTREE APRES INV'!A73:F1082,6,0) -> #N/A | M74: =VLOOKUP(Tableau2[[#This Row],[Code Article]],'SORTIE APRES INV'!A73:D483,4,0) -> #N/A
A75: TGSMACCMOUKITERC | B75: MOUNTING KIT_ SXK1252540/1 | C75: 1 | D75: PIE | E75: 0 | F75: 0 | G75: =Tableau2[[#This Row],[STOCK FIN DECEMBRE 2024 SAGE]]+Tableau2[[#This Row],[Entrée 01 Janv 2025 au 10 juillet 2026]]-Tableau2[[#This Row],[sortie 01 Janv 2025 au 10 juillet 2026]] -> 1 | H75: 1 | I75: =Tableau2[[#This Row],[inventaire juillet 2026 ]]-Tableau2[[#This Row],[stock final au 10 juillet 2026]] -> 0 | K75: 46224 | L75: =VLOOKUP(Tableau2[[#This Row],[Code Article]],'ENTREE APRES INV'!A74:F1083,6,0) -> #N/A | M75: =VLOOKUP(Tableau2[[#This Row],[Code Article]],'SORTIE APRES INV'!A74:D484,4,0) -> #N/A
A76: AMOIARM2PRT2XXXX | B76: ARMOIRES | C76: 2 | D76: PIE | E76: =VLOOKUP(Tableau2[[#This Row],[Code Article]],ENTREE!A39:C665,3,FALSE) -> 41 | F76: 30 | G76: =Tableau2[[#This Row],[STOCK FIN DECEMBRE 2024 SAGE]]+Tableau2[[#This Row],[Entrée 01 Janv 2025 au 10 juillet 2026]]-Tableau2[[#This Row],[sortie 01 Janv 2025 au 10 juillet 2026]] -> 13 | H76: 13 | I76: =Tableau2[[#This Row],[inventaire juillet 2026 ]]-Tableau2[[#This Row],[stock final au 10 juillet 2026]] -> 0 | K76: 46218 | L76: =VLOOKUP(Tableau2[[#This Row],[Code Article]],'ENTREE APRES INV'!A75:F1084,6,0) -> #N/A | M76: =VLOOKUP(Tableau2[[#This Row],[Code Article]],'SORTIE APRES INV'!A75:D485,4,0) -> #N/A
A77: TCUICBL74X448GEK | B77: Câble 74-448-6 | C77: 298 | D77: PIE | E77: =+ENTREE!C135 -> 2651 | F77: 0 | G77: =Tableau2[[#This Row],[STOCK FIN DECEMBRE 2024 SAGE]]+Tableau2[[#This Row],[Entrée 01 Janv 2025 au 10 juillet 2026]]-Tableau2[[#This Row],[sortie 01 Janv 2025 au 10 juillet 2026]] -> 2949 | H77: 2949 | I77: =Tableau2[[#This Row],[inventaire juillet 2026 ]]-Tableau2[[#This Row],[stock final au 10 juillet 2026]] -> 0 | K77: 46219 | L77: =VLOOKUP(Tableau2[[#This Row],[Code Article]],'ENTREE APRES INV'!A76:F1085,6,0) -> #N/A | M77: =VLOOKUP(Tableau2[[#This Row],[Code Article]],'SORTIE APRES INV'!A76:D486,4,0) -> #N/A
A78: TGSMACCT93020ERK | B78: TMR 9302 without AC/DC Conver | C78: 3 | D78: PIE | E78: =VLOOKUP(Tableau2[[#This Row],[Code Article]],ENTREE!A39:C667,3,FALSE) -> 9 | F78: =VLOOKUP(Tableau2[[#This Row],[Code Article]],SORTIE!A38:C467,3,FALSE) -> 9 | G78: =Tableau2[[#This Row],[STOCK FIN DECEMBRE 2024 SAGE]]+Tableau2[[#This Row],[Entrée 01 Janv 2025 au 10 juillet 2026]]-Tableau2[[#This Row],[sortie 01 Janv 2025 au 10 juillet 2026]] -> 3 | H78: 3 | I78: =Tableau2[[#This Row],[inventaire juillet 2026 ]]-Tableau2[[#This Row],[stock final au 10 juillet 2026]] -> 0 | K78: 46225 | L78: =VLOOKUP(Tableau2[[#This Row],[Code Article]],'ENTREE APRES INV'!A77:F1086,6,0) -> #N/A | M78: =VLOOKUP(Tableau2[[#This Row],[Code Article]],'SORTIE APRES INV'!A77:D487,4,0) -> #N/A
A79: TGSMADPDUX320ERC | B79: ADAPTER/DUX Adapter | C79: 150 | D79: PIE | E79: =VLOOKUP(Tableau2[[#This Row],[Code Article]],ENTREE!A39:C668,3,FALSE) -> 54 | F79: 134 | G79: =Tableau2[[#This Row],[STOCK FIN DECEMBRE 2024 SAGE]]+Tableau2[[#This Row],[Entrée 01 Janv 2025 au 10 juillet 2026]]-Tableau2[[#This Row],[sortie 01 Janv 2025 au 10 juillet 2026]] -> 70 | H79: 70 | I79: =Tableau2[[#This Row],[inventaire juillet 2026 ]]-Tableau2[[#This Row],[stock final au 10 juillet 2026]] -> 0 | K79: 46225 | L79: =VLOOKUP(Tableau2[[#This Row],[Code Article]],'ENTREE APRES INV'!A78:F1087,6,0) -> #N/A | M79: =VLOOKUP(Tableau2[[#This Row],[Code Article]],'SORTIE APRES INV'!A78:D488,4,0) -> #N/A
A80: TGSMBRADUAERSERC | B80: Dual ERS bracket_SXK1091973/2 | C80: 41 | D80: PIE | E80: =VLOOKUP(Tableau2[[#This Row],[Code Article]],ENTREE!A39:C670,3,FALSE) -> 260 | F80: 0 | G80: =Tableau2[[#This Row],[STOCK FIN DECEMBRE 2024 SAGE]]+Tableau2[[#This Row],[Entrée 01 Janv 2025 au 10 juillet 2026]]-Tableau2[[#This Row],[sortie 01 Janv 2025 au 10 juillet 2026]] -> 301 | H80: 301 | I80: =Tableau2[[#This Row],[inventaire juillet 2026 ]]-Tableau2[[#This Row],[stock final au 10 juillet 2026]] -> 0 | K80: 46216 | L80: =VLOOKUP(Tableau2[[#This Row],[Code Article]],'ENTREE APRES INV'!A79:F1088,6,0) -> #N/A | M80: =VLOOKUP(Tableau2[[#This Row],[Code Article]],'SORTIE APRES INV'!A79:D489,4,0) -> #N/A
A81: TGSMFANINTRAYERC | B81: Internal Fan Tray | C81: 19 | D81: PIE | E81: =VLOOKUP(Tableau2[[#This Row],[Code Article]],ENTREE!A39:C671,3,FALSE) -> 20 | F81: =VLOOKUP(Tableau2[[#This Row],[Code Article]],SORTIE!A39:C471,3,FALSE) -> 18 | G81: =Tableau2[[#This Row],[STOCK FIN DECEMBRE 2024 SAGE]]+Tableau2[[#This Row],[Entrée 01 Janv 2025 au 10 juillet 2026]]-Tableau2[[#This Row],[sortie 01 Janv 2025 au 10 juillet 2026]] -> 21 | H81: 21 | I81: =Tableau2[[#This Row],[inventaire juillet 2026 ]]-Tableau2[[#This Row],[stock final au 10 juillet 2026]] -> 0 | K81: 46217 | L81: =VLOOKUP(Tableau2[[#This Row],[Code Article]],'ENTREE APRES INV'!A80:F1089,6,0) -> #N/A | M81: =VLOOKUP(Tableau2[[#This Row],[Code Article]],'SORTIE APRES INV'!A80:D490,4,0) -> #N/A
A82: TGSMFLTSE600SERK | B82: AIR FILTER, SE600/SM240 SPARE | C82: 3 | D82: PIE | E82: 0 | F82: 0 | G82: =Tableau2[[#This Row],[STOCK FIN DECEMBRE 2024 SAGE]]+Tableau2[[#This Row],[Entrée 01 Janv 2025 au 10 juillet 2026]]-Tableau2[[#This Row],[sortie 01 Janv 2025 au 10 juillet 2026]] -> 3 | H82: 3 | I82: =Tableau2[[#This Row],[inventaire juillet 2026 ]]-Tableau2[[#This Row],[stock final au 10 juillet 2026]] -> 0 | K82: 46225 | L82: =VLOOKUP(Tableau2[[#This Row],[Code Article]],'ENTREE APRES INV'!A81:F1090,6,0) -> #N/A | M82: =VLOOKUP(Tableau2[[#This Row],[Code Article]],'SORTIE APRES INV'!A81:D491,4,0) -> #N/A
A83: TGSMJUMRFS713ERC | B83: RFS 1/2 jumper cable, 4.3 10( | C83: 0 | D83: PIE | E83: 0 | F83: 0 | G83: =Tableau2[[#This Row],[STOCK FIN DECEMBRE 2024 SAGE]]+Tableau2[[#This Row],[Entrée 01 Janv 2025 au 10 juillet 2026]]-Tableau2[[#This Row],[sortie 01 Janv 2025 au 10 juillet 2026]] -> 0 | I83: =Tableau2[[#This Row],[inventaire juillet 2026 ]]-Tableau2[[#This Row],[stock final au 10 juillet 2026]] -> 0 | K83: 46224 | L83: =VLOOKUP(Tableau2[[#This Row],[Code Article]],'ENTREE APRES INV'!A82:F1091,6,0) -> #N/A | M83: =VLOOKUP(Tableau2[[#This Row],[Code Article]],'SORTIE APRES INV'!A82:D492,4,0) -> #N/A
A84: TGSMCBLCPC315ERC | B84: CABLE WITH CONNECTOR/POWER CAB | C84: 13 | D84: PIE | E84: =VLOOKUP(Tableau2[[#This Row],[Code Article]],ENTREE!A40:C675,3,FALSE) -> 16 | F84: =VLOOKUP(Tableau2[[#This Row],[Code Article]],SORTIE!A39:C475,3,FALSE) -> 23 | G84: =Tableau2[[#This Row],[STOCK FIN DECEMBRE 2024 SAGE]]+Tableau2[[#This Row],[Entrée 01 Janv 2025 au 10 juillet 2026]]-Tableau2[[#This Row],[sortie 01 Janv 2025 au 10 juillet 2026]] -> 6 | H84: 6 | I84: =Tableau2[[#This Row],[inventaire juillet 2026 ]]-Tableau2[[#This Row],[stock final au 10 juillet 2026]] -> 0 | K84: 46216 | L84: =VLOOKUP(Tableau2[[#This Row],[Code Article]],'ENTREE APRES INV'!A83:F1092,6,0) -> #N/A | M84: =VLOOKUP(Tableau2[[#This Row],[Code Article]],'SORTIE APRES INV'!A83:D493,4,0) -> #N/A
A85: TGSMCRTSCU011ERC | B85: SCU0101 | C85: 3 | D85: PIE | E85: =VLOOKUP(Tableau2[[#This Row],[Code Article]],ENTREE!A40:C677,3,FALSE) -> 19 | F85: =VLOOKUP(Tableau2[[#This Row],[Code Article]],SORTIE!A39:C477,3,FALSE) -> 19 | G85: =Tableau2[[#This Row],[STOCK FIN DECEMBRE 2024 SAGE]]+Tableau2[[#This Row],[Entrée 01 Janv 2025 au 10 juillet 2026]]-Tableau2[[#This Row],[sortie 01 Janv 2025 au 10 juillet 2026]] -> 3 | H85: 3 | I85: =Tableau2[[#This Row],[inventaire juillet 2026 ]]-Tableau2[[#This Row],[stock final au 10 juillet 2026]] -> 0 | K85: 46224 | L85: =VLOOKUP(Tableau2[[#This Row],[Code Article]],'ENTREE APRES INV'!A84:F1093,6,0) -> #N/A | M85: =VLOOKUP(Tableau2[[#This Row],[Code Article]],'SORTIE APRES INV'!A84:D494,4,0) -> #N/A
A86: TGSMDISXXV06AERC | B86: Circuit Breaker 6A_NFS89990/11 | C86: 6 | D86: PIE | E86: =VLOOKUP(Tableau2[[#This Row],[Code Article]],ENTREE!A40:C678,3,FALSE) -> 24 | F86: =VLOOKUP(Tableau2[[#This Row],[Code Article]],SORTIE!A39:C478,3,FALSE) -> 30 | G86: =Tableau2[[#This Row],[STOCK FIN DECEMBRE 2024 SAGE]]+Tableau2[[#This Row],[Entrée 01 Janv 2025 au 10 juillet 2026]]-Tableau2[[#This Row],[sortie 01 Janv 2025 au 10 juillet 2026]] -> 0 | I86: =Tableau2[[#This Row],[inventaire juillet 2026 ]]-Tableau2[[#This Row],[stock final au 10 juillet 2026]] -> 0 | K86: 46224 | L86: =VLOOKUP(Tableau2[[#This Row],[Code Article]],'ENTREE APRES INV'!A85:F1094,6,0) -> #N/A | M86: =VLOOKUP(Tableau2[[#This Row],[Code Article]],'SORTIE APRES INV'!A85:D495,4,0) -> #N/A
A87: TGSMEMGR6471DERC | B87: EQUIPPED MAGAZINE/Router 6471/ | C87: 3 | D87: PIE | E87: 2 | F87: =VLOOKUP(Tableau2[[#This Row],[Code Article]],SORTIE!A39:C479,3,FALSE) -> 2 | G87: =Tableau2[[#This Row],[STOCK FIN DECEMBRE 2024 SAGE]]+Tableau2[[#This Row],[Entrée 01 Janv 2025 au 10 juillet 2026]]-Tableau2[[#This Row],[sortie 01 Janv 2025 au 10 juillet 2026]] -> 3 | H87: 3 | I87: =Tableau2[[#This Row],[inventaire juillet 2026 ]]-Tableau2[[#This Row],[stock final au 10 juillet 2026]] -> 0 | K87: 46217 | L87: =VLOOKUP(Tableau2[[#This Row],[Code Article]],'ENTREE APRES INV'!A86:F1095,6,0) -> #N/A | M87: =VLOOKUP(Tableau2[[#This Row],[Code Article]],'SORTIE APRES INV'!A86:D496,4,0) -> #N/A
A88: TGSMPDU0101PDERC | B88: PDU 01 01 | C88: 16 | D88: PIE | E88: =VLOOKUP(Tableau2[[#This Row],[Code Article]],ENTREE!A40:C680,3,FALSE) -> 32 | F88: =VLOOKUP(Tableau2[[#This Row],[Code Article]],SORTIE!A39:C480,3,FALSE) -> 46 | G88: =Tableau2[[#This Row],[STOCK FIN DECEMBRE 2024 SAGE]]+Tableau2[[#This Row],[Entrée 01 Janv 2025 au 10 juillet 2026]]-Tableau2[[#This Row],[sortie 01 Janv 2025 au 10 juillet 2026]] -> 2 | H88: 2 | I88: =Tableau2[[#This Row],[inventaire juillet 2026 ]]-Tableau2[[#This Row],[stock final au 10 juillet 2026]] -> 0 | K88: 46224 | L88: =VLOOKUP(Tableau2[[#This Row],[Code Article]],'ENTREE APRES INV'!A87:F1096,6,0) -> #N/A | M88: =VLOOKUP(Tableau2[[#This Row],[Code Article]],'SORTIE APRES INV'!A87:D497,4,0) -> #N/A
A89: TGSMPROBB5216ERC | B89: Baseband 5216 Digital Unit (wi | C89: 0 | D89: PIE | E89: =VLOOKUP(Tableau2[[#This Row],[Code Article]],ENTREE!A40:C681,3,FALSE) -> 3 | F89: =VLOOKUP(Tableau2[[#This Row],[Code Article]],SORTIE!A39:C481,3,FALSE) -> 2 | G89: =Tableau2[[#This Row],[STOCK FIN DECEMBRE 2024 SAGE]]+Tableau2[[#This Row],[Entrée 01 Janv 2025 au 10 juillet 2026]]-Tableau2[[#This Row],[sortie 01 Janv 2025 au 10 juillet 2026]] -> 1 | H89: 1 | I89: =Tableau2[[#This Row],[inventaire juillet 2026 ]]-Tableau2[[#This Row],[stock final au 10 juillet 2026]] -> 0 | K89: 46216 | L89: =VLOOKUP(Tableau2[[#This Row],[Code Article]],'ENTREE APRES INV'!A88:F1097,6,0) -> #N/A | M89: =VLOOKUP(Tableau2[[#This Row],[Code Article]],'SORTIE APRES INV'!A88:D498,4,0) -> #N/A
A90: TGSMTRCRUS1B3ERC | B90: "TRANSCEIVER/RRUS 01 B3,Radio | C90: 1 | D90: PIE | E90: 11 | F90: 11 | G90: =Tableau2[[#This Row],[STOCK FIN DECEMBRE 2024 SAGE]]+Tableau2[[#This Row],[Entrée 01 Janv 2025 au 10 juillet 2026]]-Tableau2[[#This Row],[sortie 01 Janv 2025 au 10 juillet 2026]] -> 1 | H90: 1 | I90: =Tableau2[[#This Row],[inventaire juillet 2026 ]]-Tableau2[[#This Row],[stock final au 10 juillet 2026]] -> 0 | K90: 46216 | L90: =VLOOKUP(Tableau2[[#This Row],[Code Article]],'ENTREE APRES INV'!A89:F1098,6,0) -> #N/A | M90: =VLOOKUP(Tableau2[[#This Row],[Code Article]],'SORTIE APRES INV'!A89:D499,4,0) -> #N/A
A91: MDIV000000112XXX | B91: ECRAN ORDINATEUR HP 7540 | C91: 2 | D91: PIE | E91: =VLOOKUP(Tableau2[[#This Row],[Code Article]],ENTREE!A40:C683,3,FALSE) -> 52 | F91: 54 | G91: =Tableau2[[#This Row],[STOCK FIN DECEMBRE 2024 SAGE]]+Tableau2[[#This Row],[Entrée 01 Janv 2025 au 10 juillet 2026]]-Tableau2[[#This Row],[sortie 01 Janv 2025 au 10 juillet 2026]] -> 0 | I91: =Tableau2[[#This Row],[inventaire juillet 2026 ]]-Tableau2[[#This Row],[stock final au 10 juillet 2026]] -> 0 | K91: 46224 | L91: =VLOOKUP(Tableau2[[#This Row],[Code Article]],'ENTREE APRES INV'!A90:F1099,6,0) -> #N/A | M91: =VLOOKUP(Tableau2[[#This Row],[Code Article]],'SORTIE APRES INV'!A90:D500,4,0) -> #N/A
A92: NMXTFLTHUILEXXXX | B92: FILTRE A HUILE | C92: 12 | D92: PIE | E92: 0 | F92: 0 | G92: =Tableau2[[#This Row],[STOCK FIN DECEMBRE 2024 SAGE]]+Tableau2[[#This Row],[Entrée 01 Janv 2025 au 10 juillet 2026]]-Tableau2[[#This Row],[sortie 01 Janv 2025 au 10 juillet 2026]] -> 12 | H92: 12 | I92: =Tableau2[[#This Row],[inventaire juillet 2026 ]]-Tableau2[[#This Row],[stock final au 10 juillet 2026]] -> 0 | K92: 46217 | L92: =VLOOKUP(Tableau2[[#This Row],[Code Article]],'ENTREE APRES INV'!A91:F1100,6,0) -> #N/A | M92: =VLOOKUP(Tableau2[[#This Row],[Code Article]],'SORTIE APRES INV'!A91:D501,4,0) -> #N/A
A93: OUTILTECESCABOTX | B93: Escabot | C93: 5 | D93: PIE | E93: =VLOOKUP(Tableau2[[#This Row],[Code Article]],ENTREE!A41:C686,3,FALSE) -> 1 | F93: 0 | G93: =Tableau2[[#This Row],[STOCK FIN DECEMBRE 2024 SAGE]]+Tableau2[[#This Row],[Entrée 01 Janv 2025 au 10 juillet 2026]]-Tableau2[[#This Row],[sortie 01 Janv 2025 au 10 juillet 2026]] -> 6 | H93: 6 | I93: =Tableau2[[#This Row],[inventaire juillet 2026 ]]-Tableau2[[#This Row],[stock final au 10 juillet 2026]] -> 0 | K93: 46217 | L93: =VLOOKUP(Tableau2[[#This Row],[Code Article]],'ENTREE APRES INV'!A92:F1101,6,0) -> #N/A | M93: =VLOOKUP(Tableau2[[#This Row],[Code Article]],'SORTIE APRES INV'!A92:D502,4,0) -> #N/A
A94: QUINLUMTU20L3XXX | B94: Tube URO 20mm long 3ml | C94: 1 | D94: PIE | E94: 0 | F94: 0 | G94: =Tableau2[[#This Row],[STOCK FIN DECEMBRE 2024 SAGE]]+Tableau2[[#This Row],[Entrée 01 Janv 2025 au 10 juillet 2026]]-Tableau2[[#This Row],[sortie 01 Janv 2025 au 10 juillet 2026]] -> 1 | H94: 1 | I94: =Tableau2[[#This Row],[inventaire juillet 2026 ]]-Tableau2[[#This Row],[stock final au 10 juillet 2026]] -> 0 | K94: 46225 | L94: =VLOOKUP(Tableau2[[#This Row],[Code Article]],'ENTREE APRES INV'!A93:F1102,6,0) -> #N/A | M94: =VLOOKUP(Tableau2[[#This Row],[Code Article]],'SORTIE APRES INV'!A93:D503,4,0) -> #N/A
A95: TCUICBL74X224GEK | B95: Câble 74-224-6 | C95: 639 | D95: PIE | E95: =+ENTREE!C134 -> 4837 | F95: 0 | G95: =Tableau2[[#This Row],[STOCK FIN DECEMBRE 2024 SAGE]]+Tableau2[[#This Row],[Entrée 01 Janv 2025 au 10 juillet 2026]]-Tableau2[[#This Row],[sortie 01 Janv 2025 au 10 juillet 2026]] -> 5476 | H95: 5476 | I95: =Tableau2[[#This Row],[inventaire juillet 2026 ]]-Tableau2[[#This Row],[stock final au 10 juillet 2026]] -> 0 | K95: 46216 | L95: =VLOOKUP(Tableau2[[#This Row],[Code Article]],'ENTREE APRES INV'!A94:F1103,6,0) -> #N/A | M95: =VLOOKUP(Tableau2[[#This Row],[Code Article]],'SORTIE APRES INV'!A94:D504,4,0) -> #N/A
A96: TCUICBL98X028GEK | B96: Câble 98-028-6 | C96: 201 | D96: PIE | E96: =VLOOKUP(Tableau2[[#This Row],[Code Article]],ENTREE!A43:C689,3,FALSE) -> 853 | F96: 0 | G96: =Tableau2[[#This Row],[STOCK FIN DECEMBRE 2024 SAGE]]+Tableau2[[#This Row],[Entrée 01 Janv 2025 au 10 juillet 2026]]-Tableau2[[#This Row],[sortie 01 Janv 2025 au 10 juillet 2026]] -> 1054 | H96: 1054 | I96: =Tableau2[[#This Row],[inventaire juillet 2026 ]]-Tableau2[[#This Row],[stock final au 10 juillet 2026]] -> 0 | K96: 46219 | L96: =VLOOKUP(Tableau2[[#This Row],[Code Article]],'ENTREE APRES INV'!A95:F1104,6,0) -> #N/A | M96: =VLOOKUP(Tableau2[[#This Row],[Code Article]],'SORTIE APRES INV'!A95:D505,4,0) -> #N/A
A97: TCUICBLNEO509GEK | B97: Câble néoprène 5/09 | C97: 15927 | D97: PIE | E97: 0 | F97: =VLOOKUP(Tableau2[[#This Row],[Code Article]],SORTIE!A42:C490,3,FALSE) -> 15927 | G97: =Tableau2[[#This Row],[STOCK FIN DECEMBRE 2024 SAGE]]+Tableau2[[#This Row],[Entrée 01 Janv 2025 au 10 juillet 2026]]-Tableau2[[#This Row],[sortie 01 Janv 2025 au 10 juillet 2026]] -> 0 | I97: =Tableau2[[#This Row],[inventaire juillet 2026 ]]-Tableau2[[#This Row],[stock final au 10 juillet 2026]] -> 0 | K97: 46224 | L97: =VLOOKUP(Tableau2[[#This Row],[Code Article]],'ENTREE APRES INV'!A96:F1105,6,0) -> #N/A | M97: =VLOOKUP(Tableau2[[#This Row],[Code Article]],'SORTIE APRES INV'!A96:D506,4,0) -> #N/A
A98: TCUICBLT982P5GEK | B98: Câble thermo 298 2 paires 5/10 | C98: 2 | D98: PIE | E98: 0 | F98: 0 | G98: =Tableau2[[#This Row],[STOCK FIN DECEMBRE 2024 SAGE]]+Tableau2[[#This Row],[Entrée 01 Janv 2025 au 10 juillet 2026]]-Tableau2[[#This Row],[sortie 01 Janv 2025 au 10 juillet 2026]] -> 2 | H98: 2 | I98: =Tableau2[[#This Row],[inventaire juillet 2026 ]]-Tableau2[[#This Row],[stock final au 10 juillet 2026]] -> 0 | K98: 46216 | L98: =VLOOKUP(Tableau2[[#This Row],[Code Article]],'ENTREE APRES INV'!A97:F1106,6,0) -> #N/A | M98: =VLOOKUP(Tableau2[[#This Row],[Code Article]],'SORTIE APRES INV'!A97:D507,4,0) -> #N/A
A99: TMXTSRVUCHPXXXXX | B99: UNITE CENTRALE HP (SERVEUR) | C99: 1 | D99: PIE | E99: 33 | F99: =VLOOKUP(Tableau2[[#This Row],[Code Article]],SORTIE!A42:C492,3,FALSE) -> 32 | G99: =Tableau2[[#This Row],[STOCK FIN DECEMBRE 2024 SAGE]]+Tableau2[[#This Row],[Entrée 01 Janv 2025 au 10 juillet 2026]]-Tableau2[[#This Row],[sortie 01 Janv 2025 au 10 juillet 2026]] -> 2 | H99: 2 | I99: =Tableau2[[#This Row],[inventaire juillet 2026 ]]-Tableau2[[#This Row],[stock final au 10 juillet 2026]] -> 0 | K99: 46225 | L99: =VLOOKUP(Tableau2[[#This Row],[Code Article]],'ENTREE APRES INV'!A98:F1107,6,0) -> #N/A | M99: =VLOOKUP(Tableau2[[#This Row],[Code Article]],'SORTIE APRES INV'!A98:D508,4,0) -> #N/A
A100: TGSMEMGTDM10DERC | B100: EQUIPPED MAGAZINE/TDM 1001 DC | C100: 31 | D100: PIE | E100: =VLOOKUP(Tableau2[[#This Row],[Code Article]],ENTREE!A44:C697,3,FALSE) -> 5 | F100: =VLOOKUP(Tableau2[[#This Row],[Code Article]],SORTIE!A45:C497,3,FALSE) -> 33 | G100: =Tableau2[[#This Row],[STOCK FIN DECEMBRE 2024 SAGE]]+Tableau2[[#This Row],[Entrée 01 Janv 2025 au 10 juillet 2026]]-Tableau2[[#This Row],[sortie 01 Janv 2025 au 10 juillet 2026]] -> 3 | H100: 3 | I100: =Tableau2[[#This Row],[inventaire juillet 2026 ]]-Tableau2[[#This Row],[stock final au 10 juillet 2026]] -> 0 | K100: 46217 | L100: =VLOOKUP(Tableau2[[#This Row],[Code Article]],'ENTREE APRES INV'!A99:F1108,6,0) -> #N/A | M100: =VLOOKUP(Tableau2[[#This Row],[Code Article]],'SORTIE APRES INV'!A99:D509,4,0) -> #N/A
...

Sheet code sage
A1: CODE ARTICLE | B1: DESIGNATION_ARTICLE | C1: CODE_FAMILLE_ARTICLE | D1: DESIGNATION_FAMILLE | E1: CODE_SOUS_FAMILLE | F1: DESIGN_SOUS_FAMILLE_ART | G1: CLASSE | H1: UNITE | I1: STOCKE | J1: TAUX_TVA | K1: ARTICLE_GENERIQUE | L1: DATE_CREATION | M1: CODE SAGE TELMA | N1: CAT COMPTA TELMA
A2: 10000 | B2: FIXED CELLULAR TERMINAL GSMSLM | C2: TCO | D2: Telecom | E2: TCORADI | F2: Radio | G2: C | H2: PIE | I2: 0.00 | J2: 20.00 | K2: 0 | L2: 1 | M2: TMXTTRLFIXGSMXXX | N2: Equip Mixte-Tech
A3: 10001 | B3: Fixed Optical Attenuator(PCS) OFOAPCS00 | C3: RES | D3: Câbles et réseaux | E3: RESCBLT | F3: Câble Telecom et accessoires | G3: C | H3: PIE | I3: 0.00 | J3: 20.00 | K3: 0 | L3: 1 | M3: TFOXATTFIXOPTHAW | N3: FibreOptique-Fixe
A4: 10002 | B4: Fixed Optical Attenuator,1260nm~1620nm,7dB,LC/PC,45dB SSOPA | C4: TCO | D4: Telecom | E4: TCOTRNS | F4: Transmission | G4: C | H4: PIE | I4: 0.00 | J4: 20.00 | K4: 0 | L4: 1 | M4: TDWMATT1207DLHAW | N4: Réseau d'accès-Fixe
A5: 10003 | B5: Fixed Optical Attenuator,1260nm~1620nm10dBLC/PC45dB SSOPATN | C5: TCO | D5: Telecom | E5: TCOTRNS | F5: Transmission | G5: C | H5: PIE | I5: 0.00 | J5: 20.00 | K5: 0 | L5: 1 | M5: TDWMATT1210DLHAW | N5: Réseau d'accès-Fixe
A6: 10004 | B6: Fixed Optical Attenuator,1260nm~1620nm15dBLC/PC45dB SSOPATN | C6: TCO | D6: Telecom | E6: TCOTRNS | F6: Transmission | G6: C | H6: PIE | I6: 0.00 | J6: 20.00 | K6: 0 | L6: 1 | M6: TDWMATT1215DLHAW | N6: Réseau d'accès-Fixe
A7: 10005 | B7: Fixed Optical Attenuator,1260nm~1620nm5dBLC/PC45dB SSOPATNL | C7: TCO | D7: Telecom | E7: TCOTRNS | F7: Transmission | G7: C | H7: PIE | I7: 0.00 | J7: 20.00 | K7: 0 | L7: 1 | M7: TDWMATT1205DLHAW | N7: Réseau d'accès-Fixe
A8: 10006 | B8: FIXED SHELF FOR CABINET 10P | C8: RES | D8: Câbles et réseaux | E8: RESCBLT | F8: Câble Telecom et accessoires | G8: C | H8: PIE | I8: 0.00 | J8: 20.00 | K8: 0 | L8: 1 | M8: TFOXACCFIXC10XXX | N8: FibreOptique-Fixe
A9: 10007 | B9: FIXING FH ANTENNA SUPPORT | C9: PRM | D9: Prestations de maintenance | E9: PRMBATX | F9: Bâtiments | G9: C | H9: PIE | I9: 0.00 | J9: 20.00 | K9: 0 | L9: 1 | M9: IGCVFIXSUPAFHXXX | N9: GenieCivil-Fixe
A10: 10008 | B10: FLACON BIBON DE H2SO4 (ACIDE SULFURIQUE) | C10: TCO | D10: Telecom | E10: TCORADI | F10: Radio | G10: C | H10: PIE | I10: 0.00 | J10: 20.00 | K10: 0 | L10: 1 | M10: NMXTACDFH2SO4XXX | N10: Equip Mixte-Tech
A11: 10009 | B11: Flacon de DEXID 400 (5cc) | C11: MAT | D11: Matériaux de contruction | E11: MATQUIN | F11: QUINCAILLERIE | G11: C | H11: PIE | I11: 0.00 | J11: 20.00 | K11: 0 | L11: 1 | M11: PENTRDERDEX4005C | N11: Quincaillerie
A12: 10010 | B12: FLACON DISTRIBUTEUR D'ALCOOL | C12: TCO | D12: Telecom | E12: TCORADI | F12: Radio | G12: C | H12: PIE | I12: 0.00 | J12: 20.00 | K12: 0 | L12: 1 | M12: TMXTFLADISALCXXX | N12: Equip Mixte-Tech
A13: 10011 | B13: FLAT CABLE | C13: FRN | D13: Fournitures | E13: FRNPAPF | F13: fournitures&accessoires | G13: C | H13: PIE | I13: 0.00 | J13: 20.00 | K13: 0 | L13: 1 | M13: CINFCBLFLATCBXXX | N13: Frnt de bureau
... A1403: 11399 | B1403: PLC splitter 19, 10x 1:2 SC/APC | C1403: RES | D1403: Câbles et réseaux | E1403: RESCBLT | F1403: Câble Telecom et accessoires | G1403: C | H1403: PIE | I1403: 0.00 | J1403: 20.00 | K1403: 0 | L1403: 1 | M1403: TFOXSPL1912SCSPT | N1403: FibreOptique-Fixe
A1404: 114 | B1404: SUPPORT DE FIXATION BATTERIE | C1404: SOL | D1404: Equipement Solaire | E1404: SOLBATT | F1404: Batterie Solaire | G1404: C | H1404: UN | I1404: 0.00 | J1404: 20.00 | K1404: 0 | L1404: 1 | M1404: NMXTSUPBATXXXXXX
A1405: 11400 | B1405: PLC splitter 19, 6x 1:4 SC/APC | C1405: RES | D1405: Câbles et réseaux | E1405: RESCBLT | F1405: Câble Telecom et accessoires | G1405: C | H1405: PIE | I1405: 0.00 | J1405: 20.00 | K1405: 0 | L1405: 1 | M1405: TFOXSPL1914SCSPT | N1405: FibreOptique-Fixe
A1406: 11401 | B1406: PLC Splitter 1X16 Steel tube with bare fiber SM 1m pigtail | C1406: RES | D1406: Câbles et réseaux | E1406: RESCBLT | F1406: Câble Telecom et accessoires | G1406: C | H1406: PIE | I1406: 0.00 | J1406: 20.00 | K1406: 0 | L1406: 1 | M1406: TFOXSPL116S1MSPT | N1406: FibreOptique-Fixe
A1407: 11402 | B1407: PLC SPLITTER 1X8 STEEL TUBE WITH BARE FIBER SM 1m PIGTAIL A | C1407: RES | D1407: Câbles et réseaux | E1407: RESCBLT | F1407: Câble Telecom et accessoires | G1407: C | H1407: PIE | I1407: 0.00 | J1407: 20.00 | K1407: 0 | L1407: 1 | M1407: TFOXSPL1X8S1MSPT | N1407: FibreOptique-Fixe
A1408: 11403 | B1408: PLC splitter bare fiber, 1:8, 1,5m | C1408: RES | D1408: Câbles et réseaux | E1408: RESCBLT | F1408: Câble Telecom et accessoires | G1408: C | H1408: PIE | I1408: 0.00 | J1408: 20.00 | K1408: 0 | L1408: 1 | M1408: TFOXSPLBF1815SPT | N1408: FibreOptique-Fixe
A1409: 11404 | B1409: Plexi 5mm avec ferneture | C1409: MOE | D1409: Mobilier et équipements | E1409: MOEMOBB | F1409: Mobilier et équipements de bur | G1409: C | H1409: PIE | I1409: 0.00 | J1409: 20.00 | K1409: 0 | L1409: 1 | M1409: AMOIURNPLX5MMXXX | N1409: Mobilier de bureau
A1410: 11405 | B1410: Plinthe 50X85 mm | C1410: TCO | D1410: Telecom | E1410: TCOTRNS | F1410: Transmission | G1410: C | H1410: PIE | I1410: 0.00 | J1410: 20.00 | K1410: 0 | L1410: 1 | M1410: QLCEACCPLINTHXXX | N1410: Accessoires
A1411: 11406 | B1411: PLOT DE LESTAGE CABLE FO EN BETON | C1411: PRM | D1411: Prestations de maintenance | E1411: PRMBATX | F1411: Bâtiments | G1411: C | H1411: PIE | I1411: 0.00 | J1411: 20.00 | K1411: 0 | L1411: 1 | M1411: IGCVPLOCBLBETXXX | N1411: GenieCivil-Fixe
A1412: 11407 | B1412: pluggable client I/F for 1310nm, short reach, industrial tem | C1412: RES | D1412: Câbles et réseaux | E1412: RESCBIA | F1412: Fourn Informatique et accessoi | G1412: C | H1412: PIE | I1412: 0.00 | J1412: 20.00 | K1412: 0 | L1412: 1 | M1412: TSYNCON1310SMOSQ | N1412: Mat Infos
A1413: 11408 | B1413: PLUGIN UNIT/MMU2 B | C1413: TCO | D1413: Telecom | E1413: TCORADI | F1413: Radio | G1413: C | H1413: PIE | I1413: 0.00 | J1413: 20.00 | K1413: 0 | L1413: 1 | M1413: TMXTCRTMMU2BKXXX | N1413: Equip Mixte-Tech
A1414: 11409 | B1414: PLUGIN UNIT/PFM HOD BFB14013/1 | C1414: TCO | D1414: Telecom | E1414: TCOTRNS | F1414: Transmission | G1414: C | H1414: PIE | I1414: 0.00 | J1414: 20.00 | K1414: 0 | L1414: 1 | M1414: TGSNPLGPFMHODERC | N1414: Réseau d'accès-Av
A1415: 11410 | B1415: Plumier de bureau | C1415: FRN | D1415: Fournitures | E1415: FRNPAPF | F1415: fournitures&accessoires | G1415: C | H1415: PIE | I1415: 0.00 | J1415: 20.00 | K1415: 0 | L1415: 1 | M1415: FRNBPLUBURXXX631 | N1415: Frnt de bureau
A1416: 11411 | B1416: PM2200W DC Power Supply | C1416: RES | D1416: Câbles et réseaux | E1416: RESCBLT | F1416: Câble Telecom et accessoires | G1416: C | H1416: PIE | I1416: 0.00 | J1416: 20.00 | K1416: 0 | L1416: 1 | M1416: TFOXPOEPM2200HAW | N1416: FibreOptique-Fixe
... A1525: 11519 | B1525: Powersafe 12V 190Ah | C1525: TCO | D1525: Telecom | E1525: TCORADI | F1525: Radio | G1525: C | H1525: PIE | I1525: 0.00 | J1525: 20.00 | K1525: 0 | L1525: 1 | M1525: NMXTBAT12V190XXX | N1525: Equip Mixte-Tech
A1526: 1152 | B1526: COMBINAISON | C1526: SEC | D1526: Sécurité | E1526: SECSEPI | F1526: EPI | G1526: C | H1526: UN | I1526: 0.00 | J1526: 20.00 | K1526: 0 | L1526: 1 | M1526: HABILCOMBINPLXXX
A1527: 11520 | B1527: POYNTING CELLPHONE BOOSTER ANTENNA | C1527: TCO | D1527: Telecom | E1527: TCORADI | F1527: Radio | G1527: C | H1527: PIE | I1527: 0.00 | J1527: 20.00 | K1527: 0 | L1527: 1 | M1527: TMXTANTBOSCELXXX | N1527: Equip Mixte-Tech
A1528: 11521 | B1528: PP003G LOT 4 DE CARRES GRIS | C1528: MOE | D1528: Mobilier et équipements | E1528: MOEMOBB | F1528: Mobilier et équipements de bur | G1528: C | H1528: PIE | I1528: 0.00 | J1528: 20.00 | K1528: 0 | L1528: 1 | M1528: AMOIACCPP4CGRXXX | N1528: Mobilier de bureau
A1529: 11522 | B1529: PREAMPLIFICATEUR OPTIQUE | C1529: TCO | D1529: Telecom | E1529: TCORADI | F1529: Radio | G1529: C | H1529: PIE | I1529: 0.00 | J1529: 20.00 | K1529: 0 | L1529: 1 | M1529: TFHXAMPPREOPTSGM | N1529: Equip FH-Fixe
A1530: 11523 | B1530: PREDECOUPE | C1530: FRN | D1530: Fournitures | E1530: FRNPAPF | F1530: fournitures&accessoires | G1530: C | H1530: PIE | I1530: 0.00 | J1530: 20.00 | K1530: 0 | L1530: 1 | M1530: FRNBPAPPRDCPEXXX | N1530: Frnt de bureau
A1531: 11524 | B1531: PREPAYE GSM FIXE 1000 UT | C1531: TEL | D1531: Telephonie | E1531: TELTLPH | F1531: Telephone fixe et mobile avec | G1531: C | H1531: PIE | I1531: 0.00 | J1531: 20.00 | K1531: 0 | L1531: 1 | M1531: GSMFIXE1000UT | N1531: Terminaux
A1532: 11525 | B1532: PREPAYE GSM FIXE 1200 UT | C1532: TEL | D1532: Telephonie | E1532: TELTLPH | F1532: Telephone fixe et mobile avec | G1532: C | H1532: PIE | I1532: 0.00 | J1532: 20.00 | K1532: 0 | L1532: 1 | M1532: GSMFIXE1200UT | N1532: Terminaux
A1533: 11526 | B1533: PREPAYE GSM FIXE 150 UT | C1533: TEL | D1533: Telephonie | E1533: TELTLPH | F1533: Telephone fixe et mobile avec | G1533: C | H1533: PIE | I1533: 0.00 | J1533: 20.00 | K1533: 0 | L1533: 1 | M1533: GSMFIXE150UT | N1533: Terminaux
A1534: 11527 | B1534: PREPAYE GSM FIXE 300 UT | C1534: TEL | D1534: Telephonie | E1534: TELTLPH | F1534: Telephone fixe et mobile avec | G1534: C | H1534: PIE | I1534: 0.00 | J1534: 20.00 | K1534: 0 | L1534: 1 | M1534: GSMFIXE300UT | N1534: Terminaux
A1535: 11528 | B1535: PREPAYE GSM FIXE 500 UT | C1535: TEL | D1535: Telephonie | E1535: TELTLPH | F1535: Telephone fixe et mobile avec | G1535: C | H1535: PIE | I1535: 0.00 | J1535: 20.00 | K1535: 0 | L1535: 1 | M1535: GSMFIXE500UT | N1535: Terminaux
A1536: 11529 | B1536: PRESSE ETOUPE | C1536: TCO | D1536: Telecom | E1536: TCORADI | F1536: Radio | G1536: C | H1536: PIE | I1536: 0.00 | J1536: 20.00 | K1536: 0 | L1536: 1 | M1536: NMXTACCPRESETXXX | N1536: Equip Mixte-Tech
A1537: 11530 | B1537: PRESTATION ANIMATEUR | C1537: PRI | D1537: Prestations intellectuelles | E1537: PRICTRL | F1537: Prestation&service externe | G1537: C | H1537: PIE | I1537: 0.00 | J1537: 20.00 | K1537: 0 | L1537: 1 | M1537: PRSTANIMATEURXXX | N1537: Scexterne
A1538: 11531 | B1538: PRESTATION AUTRE FRAIS RH | C1538: PRI | D1538: Prestations intellectuelles | E1538: PRICTRL | F1538: Prestation&service externe | G1538: C | H1538: PIE | I1538: 0.00 | J1538: 20.00 | K1538: 0 | L1538: 1 | M1538: PRSTAUTREFRAISRH | N1538: Scexterne
... A3109: 13309 | B3109: Toner pour imprimante HP127FN-83A | C3109: PRT | D3109: Imprimante et Copieur | E3109: PRTCONS | F3109: Consommable | G3109: C | H3109: PIE | I3109: 0.00 | J3109: 20.00 | K3109: 0 | L3109: 1 | M3109: CINFTONHP127P83A | N3109: Frnt de bureau
A3110: 13310 | B3110: TEINTE | C3110: MAT | D3110: Matériaux de contruction | E3110: MATPEIN | F3110: Peinture, laque et produits d' | G3110: C | H3110: PIE | I3110: 0.00 | J3110: 20.00 | K3110: 0 | L3110: 1 | M3110: 0 | N3110: Achatnontecn
A3111: 13311 | B3111: TROUSSE DE SECOUR GM | C3111: OUT | D3111: Atelier et outillages | E3111: OUTOUTL | F3111: Outillages techniciens | G3111: C | H3111: PIE | I3111: 0.00 | J3111: 20.00 | K3111: 0 | L3111: 1 | M3111: OUTIACCTRSEGMXXX | N3111: Outillage
A3112: 13312 | B3112: Encre canon 24 noir | C3112: PRT | D3112: Imprimante et Copieur | E3112: PRTCONS | F3112: Consommable | G3112: C | H3112: PIE | I3112: 0.00 | J3112: 20.00 | K3112: 0 | L3112: 1 | M3112: CINFENCCAN24N277 | N3112: Frnt de bureau
A3113: 13313 | B3113: ENCRE HP CYAN 201A | C3113: PRT | D3113: Imprimante et Copieur | E3113: PRTCONS | F3113: Consommable | G3113: C | H3113: PIE | I3113: 0.00 | J3113: 20.00 | K3113: 0 | L3113: 1 | M3113: CINFENC201ACYHPX | N3113: Frnt de bureau
A3114: 13314 | B3114: Encre HP Laserjet 201 A Jaune | C3114: PRT | D3114: Imprimante et Copieur | E3114: PRTCONS | F3114: Consommable | G3114: C | H3114: PIE | I3114: 0.00 | J3114: 20.00 | K3114: 0 | L3114: 1 | M3114: CINFENC201AJNHPX | N3114: Frnt de bureau
A3115: 13315 | B3115: Encre HP Laserjet 201A Magenta | C3115: PRT | D3115: Imprimante et Copieur | E3115: PRTCONS | F3115: Consommable | G3115: C | H3115: PIE | I3115: 0.00 | J3115: 20.00 | K3115: 0 | L3115: 1 | M3115: CINFENC201ARGHPX | N3115: Frnt de bureau
A3116: 13316 | B3116: Encre HP Laserjet 1160/49A | C3116: PRT | D3116: Imprimante et Copieur | E3116: PRTCONS | F3116: Consommable | G3116: C | H3116: PIE | I3116: 0.00 | J3116: 20.00 | K3116: 0 | L3116: 1 | M3116: CINFENCHP116049A | N3116: Frnt de bureau
A3117: 13317 | B3117: TIRE FOND 10X80 | C3117: PRM | D3117: Prestations de maintenance | E3117: PRMBATX | F3117: Bâtiments | G3117: C | H3117: PIE | I3117: 0.00 | J3117: 20.00 | K3117: 0 | L3117: 1 | M3117: TMXTTIRF10X80XXX | N3117: Equip Mixte-Tech
A3118: 13318 | B3118: Ubiquiti Omni 5.45 - 5.85 GHz 10dBi Antenna | C3118: VEN | D3118: PRODUITS VENDABLES | E3118: VENSIMR | F3118: SIM & RECHARGES | G3118: C | H3118: PIE | I3118: 0.00 | J3118: 20.00 | K3118: 0 | L3118: 1 | M3118: TMXTANTOM5G10XXX | N3118: Réseau d'accès-Int
A3119: 13319 | B3119: Ubiquiti Rocket 5AC-Lite 5GHz 2x2 802.11ac Access Point US | C3119: VEN | D3119: PRODUITS VENDABLES | E3119: VENSIMR | F3119: SIM & RECHARGES | G3119: C | H3119: PIE | I3119: 0.00 | J3119: 20.00 | K3119: 0 | L3119: 1 | M3119: TMXTANT5ACL5GXXX | N3119: Réseau d'accès-Int
A3120: 13320 | B3120: COLLE FEVICOL SH 250GR - DVI-T - FEVRIER 2022 | C3120: FRN | D3120: Fournitures | E3120: FRNPAPF | F3120: fournitures&accessoires | G3120: C | H3120: PIE | I3120: 0.00 | J3120: 20.00 | K3120: 0 | L3120: 1 | M3120: MDIV000002458XXX | N3120: Accessoires
A3121: 13321 | B3121: SAMSUNG A02 LTE 2+32GB | C3121: TEL | D3121: Telephonie | E3121: TELTLPH | F3121: Telephone fixe et mobile avec | G3121: C | H3121: PIE | I3121: 0.00 | J3121: 20.00 | K3121: 0 | L3121: 1 | M3121: GSM SAMSUNG A02 LTE 2+32GB | N3121: Terminaux
A3122: 13322 | B3122: CABLE SIGNAL MGW3 COAXIAL TSR491620/2000 | C3122: TCO | D3122: Telecom | E3122: TCOTRNS | F3122: Transmission | G3122: C | H3122: PIE | I3122: 0.00 | J3122: 20.00 | K3122: 0 | L3122: 1 | M3122: TCCSMGWCONSCXERC | N3122: Réseau d'accès-Fixe
... A3125: 13325 | B3125: AFFICHE - 90X40CM - TELMA NET REFONTE - FEVRIER 2022 | C3125: FRN | D3125: Fournitures | E3125: FRNPAPF | F3125: fournitures&accessoires | G3125: C | H3125: PIE | I3125: 0.00 | J3125: 20.00 | K3125: 0 | L3125: 1 | M3125: MPRT000002464XXX | N3125: Marketingplv
A3126: 13326 | B3126: BOITE A BORNES D'ESSAI POUR RESEAU TRIPHASE 4 FILS | C3126: ELE | D3126: Electricité | E3126: ELECBLI | F3126: Câblage et interrupteur | G3126: C | H3126: PIE | I3126: 0.00 | J3126: 20.00 | K3126: 0 | L3126: 1 | M3126: 0 | N3126: 0
A3127: 13327 | B3127: POTELET EN FER | C3127: INF | D3127: Infrastructure Telecom | E3127: INFPOTO | F3127: Poteaux | G3127: C | H3127: PIE | I3127: 0.00 | J3127: 20.00 | K3127: 0 | L3127: 1 | M3127: 0 | N3127: 0
A3128: 13328 | B3128: IMPERMEABLE PONCHO | C3128: GOO | D3128: Goodies | E3128: GOOHABI | F3128: Habillement | G3128: C | H3128: PIE | I3128: 0.00 | J3128: 20.00 | K3128: 0 | L3128: 1 | M3128: HABILTECPONIMXXX | N3128: Achatnontecn
A3129: 13329 | B3129: FSCOM HW LE2MXSC80FF0 Compatible 10GBASE-ZR SFP+ 1550nm 80km | C3129: GOO | D3129: Goodies | E3129: GOOHABI | F3129: Habillement | G3129: C | H3129: PIE | I3129: 0.00 | J3129: 20.00 | K3129: 0 | L3129: 1 | M3129: TIPMSFP10Z158FSC | N3129: Réseau d'accès-Fixe
A3130: 13330 | B3130: BOUTEILLE D EAU de 0,5L | C3130: GOO | D3130: Goodies | E3130: GOOHABI | F3130: Habillement | G3130: C | H3130: PIE | I3130: 0.00 | J3130: 20.00 | K3130: 0 | L3130: 1 | M3130: EAUREPBT05NATURE | N3130: Consommation
A3131: 13331 | B3131: BATTERIE A PLOMB OUVERT 1830Ah 2V ETERNITY | C3131: SOL | D3131: Equipement Solaire | E3131: SOLBATT | F3131: Batterie Solaire | G3131: C | H3131: PIE | I3131: 0.00 | J3131: 20.00 | K3131: 0 | L3131: 1 | M3131: 0 | N3131: 0
A3132: 13332 | B3132: BATTERIE A PLOMB OUVERT 2250Ah 2V ETERNITY | C3132: SOL | D3132: Equipement Solaire | E3132: SOLBATT | F3132: Batterie Solaire | G3132: C | H3132: PIE | I3132: 0.00 | J3132: 20.00 | K3132: 0 | L3132: 1 | M3132: 0 | N3132: 0
A3133: 13333 | B3133: DISJONCTEUR MODULAIRE 1PC125A SCHNEIDER | C3133: ELE | D3133: Electricité | E3133: ELECBLI | F3133: Câblage et interrupteur | G3133: C | H3133: PIE | I3133: 0.00 | J3133: 20.00 | K3133: 0 | L3133: 1 | M3133: 0 | N3133: 0
A3134: 13334 | B3134: DISJONCTEUR MODULAIRE 2PC125A SCHNEIDER | C3134: ELE | D3134: Electricité | E3134: ELECBLI | F3134: Câblage et interrupteur | G3134: C | H3134: PIE | I3134: 0.00 | J3134: 20.00 | K3134: 0 | L3134: 1 | M3134: 0 | N3134: 0
A3135: 13335 | B3135: DISJONCTEUR MODULAIRE 1PC02A ABB | C3135: ELE | D3135: Electricité | E3135: ELECBLI | F3135: Câblage et interrupteur | G3135: C | H3135: PIE | I3135: 0.00 | J3135: 20.00 | K3135: 0 | L3135: 1 | M3135: 0 | N3135: 0
A3136: 13336 | B3136: DISJONCTEUR MODULAIRE 1PC06A ABB | C3136: ELE | D3136: Electricité | E3136: ELECBLI | F3136: Câblage et interrupteur | G3136: C | H3136: PIE | I3136: 0.00 | J3136: 20.00 | K3136: 0 | L3136: 1 | M3136: 0 | N3136: 0
A3137: 13337 | B3137: DISJONCTEUR MODULAIRE 1PC20A ABB | C3137: ELE | D3137: Electricité | E3137: ELECBLI | F3137: Câblage et interrupteur | G3137: C | H3137: PIE | I3137: 0.00 | J3137: 20.00 | K3137: 0 | L3137: 1 | M3137: 0 | N3137: 0
A3138: 13338 | B3138: TAXE SUR LES PYLONES | C3138: IMP | D3138: Impôts et Taxes | E3138: IMPTAXE | F3138: Taxe divers | G3138: C | H3138: PIE | I3138: 0.00 | J3138: 0.00 | K3138: 0 | L3138: 1 | M3138: PRSTACCTAXPYLXXX | N3138: Taxe
A3139: 13340 | B3139: Assurance Bureau Incendie - MRD - RC | C3139: RCI | D3139: RC et Immo | E3139: RCIRCSC | F3139: Responsabilité civile et socié | G3139: C | H3139: PIE | I3139: 0.00 | J3139: 20.00 | K3139: 0 | L3139: 1 | M3139: 0 | N3139: Assurance
A3140: 13341 | B3140: Assurance Magasin Incendie - MRD - RC | C3140: RCI | D3140: RC et Immo | E3140: RCIRCSC | F3140: Responsabilité civile et socié | G3140: C | H3140: PIE | I3140: 0.00 | J3140: 20.00 | K3140: 0 | L3140: 1 | M3140: 0 | N3140: Assurance
A3141: 13342 | B3141: Assurance personnel contre les accidents | C3141: RCI | D3141: RC et Immo | E3141: RCIRCSC | F3141: Responsabilité civile et socié | G3141: C | H3141: PIE | I3141: 0.00 | J3141: 20.00 | K3141: 0 | L3141: 1 | M3141: 0 | N3141: Assurance
A3142: 13343 | B3142: Assurance Site PICOM incendie - MRD – RC | C3142: RCI | D3142: RC et Immo | E3142: RCIRCSC | F3142: Responsabilité civile et socié | G3142: C | H3142: PIE | I3142: 0.00 | J3142: 20.00 | K3142: 0 | L3142: 1 | M3142: 0 | N3142: Assurance
A3143: 13344 | B3143: Assurance Site TOM Incendie - MRD - RC | C3143: RCI | D3143: RC et Immo | E3143: RCIRCSC | F3143: Responsabilité civile et socié | G3143: C | H3143: PIE | I3143: 0.00 | J3143: 20.00 | K3143: 0 | L3143: 1 | M3143: 0 | N3143: Assurance
A3144: 13345 | B3144: Autres Assurances | C3144: RCI | D3144: RC et Immo | E3144: RCIRCSC | F3144: Responsabilité civile et socié | G3144: C | H3144: PIE | I3144: 0.00 | J3144: 20.00 | K3144: 0 | L3144: 1 | M3144: PRSTATRASS001XXX | N3144: Assurance
A3145: 13347 | B3145: COURONNE NOEL 2021 - MARS 2022 | C3145: GOO | D3145: Goodies | E3145: GOOHABI | F3145: Habillement | G3145: C | H3145: PIE | I3145: 0.00 | J3145: 20.00 | K3145: 0 | L3145: 1 | M3145: MGDI000002468XXX | N3145: ComHorsMedia
A3146: 13348 | B3146: BRETELLE NOEL 2021 - MARS 2022 | C3146: GOO | D3146: Goodies | E3146: GOOHABI | F3146: Habillement | G3146: C | H3146: PIE | I3146: 0.00 | J3146: 20.00 | K3146: 0 | L3146: 1 | M3146: MGDI000002469XXX | N3146: ComHorsMedia
A3147: 13349 | B3147: AFFICHE - 40X60CM - MBALIK HOME 60 - MARS 2022 | C3147: GOO | D3147: Goodies | E3147: GOOHABI | F3147: Habillement | G3147: C | H3147: PIE | I3147: 0.00 | J3147: 20.00 | K3147: 0 | L3147: 1 | M3147: MPRT000002470XXX | N3147: Marketingplv
A3148: 13350 | B3148: Casque escalade EN397 | C3148: GOO | D3148: Goodies | E3148: GOOHABI | F3148: Habillement | G3148: C | H3148: PIE | I3148: 0.00 | J3148: 20.00 | K3148: 0 | L3148: 1 | M3148: HABICSQESCEN397X | N3148: Achatnontecn
A3149: 13351 | B3149: Gant refueling Latex rouge EN374 | C3149: GOO | D3149: Goodies | E3149: GOOHABI | F3149: Habillement | G3149: C | H3149: PIE | I3149: 0.00 | J3149: 20.00 | K3149: 0 | L3149: 1 | M3149: HABIGNTRGEEN374X | N3149: Achatnontecn
A3150: 13352 | B3150: Casque antibruit EN 352 | C3150: GOO | D3150: Goodies | E3150: GOOHABI | F3150: Habillement | G3150: C | H3150: PIE | I3150: 0.00 | J3150: 20.00 | K3150: 0 | L3150: 1 | M3150: HABICSQANTEN352X | N3150: AchattecnFixe
A3151: 13353 | B3151: ALCOTEST | C3151: GOO | D3151: Goodies | E3151: GOOHABI | F3151: Habillement | G3151: C | H3151: PIE | I3151: 0.00 | J3151: 20.00 | K3151: 0 | L3151: 1 | M3151: OUTILALCOTESTXXX | N3151: Achatnontecn
A3152: 13354 | B3152: IMPRIMANTE LASERJET PRO MFP M130FN | C3152: GOO | D3152: Goodies | E3152: GOOHABI | F3152: Habillement | G3152: C | H3152: PIE | I3152: 0.00 | J3152: 20.00 | K3152: 0 | L3152: 1 | M3152: CINFIPMM130FNHPX | N3152: Mat Infos
A3153: 13355 | B3153: Clamps for Fiber and Power Cab | C3153: GOO | D3153: Goodies | E3153: GOOHABI | F3153: Habillement | G3153: C | H3153: PIE | I3153: 0.00 | J3153: 20.00 | K3153: 0 | L3153: 1 | M3153: TGSMACCCFPC10ERK | N3153: Equip Mixte-ImmoCop
A3154: 13356 | B3154: MOTO HONDA 125 ACE TFH TUF TAXI | C3154: GOO | D3154: Goodies | E3154: GOOHABI | F3154: Habillement | G3154: C | H3154: PIE | I3154: 0.00 | J3154: 20.00 | K3154: 0 | L3154: 1 | M3154: VMOTMTOHD125TXXX | N3154: Achatnontecn
A3155: 13358 | B3155: SABRE DE JAUGEAGE SANS CURSEUR PIGE 500MM | C3155: GOO | D3155: Goodies | E3155: GOOHABI | F3155: Habillement | G3155: C | H3155: PIE | I3155: 0.00 | J3155: 20.00 | K3155: 0 | L3155: 1 | M3155: NMXTAPMSJAUG5XXX | N3155: Equip Mixte-Tech
... A3196: 13399 | B3196: REGULATEUR AVR | C3196: PCL | D3196: PC et Laptop | E3196: PCLPACC | F3196: Périphérique&accessoire divers | G3196: C | H3196: PIE | I3196: 0.00 | J3196: 20.00 | K3196: 0 | L3196: 1 | M3196: NMXTAGREGULXXXXX | N3196: Equip Mixte
A3197: 13400 | B3197: CABLE PREASSEMBLE ALU TORSADE 3X25MM2+1X16MM2+1X54H6MM2 | C3197: ELE | D3197: Electricité | E3197: ELECBLI | F3197: Câblage et interrupteur | G3197: C | H3197: M | I3197: 0.00 | J3197: 20.00 | K3197: 0 | L3197: 1 | M3197: 0 | N3197: 0
A3198: 13402 | B3198: SP1799 - CABLE DE RACCORDEMENT 2 FIBRE MULTI-USAGE 657A | C3198: PRM | D3198: Prestations de maintenance | E3198: PRMEQUI | F3198: Equipements | G3198: C | H3198: PIE | I3198: 0.00 | J3198: 20.00 | K3198: 0 | L3198: 1 | M3198: TFOXCBLR2FOXXNEX | N3198: Réseau d'accès-Fixe
A3199: 13403 | B3199: HT2650 Cellular Backhaul Satellite Router with TDMReturn, -4 | C3199: PRM | D3199: Prestations de maintenance | E3199: PRMEQUI | F3199: Equipements | G3199: C | H3199: PIE | I3199: 0.00 | J3199: 20.00 | K3199: 0 | L3199: 1 | M3199: TVSTRTRHT2650AMO | N3199: Equip Mixte-Tech
A3200: 13404 | B3200: 1.8m C-Band Linear antenna with circular pol | C3200: PRM | D3200: Prestations de maintenance | E3200: PRMEQUI | F3200: Equipements | G3200: C | H3200: PIE | I3200: 0.00 | J3200: 20.00 | K3200: 0 | L3200: 1 | M3200: TVSTANT18MCLNHNS | N3200: Equip Mixte-Tech
A3201: 13405 | B3201: 5W BUC, C-Band | C3201: PRM | D3201: Prestations de maintenance | E3201: PRMEQUI | F3201: Equipements | G3201: C | H3201: PIE | I3201: 0.00 | J3201: 20.00 | K3201: 0 | L3201: 1 | M3201: TVSTAMP5WCBUCHNS | N3201: Equip Mixte-Tech
A3202: 13406 | B3202: LNB Ext C-band | C3202: PRM | D3202: Prestations de maintenance | E3202: PRMEQUI | F3202: Equipements | G3202: C | H3202: PIE | I3202: 0.00 | J3202: 20.00 | K3202: 0 | L3202: 1 | M3202: TVSTSREXCBLNBHNS | N3202: Equip Mixte-Tech
A3203: 13407 | B3203: Cable Coax RG-11 type Non Plenum 1000' | C3203: PRM | D3203: Prestations de maintenance | E3203: PRMEQUI | F3203: Equipements | G3203: C | H3203: PIE | I3203: 0.00 | J3203: 20.00 | K3203: 0 | L3203: 1 | M3203: TVSTCBLIFRG11HNS | N3203: Equip Mixte-Tech
A3204: 13408 | B3204: KIT, CONN F-TYPE COMP, RG-11, (COMPRESSIONTYPE) | C3204: PRM | D3204: Prestations de maintenance | E3204: PRMEQUI | F3204: Equipements | G3204: C | H3204: PIE | I3204: 0.00 | J3204: 20.00 | K3204: 0 | L3204: 1 | M3204: TVSTCONIFRG11HNS | N3204: Equip Mixte-Tech
A3205: 13409 | B3205: AMPLI 5 watt BUC | C3205: PRM | D3205: Prestations de maintenance | E3205: PRMEQUI | F3205: Equipements | G3205: C | H3205: PIE | I3205: 0.00 | J3205: 20.00 | K3205: 0 | L3205: 1 | M3205: TVSTAMP5WABUCHGS | N3205: Equip Mixte-Tech
A3206: 13410 | B3206: POST IT GM COULEUR | C3206: PRM | D3206: Prestations de maintenance | E3206: PRMEQUI | F3206: Equipements | G3206: C | H3206: PIE | I3206: 0.00 | J3206: 20.00 | K3206: 0 | L3206: 1 | M3206: FRNBPSIGMCOUL648 | N3206: Frnt de bureau
A3207: 13413 | B3207: Baseband 5216 Digital Unit (with security) KDU137925/31 | C3207: PRM | D3207: Prestations de maintenance | E3207: PRMEQUI | F3207: Equipements | G3207: C | H3207: PIE | I3207: 0.00 | J3207: 20.00 | K3207: 0 | L3207: 1 | M3207: TGSMPROBB5216ERC | N3207: Equip FH-Av
A3208: 13414 | B3208: COMBINED UNIT/Baseband 6620 with fan_KDV127620/11 | C3208: PRM | D3208: Prestations de maintenance | E3208: PRMEQUI | F3208: Equipements | G3208: C | H3208: PIE | I3208: 0.00 | J3208: 20.00 | K3208: 0 | L3208: 1 | M3208: TGSMCRTBB6620ERC | N3208: Equip FH-Av
A3209: 13415 | B3209: PROCESSOR UNIT Baseband R503 Auxiliary KDU137949 1 | C3209: PRM | D3209: Prestations de maintenance | E3209: PRMEQUI | F3209: Equipements | G3209: C | H3209: PIE | I3209: 0.00 | J3209: 20.00 | K3209: 0 | L3209: 1 | M3209: TGSMPRUBBR503ERC | N3209: Equip FH-Av
...

Sheet SORTIE
A1: CODES | B1: designation | C1: QUANTITE | D1: date sortie | E1: verif sage
A2: TGSMTRC2219B8ERC | B2: Radio 2219 B8 Radio Unit | C2: 739 | D2: 45792 | E2: =VLOOKUP(A2,Tableau2[[Code Article]:[inventaire juillet 2026 ]],8,FALSE) -> 90
A3: TWMXIDUMBSCCHALV | B3: ALVARION | C3: 20 | D3: 45799 | E3: =VLOOKUP(A3,Tableau2[[Code Article]:[inventaire juillet 2026 ]],8,FALSE) -> 8
A4: TGSMCBLRTZ500ERC | B4: IF CABLE 7,6mm / TZC50097(500m) | C4: 16573 | D4: 45664 | E4: =VLOOKUP(A4,Tableau2[[Code Article]:[inventaire juillet 2026 ]],8,FALSE) -> 0
A5: TGSMTRC2219B3ERC | B5: Radio 2219 B3 Radio Unit_KRC161619/1 | C5: 559 | D5: 45666 | E5: =VLOOKUP(A5,Tableau2[[Code Article]:[inventaire juillet 2026 ]],8,FALSE) -> 9
A6: TGSMCBL78F500ERK | B6: """ FEEDER CABLE 7/8"""" 500M (01 DRUM OF 500M) """ | C6: 883 | D6: 45671 | E6: =VLOOKUP(A6,Tableau2[[Code Article]:[inventaire juillet 2026 ]],8,FALSE) -> 0
A7: TGSMPRUDUS411ERC | B7: "DUS 41 01,Digital unit" | C7: 4 | D7: 45673 | E7: =VLOOKUP(A7,Tableau2[[Code Article]:[inventaire juillet 2026 ]],8,FALSE) -> 5
A8: TGSMPROUDUW31ERC | B8: "DUW, 31 01 Digital Unit" | C8: 134 | D8: 45674 | E8: =VLOOKUP(A8,Tableau2[[Code Article]:[inventaire juillet 2026 ]],8,FALSE) -> 4
A9: TGSMPROUDUG20ERK | B9: PROCESSOR UNIT DUG 20 01,Digit | C9: 240 | D9: 45678 | E9: =VLOOKUP(A9,Tableau2[[Code Article]:[inventaire juillet 2026 ]],8,FALSE) -> 29
A10: TGSMCBLJU413MERC | B10: Rosenberger 1/2" jumper cable, | C10: 3063 | D10: 45680 | E10: =VLOOKUP(A10,Tableau2[[Code Article]:[inventaire juillet 2026 ]],8,FALSE) -> 0
A11: TGSMTRCRUS1B3ERC | B11: "TRANSCEIVER/RRUS 01 B3,Radio | C11: 11 | D11: 45790 | E11: =VLOOKUP(A11,Tableau2[[Code Article]:[inventaire juillet 2026 ]],8,FALSE) -> 1
A12: TGSMTRCRUS1B8ERC | B12: "TRANSCEIVER/RRUS 01B8,Radio U | C12: 95 | D12: 45685 | E12: =VLOOKUP(A12,Tableau2[[Code Article]:[inventaire juillet 2026 ]],8,FALSE) -> 0
A13: TGSMANTTC3HXXERC | B13: ANTENNA TRIPLE COLUMN 3H_61774 | C13: 36 | D13: 45720 | E13: =VLOOKUP(A13,Tableau2[[Code Article]:[inventaire juillet 2026 ]],8,FALSE) -> 0
... A45: TGSMANTM0678HERC | B45: ANTENNA/ANTm 0.6 7/8 HP/HPX | C45: 242 | D45: 45755 | E45: =VLOOKUP(A45,Tableau2[[Code Article]:[inventaire juillet 2026 ]],8,FALSE) -> 0
A46: TGSMANTDBC2HXERC | B46: ANTENNA DUAL COLUMN BAND 2H_61 | C46: 58 | D46: 30/01/25 ET 08/05/26 | E46: =VLOOKUP(A46,Tableau2[[Code Article]:[inventaire juillet 2026 ]],8,FALSE) -> 9
A47: TGSMANTXPL84XERK | B47: ANTENNA XPOL C-PANEL 806-960/8 | C47: 2 | D47: 45687 | E47: =VLOOKUP(A47,Tableau2[[Code Article]:[inventaire juillet 2026 ]],8,FALSE) -> 0
A48: TFHMANT30315HERC | B48: ANTENNA/ANTm 0.3 15 HP/HPX | C48: 50 | D48: 45792 | E48: =VLOOKUP(A48,Tableau2[[Code Article]:[inventaire juillet 2026 ]],8,FALSE) -> 0
A49: TGSMANTM0915HERC | B49: ANTENNA/ANTm 0.9 15 HP/HPX | C49: 44 | D49: 45799 | E49: =VLOOKUP(A49,Tableau2[[Code Article]:[inventaire juillet 2026 ]],8,FALSE) -> 0
A50: TGSMANT2478HPERK | B50: ANTENNE 2.4 | C50: 61 | D50: 45664 | E50: =VLOOKUP(A50,Tableau2[[Code Article]:[inventaire juillet 2026 ]],8,FALSE) -> 0
A51: MDIV000000354XXX | B51: ANTENNE 2STUCK LAT 56 DUO SET | C51: 1 | D51: 45666 | E51: =VLOOKUP(A51,Tableau2[[Code Article]:[inventaire juillet 2026 ]],8,FALSE) -> 0
A52: ANTINDOORHUAWEI | B52: ANTENNE CDMA | C52: 3 | D52: 45671 | E52: =VLOOKUP(A52,Tableau2[[Code Article]:[inventaire juillet 2026 ]],8,FALSE) -> 0
A53: TGSMANT127G11ERC | B53: ANTENNE FH 1.2 ERICSSON | C53: 180 | D53: 45673 | E53: =VLOOKUP(A53,Tableau2[[Code Article]:[inventaire juillet 2026 ]],8,FALSE) -> 0
A54: TGSMANT3BX790ERK | B54: ANTENNE Triple band antenna,XX | C54: 48 | D54: 45674 | E54: =VLOOKUP(A54,Tableau2[[Code Article]:[inventaire juillet 2026 ]],8,FALSE) -> 0
A55: ISPTISPANT519120UBI | B55: ANTENNE UBIQUITI | C55: 3 | D55: 45678 | E55: =VLOOKUP(A55,Tableau2[[Code Article]:[inventaire juillet 2026 ]],8,FALSE) -> 6
A56: TGSMANTDB8790ERC | B56: ANTENNE X/X-pol,790-960/1710-2170MHz,65/65deg,17.5/19.5dBiMET0-8 | C56: 12 | D56: 45680 | E56: =VLOOKUP(A56,Tableau2[[Code Article]:[inventaire juillet 2026 ]],8,FALSE) -> 0
A57: TGSMANTSB1790ERK | B57: ANTENNE X-pol.790-960MHz,65deg | C57: 63 | D57: 45790 | E57: =VLOOKUP(A57,Tableau2[[Code Article]:[inventaire juillet 2026 ]],8,FALSE) -> 0
A58: TGSMANTSECDBDERK | B58: ANTENNES SECTORIELLES DOUBLE | C58: 42 | D58: 45685 | E58: =VLOOKUP(A58,Tableau2[[Code Article]:[inventaire juillet 2026 ]],8,FALSE) -> 0
... A88: TGSMBAT6313XXERC | B88: Battery 6313_BKB90290/2 | C88: 1 | D88: 45694 | E88: =VLOOKUP(A88,Tableau2[[Code Article]:[inventaire juillet 2026 ]],8,FALSE) -> 0
A89: NMXTBATC90C5BXXX | B89: BATTERY CABLE HALOGEN FREE, 90C, 50MM2 BLACK,TFL103106 00 | C89: 330 | D89: 11/07/25 et 05/12/25 | E89: =VLOOKUP(A89,Tableau2[[Code Article]:[inventaire juillet 2026 ]],8,FALSE) -> 28
A90: NMXTCBL90C35MERC | B90: Battery Cable, Halogenfree, 90 C, 35 MM2, GREY, 30 m | C90: 5 | D90: 05/03/25 et 07/11/25 | E90: =VLOOKUP(A90,Tableau2[[Code Article]:[inventaire juillet 2026 ]],8,FALSE) -> 0
A91: TGSMBFU0103BFERC | B91: BATTERY FUSE UNIT BFU 01 03 Battery Fuse | C91: 22 | D91: 05/03/25 et 07/11/25 | E91: =VLOOKUP(A91,Tableau2[[Code Article]:[inventaire juillet 2026 ]],8,FALSE) -> 0
A92: NMXTBAT48V60AERC | B92: Battery Set 48V / 60Ah NSB Silver FT | C92: 28 | D92: 05/03/25 et 07/11/25 | E92: =VLOOKUP(A92,Tableau2[[Code Article]:[inventaire juillet 2026 ]],8,FALSE) -> 0
A93: NMXTBAT100BLUERC | B93: BATTERY/NSB 100 BLUE+ (4x12V) 100Ah_BKC90106/160 | C93: 21 | D93: 05/03/25 et 07/11/25 | E93: =VLOOKUP(A93,Tableau2[[Code Article]:[inventaire juillet 2026 ]],8,FALSE) -> 0
A94: TGSMBBSOU6102ERC | B94: BBS 6102 | C94: 1 | D94: 05/03/25 et 07/11/25 | E94: =VLOOKUP(A94,Tableau2[[Code Article]:[inventaire juillet 2026 ]],8,FALSE) -> 0
A95: TGSMBFU0101BFERC | B95: BFU 0101 | C95: 4 | D95: 05/03/25 et 07/11/25 | E95: =VLOOKUP(A95,Tableau2[[Code Article]:[inventaire juillet 2026 ]],8,FALSE) -> 4
A96: TGSMBFU0102BFERC | B96: BFU0102 | C96: 15 | D96: 05/03/25 et 07/11/25 | E96: =VLOOKUP(A96,Tableau2[[Code Article]:[inventaire juillet 2026 ]],8,FALSE) -> 0
A97: NMXTBIDVIDXXXXXX | B97: BIDON VIDE | C97: 69 | D97: 05/03/25 et 07/11/25 | E97: =VLOOKUP(A97,Tableau2[[Code Article]:[inventaire juillet 2026 ]],8,FALSE) -> 0
A98: TMXTRTROHG85HHAW | B98: HUAWEI(divers) | C98: 171 | D98: 05/03/25 et 07/11/25 | E98: =VLOOKUP(A98,Tableau2[[Code Article]:[inventaire juillet 2026 ]],8,FALSE) -> 15
A99: MPLV000004128XXX | B99: BUNTING TELMA/MVOLA | C99: 1 | D99: 05/03/25 et 07/11/25 | E99: =VLOOKUP(A99,Tableau2[[Code Article]:[inventaire juillet 2026 ]],8,FALSE) -> 0
A100: TFOXCBLOP12STXXX | B100: cable 12FO coupon | C100: 2588 | D100: 05/03/25 et 07/11/25 | E100: =VLOOKUP(A100,Tableau2[[Code Article]:[inventaire juillet 2026 ]],8,FALSE) -> 0
... A103: TFOXCBLS2FMUAPHO | B103: CABLE 2FO | C103: 1095 | D103: 05/03/25 et 07/11/25 | E103: =VLOOKUP(A103,Tableau2[[Code Article]:[inventaire juillet 2026 ]],8,FALSE) -> 0
A104: TFOXCBL48FOMUGEK | B104: CABLE 48FO | C104: 354 | D104: 45792 | E104: =VLOOKUP(A104,Tableau2[[Code Article]:[inventaire juillet 2026 ]],8,FALSE) -> 0
A105: FIXTCUICBL74X286GEK | B105: CABLE 74-56-8 | C105: 10 | D105: 45799 | E105: =VLOOKUP(A105,Tableau2[[Code Article]:[inventaire juillet 2026 ]],8,FALSE) -> 0
A106: FIXTCUICBL74X566GEK | B106: CABLE 78-28-8 | C106: 15 | D106: 45664 | E106: =VLOOKUP(A106,Tableau2[[Code Article]:[inventaire juillet 2026 ]],8,FALSE) -> 0
A107: TFOXCBL96FOMUGEK | B107: Cable 96FO | C107: 60 | D107: 45666 | E107: =VLOOKUP(A107,Tableau2[[Code Article]:[inventaire juillet 2026 ]],8,FALSE) -> 0
A108: TGSMCBLRPM517XXX | B108: Cable avec connection Norel (RPM 517560/5000) AC3 Bleu | C108: 110 | D108: 45671 | E108: =VLOOKUP(A108,Tableau2[[Code Article]:[inventaire juillet 2026 ]],8,FALSE) -> 0
A109: TFHXCBLIFCOAXNEC | B109: CABLE COAXIAL | C109: 193 | D109: 45673 | E109: =VLOOKUP(A109,Tableau2[[Code Article]:[inventaire juillet 2026 ]],8,FALSE) -> 0
A110: TCUICBLNEO599GEK | B110: Cable néo coupon 10M*10 | C110: 22307 | D110: 45674 | E110: =VLOOKUP(A110,Tableau2[[Code Article]:[inventaire juillet 2026 ]],8,FALSE) -> 0
A111: TCUICBLNEO509GEK | B111: CABLE néoprene | C111: 15927 | D111: 07/11/25 et 07/04/26 | E111: =VLOOKUP(A111,Tableau2[[Code Article]:[inventaire juillet 2026 ]],8,FALSE) -> 0
A112: NMXTCBL6M35YGERC | B112: CABLE SET/Grounding cable set, 35mm¦, 6 | C112: 98 | D112: 45678 | E112: =VLOOKUP(A112,Tableau2[[Code Article]:[inventaire juillet 2026 ]],8,FALSE) -> 35
A113: MDIV000000076XXX | B113: CABLE VERT JAUNE | C113: 1 | D113: 45680 | E113: =VLOOKUP(A113,Tableau2[[Code Article]:[inventaire juillet 2026 ]],8,FALSE) -> 0
A114: TGSMCBLR01600ERC | B114: CABLE WITH CONNECTOR RPM77701/00600 | C114: 10 | D114: 45792 | E114: =VLOOKUP(A114,Tableau2[[Code Article]:[inventaire juillet 2026 ]],8,FALSE) -> 0
A115: TGSMCBL2LC670ERC | B115: CABLE WITH CONNECTOR/2F LC(FullAXS)-LC S | C115: 2217 | D115: 45799 | E115: =VLOOKUP(A115,Tableau2[[Code Article]:[inventaire juillet 2026 ]],8,FALSE) -> 0
A116: TGSMCBLCPC160ERC | B116: CABLE WITH CONNECTOR/DC POWER CABLE - RPM777193/00160 | C116: 25 | D116: 45664 | E116: =VLOOKUP(A116,Tableau2[[Code Article]:[inventaire juillet 2026 ]],8,FALSE) -> 0
A117: TGSMCBLC93006ERC | B117: CABLE WITH CONNECTOR/DC POWER CABLE - RPM777193/00600 | C117: 30 | D117: 45666 | E117: =VLOOKUP(A117,Tableau2[[Code Article]:[inventaire juillet 2026 ]],8,FALSE) -> 0
A118: TGSMCBLCPC800ERC | B118: CABLE WITH CONNECTOR/DC POWER CABLE - RPM777193/00800 | C118: 22 | D118: 45671 | E118: =VLOOKUP(A118,Tableau2[[Code Article]:[inventaire juillet 2026 ]],8,FALSE) -> 0
A119: TGSMCBLCPC550ERC | B119: CABLE WITH CONNECTOR/DC POWER CABLE - RPM777193/550 | C119: 41 | D119: 45673 | E119: =VLOOKUP(A119,Tableau2[[Code Article]:[inventaire juillet 2026 ]],8,FALSE) -> 0
A120: TGSMCBLC93100ERC | B120: CABLE WITH CONNECTOR/DC POWER CABLE RPM777193/01000 | C120: 71 | D120: 45674 | E120: =VLOOKUP(A120,Tableau2[[Code Article]:[inventaire juillet 2026 ]],8,FALSE) -> 45
A121: TGSMCBLCODC22ERC | B121: CABLE WITH CONNECTOR/DC,2x2,5mm2,1m | C121: 26 | D121: 45678 | E121: =VLOOKUP(A121,Tableau2[[Code Article]:[inventaire juillet 2026 ]],8,FALSE) -> 0
A122: TGSMCBLGRPM25ERC | B122: CABLE WITH CONNECTOR/Grounding Cable_RPM777567/02500 | C122: 32 | D122: 45680 | E122: =VLOOKUP(A122,Tableau2[[Code Article]:[inventaire juillet 2026 ]],8,FALSE) -> 2
A123: TGSMCBLCPC715ERC | B123: CABLE WITH CONNECTOR/POWER CABLE RPM 919715/02000 | C123: 60 | D123: 45790 | E123: =VLOOKUP(A123,Tableau2[[Code Article]:[inventaire juillet 2026 ]],8,FALSE) -> 0
... A456: TGSMRAU4428B3ERC | B456: Radio 4428 B3 KRC161713 1 | C456: 240 | D456: 46212 | E456: =VLOOKUP(A456,Tableau2[[Code Article]:[inventaire juillet 2026 ]],8,FALSE) -> 8

Sheet ENTREE APRES INV
A1: CODE ARTICLE | B1: PROVENANCE | C1: DESIGNATION | D1: REF FMR | E1: DATE DE RECEPTION | F1: QUANTITE RECU | G1: UNITE | H1: LOCAL | I1: STATU | J1: OBSERVATION | K1: PRESTATAIRE
A2: ISPTMXTRTR951UI2XXX | B2: ANALAKELY 3M ETAGE | C2: ROUTERBOARD RB951UI-2HND | D2: 4023/26/DTG/LOG | E2: 46226 | F2: 1 | G2: PIE | H2: Ilafy | I2: RECU | J2: A METTRE AU REBUT | K2: DTG
A3: ISPTMXTRTR951UI2XXX | B3: ANALAKELY 3M ETAGE | C3: ROUTERBOARD RB951UI-2HND | D3: 4023/26/DTG/LOG | E3: 46226 | F3: 1 | G3: PIE | H3: Ilafy | I3: RECU | J3: A METTRE AU REBUT | K3: DTG
A4: ISPTMXTRTR951UI2XXX | B4: ANALAKELY 3M ETAGE | C4: ROUTERBOARD RB951UI-2HND | D4: 4023/26/DTG/LOG | E4: 46226 | F4: 1 | G4: PIE | H4: Ilafy | I4: RECU | J4: A METTRE AU REBUT | K4: DTG
A5: ISPTMXTRTR951UI2XXX | B5: ANALAKELY 3M ETAGE | C5: ROUTERBOARD RB951UI-2HND | D5: 4023/26/DTG/LOG | E5: 46226 | F5: 1 | G5: PIE | H5: Ilafy | I5: RECU | J5: A METTRE AU REBUT | K5: DTG
A6: ISPTMXTRTR951UI2XXX | B6: ANALAKELY 3M ETAGE | C6: ROUTERBOARD RB951UI-2HND | D6: 4023/26/DTG/LOG | E6: 46226 | F6: 1 | G6: PIE | H6: Ilafy | I6: RECU | J6: A METTRE AU REBUT | K6: DTG
A7: ISPTMXTRTR951UI2XXX | B7: ANALAKELY 3M ETAGE | C7: ROUTERBOARD RB951UI-2HND | D7: 4023/26/DTG/LOG | E7: 46226 | F7: 1 | G7: PIE | H7: Ilafy | I7: RECU | J7: A METTRE AU REBUT | K7: DTG
A8: ISPTMXTRTR951UI2XXX | B8: ANALAKELY 3M ETAGE | C8: ROUTERBOARD RB951UI-2HND | D8: 4023/26/DTG/LOG | E8: 46226 | F8: 1 | G8: PIE | H8: Ilafy | I8: RECU | J8: A METTRE AU REBUT | K8: DTG
A9: ISPTMXTRTR951UI2XXX | B9: ANALAKELY 3M ETAGE | C9: ROUTERBOARD RB951UI-2HND | D9: 4023/26/DTG/LOG | E9: 46226 | F9: 1 | G9: PIE | H9: Ilafy | I9: RECU | J9: A METTRE AU REBUT | K9: DTG
A10: ISPTMXTRTR951UI2XXX | B10: ANALAKELY 3M ETAGE | C10: ROUTERBOARD RB951UI-2HND | D10: 4023/26/DTG/LOG | E10: 46226 | F10: 1 | G10: PIE | H10: Ilafy | I10: RECU | J10: A METTRE AU REBUT | K10: DTG
A11: ISPTMXTRTR951UI2XXX | B11: ANALAKELY 3M ETAGE | C11: ROUTERBOARD RB951UI-2HND | D11: 4023/26/DTG/LOG | E11: 46226 | F11: 1 | G11: PIE | H11: Ilafy | I11: RECU | J11: A METTRE AU REBUT | K11: DTG
A12: ISPTMXTRTR951UI2XXX | B12: ANALAKELY 3M ETAGE | C12: ROUTERBOARD RB951UI-2HND | D12: 4023/26/DTG/LOG | E12: 46226 | F12: 1 | G12: PIE | H12: Ilafy | I12: RECU | J12: A METTRE AU REBUT | K12: DTG
A13: ISPTMXTRTR951UI2XXX | B13: ANALAKELY 3M ETAGE | C13: ROUTERBOARD RB951UI-2HND | D13: 4023/26/DTG/LOG | E13: 46226 | F13: 1 | G13: PIE | H13: Ilafy | I13: RECU | J13: A METTRE AU REBUT | K13: DTG
... A280: TMXTBATTPHMBLXXX | B280: ANDRAHARO | C280: MINI BATTERIE | D280: 130826/DHSE | E280: 46247 | F280: 1 | G280: PIE | H280: Ilafy | I280: RECU | J280: A METTRE AU REBUT | K280: HSSES
B281: ANDRAHARO | C281: MINI ONDEULEUR | D281: 130826/DHSE | E281: 46247 | F281: 1 | G281: PIE | H281: Ilafy | I281: RECU | J281: A METTRE AU REBUT | K281: HSSES
B282: ANDRAHARO | C282: MINI MONTRE | D282: 130826/DHSE | E282: 46247 | F282: 1 | G282: PIE | H282: Ilafy | I282: RECU | J282: A METTRE AU REBUT | K282: HSSES
B283: ANDRAHARO | C283: OTG | D283: 130826/DHSE | E283: 46247 | F283: 1 | G283: PIE | H283: Ilafy | I283: RECU | J283: A METTRE AU REBUT | K283: HSSES
B284: ANDRAHARO | C284: PORT TELEPHONE | D284: 130826/DHSE | E284: 46247 | F284: 1 | G284: PIE | H284: Ilafy | I284: RECU | J284: A METTRE AU REBUT | K284: HSSES
B285: ANDRAHARO | C285: ROTATING ANTENNA TV | D285: 130826/DHSE | E285: 46247 | F285: 1 | G285: PIE | H285: Ilafy | I285: RECU | J285: A METTRE AU REBUT | K285: HSSES
B286: ANDRAHARO | C286: SOURIS | D286: 130826/DHSE | E286: 46247 | F286: 1 | G286: PIE | H286: Ilafy | I286: RECU | J286: A METTRE AU REBUT | K286: HSSES
B287: ANDRAHARO | C287: SPEAKER | D287: 130826/DHSE | E287: 46247 | F287: 1 | G287: PIE | H287: Ilafy | I287: RECU | J287: A METTRE AU REBUT | K287: HSSES
B288: ANDRAHARO | C288: TABLETTE | D288: 130826/DHSE | E288: 46247 | F288: 1 | G288: PIE | H288: Ilafy | I288: RECU | J288: A METTRE AU REBUT | K288: HSSES
B289: ANDRAHARO | C289: TELECOMMANDE | D289: 130826/DHSE | E289: 46247 | F289: 1 | G289: PIE | H289: Ilafy | I289: RECU | J289: A METTRE AU REBUT | K289: HSSES
B290: ANDRAHARO | C290: TELEPHONES/SMARTPHONES | D290: 130826/DHSE | E290: 46247 | F290: 12 | G290: PIE | H290: Ilafy | I290: RECU | J290: A METTRE AU REBUT | K290: HSSES
B291: ANDRAHARO | C291: THERMOMETRE | D291: 130826/DHSE | E291: 46247 | F291: 1 | G291: PIE | H291: Ilafy | I291: RECU | J291: A METTRE AU REBUT | K291: HSSES
B292: ANDRAHARO | C292: USB | D292: 130826/DHSE | E292: 46247 | F292: 1 | G292: PIE | H292: Ilafy | I292: RECU | J292: A METTRE AU REBUT | K292: HSSES
... B295: ANALAKELY | C295: ARMOIRE METHALLIQUE | D295: 229/26-MAINT-LOG | E295: 46252 | F295: 3 | G295: PIE | H295: Ilafy | I295: RECU | J295: A METTRE AU REBUT | K295: MAINTENANCE
A296: TMXTREBD3EGENXXX | B296: ANALAKELY | C296: CARTE OCB | D296: 4135/26/DTG/LOG | E296: 46254 | F296: 904 | G296: PIE | H296: Ilafy | I296: RECU | J296: A METTRE AU REBUT | K296: ONIX
A297: TMXTREBD3EGENXXX | B297: ANALAKELY | C297: CARTE OCB GM | D297: 4135/26/DTG/LOG | E297: 46254 | F297: 70 | G297: PIE | H297: Ilafy | I297: RECU | J297: A METTRE AU REBUT | K297: ONIX
A298: TMXTREBD3EGENXXX | B298: ANALAKELY | C298: ACCESSOIRE RACK | D298: 4135/26/DTG/LOG | E298: 46254 | F298: 167 | G298: PIE | H298: Ilafy | I298: RECU | J298: A METTRE AU REBUT | K298: ONIX
A299: TMXTREBD3EGENXXX | B299: ANALAKELY | C299: PORTE RACK | D299: 4135/26/DTG/LOG | E299: 46254 | F299: 2 | G299: PIE | H299: Ilafy | I299: RECU | J299: A METTRE AU REBUT | K299: ONIX
A300: TMXTREBD3EGENXXX | B300: ANALAKELY | C300: COFFRET ALCATEL | D300: 4135/26/DTG/LOG | E300: 46254 | F300: 1 | G300: PIE | H300: Ilafy | I300: RECU | J300: A METTRE AU REBUT | K300: ONIX
A301: TMXTREBD3EGENXXX | B301: ANALAKELY | C301: CARTE PM | D301: 4138/26/DTG/LOG | E301: 46259 | F301: 456 | G301: PIE | H301: Ilafy | I301: RECU | J301: A METTRE AU REBUT | K301: ONIX
A302: TMXTREBD3EGENXXX | B302: ANALAKELY | C302: CARTE GM | D302: 4138/26/DTG/LOG | E302: 46259 | F302: 72 | G302: PIE | H302: Ilafy | I302: RECU | J302: A METTRE AU REBUT | K302: ONIX
A303: TMXTREBD3EGENXXX | B303: ANALAKELY | C303: INTERFACE | D303: 4138/26/DTG/LOG | E303: 46259 | F303: 860 | G303: PIE | H303: Ilafy | I303: RECU | J303: A METTRE AU REBUT | K303: ONIX
A304: TMXTREBD3EGENXXX | B304: ANALAKELY | C304: CONVERTER ALCATEL | D304: 4138/26/DTG/LOG | E304: 46259 | F304: 61 | G304: PIE | H304: Ilafy | I304: RECU | J304: A METTRE AU REBUT | K304: ONIX
A305: TMXTREBD3EGENXXX | B305: ANALAKELY | C305: CONVERTER | D305: 4138/26/DTG/LOG | E305: 46259 | F305: 27 | G305: PIE | H305: Ilafy | I305: RECU | J305: A METTRE AU REBUT | K305: ONIX
A306: TMXTREBD3EGENXXX | B306: ANALAKELY | C306: RACCORDEMENT | D306: 4138/26/DTG/LOG | E306: 46259 | F306: 5 | G306: PIE | H306: Ilafy | I306: RECU | J306: A METTRE AU REBUT | K306: ONIX
A307: TMXTREBD3EGENXXX | B307: ANALAKELY | C307: ACCESSOIRE | D307: 4138/26/DTG/LOG | E307: 46259 | F307: 149 | G307: PIE | H307: Ilafy | I307: RECU | J307: A METTRE AU REBUT | K307: ONIX
... A323: EELAECOUBLUTHXXX | B323: NOC | C323: ECOUTEUR A CASQUE | D323: 0002-26/DHSE | E323: 46259 | F323: 1 | G323: LOT | H323: Ilafy | I323: RECU | J323: A METTRE AU REBUT | K323: HSSES
B324: NOC | C324: CHARGEURS | D324: 0002-26/DHSE | E324: 46259 | F324: 1 | G324: LOT | H324: Ilafy | I324: RECU | J324: A METTRE AU REBUT | K324: HSSES
B325: NOC | C325: LSER JET | D325: 0002-26/DHSE | E325: 46259 | F325: 2 | G325: PIE | H325: Ilafy | I325: RECU | J325: A METTRE AU REBUT | K325: HSSES
B326: NOC | C326: TELEPHONE FIXE | D326: 0002-26/DHSE | E326: 46259 | F326: 3 | G326: PIE | H326: Ilafy | I326: RECU | J326: A METTRE AU REBUT | K326: HSSES
B327: NOC | C327: CLAVIER | D327: 0002-26/DHSE | E327: 46259 | F327: 1 | G327: PIE | H327: Ilafy | I327: RECU | J327: A METTRE AU REBUT | K327: HSSES
B328: NOC | C328: TELECOMMANDE | D328: 0002-26/DHSE | E328: 46259 | F328: 1 | G328: PIE | H328: Ilafy | I328: RECU | J328: A METTRE AU REBUT | K328: HSSES
B329: ANALAKELY | C329: TABLE MARQUERITTE HS | D329: 237/26-MAINT-LOG | E329: 46259 | F329: 1 | G329: PIE | H329: Ilafy | I329: RECU | J329: A METTRE AU REBUT | K329: MAINTENANCE
B330: ANALAKELY | C330: CHAISE HS | D330: 237/26-MAINT-LOG | E330: 46259 | F330: 1 | G330: PIE | H330: Ilafy | I330: RECU | J330: A METTRE AU REBUT | K330: MAINTENANCE
B331: ANALAKELY | C331: CAISSON HS | D331: 237/26-MAINT-LOG | E331: 46259 | F331: 5 | G331: PIE | H331: Ilafy | I331: RECU | J331: A METTRE AU REBUT | K331: MAINTENANCE
B332: ANALAKELY | C332: TABLE HS | D332: 237/26-MAINT-LOG | E332: 46259 | F332: 1 | G332: PIE | H332: Ilafy | I332: RECU | J332: A METTRE AU REBUT | K332: MAINTENANCE
B333: ANALAKELY | C333: ARMOIRE HS | D333: 237/26-MAINT-LOG | E333: 46259 | F333: 2 | G333: PIE | H333: Ilafy | I333: RECU | J333: A METTRE AU REBUT | K333: MAINTENANCE
B334: ANALAKELY | C334: CHARIOT BLEU | D334: 237/26-MAINT-LOG | E334: 46259 | F334: 1 | G334: PIE | H334: Ilafy | I334: RECU | J334: A METTRE AU REBUT | K334: MAINTENANCE
A335: TFHPANT180M7GSGM | B335: ANKINGABE | C335: ANTENNE 1.80M 7G | D335: 213060/26/DTG/LOG | E335: 46259 | F335: 2 | G335: UN | H335: Ilafy | I335: RECU | J335: A METTRE AU REBUT | K335: AFROTEL
A336: TGSMMOTSETPBSERK | B336: ANKINGABE | C336: MOUNTING SET/POLE BRACKET SET | D336: 213060/26/DTG/LOG | E336: 46259 | F336: 2 | G336: PIE | H336: Ilafy | I336: RECU | J336: A METTRE AU REBUT | K336: AFROTEL
A337: TGSMCONTNCM76ERK | B337: ANKINGABE | C337: CONTACT SET/TNC-male 7,6 mm ca | D337: 213060/26/DTG/LOG | E337: 46259 | F337: 12 | G337: PIE | H337: Ilafy | I337: RECU | J337: A METTRE AU REBUT | K337: AFROTEL
A338: TGSMCBLPWRIDUERC | B338: ANKINGABE | C338: IDU CGble/Power cable_RPM517560/10000 | D338: 213060/26/DTG/LOG | E338: 46259 | F338: 5 | G338: PIE | H338: Ilafy | I338: RECU | J338: A METTRE AU REBUT | K338: AFROTEL
A339: TGSMCBLRTZ500ERC | B339: ANKINGABE | C339: IF CABLE 7,6mm / TZC50097 (500m) | D339: 213060/26/DTG/LOG | E339: 46259 | F339: 35 | G339: M | H339: Ilafy | I339: RECU | J339: A METTRE AU REBUT | K339: AFROTEL
A340: TGSMCBLRTZ500ERC | B340: ANKINGABE | C340: IF CABLE 7,6mm / TZC50097 (500m) | D340: 213060/26/DTG/LOG | E340: 46259 | F340: 35 | G340: M | H340: Ilafy | I340: RECU | J340: A METTRE AU REBUT | K340: AFROTEL
A341: TGSMCBLRTZ500ERC | B341: ANKINGABE | C341: IF CABLE 7,6mm / TZC50097 (500m) | D341: 213060/26/DTG/LOG | E341: 46259 | F341: 35 | G341: M | H341: Ilafy | I341: RECU | J341: A METTRE AU REBUT | K341: AFROTEL
A342: TGSMCBLRTZ500ERC | B342: ANKINGABE | C342: IF CABLE 7,6mm / TZC50097 (500m) | D342: 213060/26/DTG/LOG | E342: 46259 | F342: 42 | G342: M | H342: Ilafy | I342: RECU | J342: A METTRE AU REBUT | K342: AFROTEL
A343: TGSMCBLRTZ500ERC | B343: ANKINGABE | C343: IF CABLE 7,6mm / TZC50097 (500m) | D343: 213060/26/DTG/LOG | E343: 46259 | F343: 42 | G343: M | H343: Ilafy | I343: RECU | J343: A METTRE AU REBUT | K343: AFROTEL
A344: TGSMCBLRTZ500ERC | B344: ANKINGABE | C344: IF CABLE 7,6mm / TZC50097 (500m) | D344: 213060/26/DTG/LOG | E344: 46259 | F344: 42 | G344: M | H344: Ilafy | I344: RECU | J344: A METTRE AU REBUT | K344: AFROTEL
A345: TFHPANT180M7GSGM | B345: MIARENA | C345: ANTENNE 1.80M 7G | D345: 213055/26/DTG/LOG | E345: 46259 | F345: 2 | G345: UN | H345: Ilafy | I345: RECU | J345: A METTRE AU REBUT | K345: AFROTEL
A346: TGSMMOTSETPBSERK | B346: MIARENA | C346: MOUNTING SET/POLE BRACKET SET | D346: 213055/26/DTG/LOG | E346: 46259 | F346: 2 | G346: PIE | H346: Ilafy | I346: RECU | J346: A METTRE AU REBUT | K346: AFROTEL
... A365: TGSMCBLRTZ500ERC | B365: AMBANJA AMBAIBO | C365: IF CABLE 7,6mm / TZC50097 (500m) | D365: 213045/26/DTG/LOG | E365: 46259 | F365: 40 | G365: M | H365: Ilafy | I365: RECU | J365: A METTRE AU REBUT | K365: AFROTEL
A366: TMXTREBD3EGENXXX | B366: TSOF006 BEFANDRIANA AVARATRA | C366: MATERIEL HS ET DECHETS LAISSES SUR SITE | D366: 3999/26/DTG/LOG | E366: 46261 | F366: 1 | G366: LOT | H366: Ilafy | I366: RECU | J366: A METTRE AU REBUT
A367: TCUIPOTBOIS8MXXX | B367: ANALAKELY | C367: POTEAU BOIS DE 8M | D367: 212727/26/DTG/LOG | E367: 46261 | F367: 12 | G367: PIE | H367: Ilafy | I367: RECU | J367: Défectueux | K367: ENC
A368: FIXTCUIPOTPTJEANGEK | B368: ANALAKELY | C368: Poteau petit jean | D368: 212727/26/DTG/LOG | E368: 46261 | F368: 3 | G368: PIE | H368: Ilafy | I368: RECU | J368: Défectueux | K368: ENC
A369: FIXTCUIPOTBOIS9MXXX | B369: ANALAKELY | C369: 9M 140/160MM WOODEN POLES | D369: 212727/26/DTG/LOG | E369: 46261 | F369: 2 | G369: PIE | H369: Ilafy | I369: RECU | J369: Défectueux | K369: ENC
B370: STUDIO ADN | C370: ACCESSOIRE ECO SAPIN DE FER | D370: 0001/26/PROD | E370: 46261 | F370: 1 | G370: LOT | H370: Ilafy | I370: RECU | J370: A METTRE AU REBUT | K370: DTUDIO ADN
B371: STUDIO ADN | C371: ACCESSOIRE LAMPIONS YAS | D371: 0001/26/PROD | E371: 46261 | F371: 1 | G371: LOT | H371: Ilafy | I371: RECU | J371: A METTRE AU REBUT | K371: DTUDIO ADN
B372: STUDIO ADN | C372: ACCESSOIRE DECO TOURNAGE | D372: 0001/26/PROD | E372: 46261 | F372: 3 | G372: LOT | H372: Ilafy | I372: RECU | J372: A METTRE AU REBUT | K372: DTUDIO ADN
B373: STUDIO ADN | C373: ACCESSOIRE VESTIMENTAIRES(BOTTE BLANC,TALON,TISSU….) | D373: 0001/26/PROD | E373: 46261 | F373: 2 | G373: LOT | H373: Ilafy | I373: RECU | J373: A METTRE AU REBUT | K373: DTUDIO ADN
B374: STUDIO ADN | C374: CHAISE HS | D374: 0001/26/PROD | E374: 46261 | F374: 1 | G374: LOT | H374: Ilafy | I374: RECU | J374: A METTRE AU REBUT | K374: DTUDIO ADN
B375: STUDIO ADN | C375: ASSIS DE CHAISE | D375: 0001/26/PROD | E375: 46261 | F375: 1 | G375: PIE | H375: Ilafy | I375: RECU | J375: A METTRE AU REBUT | K375: DTUDIO ADN
B376: STUDIO ADN | C376: DOS DE CHAISE+POSE TETE | D376: 0001/26/PROD | E376: 46261 | F376: 1 | G376: PIE | H376: Ilafy | I376: RECU | J376: A METTRE AU REBUT | K376: DTUDIO ADN
B377: STUDIO ADN | C377: ECRAN TOSHIBA | D377: 0001/26/PROD | E377: 46261 | F377: 1 | G377: PIE | H377: Ilafy | I377: RECU | J377: A METTRE AU REBUT | K377: DTUDIO ADN
B378: STUDIO ADN | C378: LAMPE EXTERIEUR | D378: 0001/26/PROD | E378: 46261 | F378: 1 | G378: PIE | H378: Ilafy | I378: RECU | J378: A METTRE AU REBUT | K378: DTUDIO ADN
B379: STUDIO ADN | C379: TELECOMMANDE | D379: 0001/26/PROD | E379: 46261 | F379: 1 | G379: PIE | H379: Ilafy | I379: RECU | J379: A METTRE AU REBUT | K379: DTUDIO ADN
B380: ANALAKELY | C380: ARMOIRE VITRE | D380: 238/26/DFG-MAINT | E380: 46261 | F380: 6 | G380: PIE | H380: Ilafy | I380: RECU | J380: A METTRE AU REBUT | K380: MAINTENANCE
B381: ANALAKELY | C381: ARMOIRE HAUTE | D381: 238/26/DFG-MAINT | E381: 46261 | F381: 1 | G381: PIE | H381: Ilafy | I381: RECU | J381: A METTRE AU REBUT | K381: MAINTENANCE
B382: ANALAKELY | C382: ARMOIRE BASSE 4PORTES | D382: 238/26/DFG-MAINT | E382: 46261 | F382: 1 | G382: PIE | H382: Ilafy | I382: RECU | J382: A METTRE AU REBUT | K382: MAINTENANCE
A383: ISPTMXTRTR951UI2XXX | B383: ANALAKELY 3M ET | C383: ROUTERBOARD RB951UI-2HND | D383: 4095/26/DTG/LOG | E383: 46261 | F383: 1 | G383: PIE | H383: Ilafy | I383: RECU | J383: A METTRE AU REBUT | K383: DTG
A384: ISPTMXTRTR951UI2XXX | B384: ANALAKELY 3M ET | C384: ROUTERBOARD RB951UI-2HND | D384: 4095/26/DTG/LOG | E384: 46261 | F384: 1 | G384: PIE | H384: Ilafy | I384: RECU | J384: A METTRE AU REBUT | K384: DTG
A385: ISPTMXTRTR951UI2XXX | B385: ANALAKELY 3M ET | C385: ROUTERBOARD RB951UI-2HND | D385: 4095/26/DTG/LOG | E385: 46261 | F385: 1 | G385: PIE | H385: Ilafy | I385: RECU | J385: A METTRE AU REBUT | K385: DTG
A386: ISPTMXTRTR951UI2XXX | B386: ANALAKELY 3M ET | C386: ROUTERBOARD RB951UI-2HND | D386: 4095/26/DTG/LOG | E386: 46261 | F386: 1 | G386: PIE | H386: Ilafy | I386: RECU | J386: A METTRE AU REBUT | K386: DTG
A387: ISPTMXTRTR951UI2XXX | B387: ANALAKELY 3M ET | C387: ROUTERBOARD RB951UI-2HND | D387: 4095/26/DTG/LOG | E387: 46261 | F387: 1 | G387: PIE | H387: Ilafy | I387: RECU | J387: A METTRE AU REBUT | K387: DTG
A388: ISPTMXTRTR951UI2XXX | B388: ANALAKELY 3M ET | C388: ROUTERBOARD RB951UI-2HND | D388: 4095/26/DTG/LOG | E388: 46261 | F388: 1 | G388: PIE | H388: Ilafy | I388: RECU | J388: A METTRE AU REBUT | K388: DTG
A389: ISPTMXTRTR951UI2XXX | B389: ANALAKELY 3M ET | C389: ROUTERBOARD RB951UI-2HND | D389: 4095/26/DTG/LOG | E389: 46261 | F389: 1 | G389: PIE | H389: Ilafy | I389: RECU | J389: A METTRE AU REBUT | K389: DTG
A390: ISPTMXTRTR951UI2XXX | B390: ANALAKELY 3M ET | C390: ROUTERBOARD RB951UI-2HND | D390: 4095/26/DTG/LOG | E390: 46261 | F390: 1 | G390: PIE | H390: Ilafy | I390: RECU | J390: A METTRE AU REBUT | K390: DTG
A391: ISPTMXTRTR951UI2XXX | B391: ANALAKELY 3M ET | C391: ROUTERBOARD RB951UI-2HND | D391: 4095/26/DTG/LOG | E391: 46261 | F391: 1 | G391: PIE | H391: Ilafy | I391: RECU | J391: A METTRE AU REBUT | K391: DTG
A392: ISPTMXTRTR951UI2XXX | B392: ANALAKELY 3M ET | C392: ROUTERBOARD RB951UI-2HND | D392: 4095/26/DTG/LOG | E392: 46261 | F392: 1 | G392: PIE | H392: Ilafy | I392: RECU | J392: A METTRE AU REBUT | K392: DTG
A393: ISPTMXTRTR951UI2XXX | B393: ANALAKELY 3M ET | C393: ROUTERBOARD RB951UI-2HND | D393: 4095/26/DTG/LOG | E393: 46261 | F393: 1 | G393: PIE | H393: Ilafy | I393: RECU | J393: A METTRE AU REBUT | K393: DTG
A394: ISPTMXTRTR951UI2XXX | B394: ANALAKELY 3M ET | C394: ROUTERBOARD RB951UI-2HND | D394: 4095/26/DTG/LOG | E394: 46261 | F394: 1 | G394: PIE | H394: Ilafy | I394: RECU | J394: A METTRE AU REBUT | K394: DTG
... A554: TMXTREBD3EGENXXX | B554: ANM134 AMPASAMPITO | C554: RADIO SAGEM | D554: 4165/26/DTG/LOG | E554: 46273 | F554: 2 | G554: PIE | H554: Ilafy | I554: RECU | J554: A METTRE AU REBUT | K554: FIELD
B555: ANALAKELY | C555: TABLE ORDI BASSE | D555: 243/26/DFG-MAINT | E555: 46273 | F555: 3 | G555: PIE | H555: Ilafy | I555: RECU | J555: A METTRE AU REBUT | K555: MAINT
B556: ANALAKELY | C556: TABLE ORDI HAUTE | D556: 243/26/DFG-MAINT | E556: 46273 | F556: 3 | G556: PIE | H556: Ilafy | I556: RECU | J556: A METTRE AU REBUT | K556: MAINT
B557: ANALAKELY | C557: ARMOIRE VITRE | D557: 243/26/DFG-MAINT | E557: 46273 | F557: 1 | G557: PIE | H557: Ilafy | I557: RECU | J557: A METTRE AU REBUT | K557: MAINT
B558: ANALAKELY | C558: CHAISE HS | D558: 243/26/DFG-MAINT | E558: 46273 | F558: 3 | G558: PIE | H558: Ilafy | I558: RECU | J558: A METTRE AU REBUT | K558: MAINT
B559: ANALAKELY | C559: TABLEAU | D559: 243/26/DFG-MAINT | E559: 46273 | F559: 3 | G559: PIE | H559: Ilafy | I559: RECU | J559: A METTRE AU REBUT | K559: MAINT
A560: TFOXLOTCAFOM3XXX | B560: ANALAKELY | C560: COUPON FIBRE | D560: 243/26/DFG-MAINT | E560: 46273 | F560: 1 | G560: CART | H560: Ilafy | I560: RECU | J560: A METTRE AU REBUT | K560: MAINT
...

Sheet SORTIE APRES INV
A1: Date d'enlèvement | B1: Code articles | C1: Article Description | D1: Quantité | E1: Unité | F1: Méthode de traitement / d'élimination | G1: NUMERO BSD | H1: FMR/GDA | I1: DATE D'ENLEVEMENT | J1: N° BL | K1: DESTINATION
A2: 46237 | C2: POTEAU EN BOIS | D2: 42 | E2: PIE | F2: M. OLIVIER ROZIERE | G2: BSD300726 | H2: 4089/25/DTG/LOG | I2: 46237 | J2: 146/26-REVLOG | K2: M. OLIVIER ROZIERE
A3: 46241 | B3: TMXTREBD3EGENXXX | C3: RACK OCB ALCATEL 2,10X0,66m | D3: 30 | E3: PIE | F3: VALOMADA | G3: BSD070826 | H3: 4082/26/DTG/LOG | I3: 46241 | J3: 147/26-REVLOG | K3: VALOMADA
A4: 46241 | B4: TMXTREBD3EGENXXX | C4: PORTE DE RACK 2,00x0,45m | D4: 104 | E4: PIE | F4: VALOMADA | G4: BSD070826 | H4: 4082/26/DTG/LOG | I4: 46241 | J4: 147/26-REVLOG | K4: VALOMADA
A5: 46241 | B5: TMXTREBD3EGENXXX | C5: PANNEAU LATERAL 2,20x 0,66m | D5: 10 | E5: PIE | F5: VALOMADA | G5: BSD070826 | H5: 4082/26/DTG/LOG | I5: 46241 | J5: 147/26-REVLOG | K5: VALOMADA
A6: 46241 | B6: TMXTREBD3EGENXXX | C6: CAPOT SUPERIEUR RACK 0,90X0,60 | D6: 30 | E6: PIE | F6: VALOMADA | G6: BSD070826 | H6: 4082/26/DTG/LOG | I6: 46241 | J6: 147/26-REVLOG | K6: VALOMADA
A7: 46241 | B7: TMXTREBD3EGENXXX | C7: SUPPORT CAPOT 0,15X0,95m | D7: 10 | E7: PIE | F7: VALOMADA | G7: BSD070826 | H7: 4082/26/DTG/LOG | I7: 46241 | J7: 147/26-REVLOG | K7: VALOMADA
A8: 46241 | B8: TMXTREBD3EGENXXX | C8: SUPPORT CAPOT 0,25X0,95m | D8: 9 | E8: PIE | F8: VALOMADA | G8: BSD070826 | H8: 4082/26/DTG/LOG | I8: 46241 | J8: 147/26-REVLOG | K8: VALOMADA
A9: 46246 | B9: TGSMANT21278HERC | C9: ANTENNA/ANTm1.2 | D9: 1 | E9: PIE | F9: VALOMADA | G9: BSD120826 | H9: 4045/26/DTG/LOG | I9: 46246 | J9: 148/26-REVLOG | K9: VALOMADA
A10: 46246 | B10: TFOXCFD12SA10NET | C10: CABLE 1FO | D10: 430 | E10: M | F10: VALOMADA | G10: BSD120827 | H10: 3799/26/DTG/LOG | I10: 46246 | J10: 148/26-REVLOG | K10: VALOMADA
A11: 46246 | B11: TMXTREBD3EGENXXX | C11: CABLE JARETIERE | D11: 1250 | E11: M | F11: VALOMADA | G11: BSD120828 | H11: 3799/26/DTG/LOG | I11: 46246 | J11: 148/26-REVLOG | K11: VALOMADA
A12: 46246 | B12: TMXTREBD3EGENXXX | C12: TETE JARETIERE | D12: 828 | E12: PCS | F12: VALOMADA | G12: BSD120829 | H12: 3799/26/DTG/LOG | I12: 46246 | J12: 148/26-REVLOG | K12: VALOMADA
A13: 46246 | B13: TMXTREBD3EGENXXX | C13: PORTE | D13: 48 | E13: PCS | F13: VALOMADA | G13: BSD120830 | H13: 3799/26/DTG/LOG | I13: 46246 | J13: 148/26-REVLOG | K13: VALOMADA
A14: 46246 | B14: FIXTCUIBMX28PEQUGEK | C14: PC 28/2 | D14: 2 | E14: PCS | F14: VALOMADA | G14: BSD120831 | H14: 3799/26/DTG/LOG | I14: 46246 | J14: 148/26-REVLOG | K14: VALOMADA
A15: 46246 | B15: TMXTSWTMTS108DWS | C15: SWITCH | D15: 14 | E15: PCS | F15: VALOMADA | G15: BSD120832 | H15: 4065/26/DTG/LOG | I15: 46246 | J15: 148/26-REVLOG | K15: VALOMADA
A16: 46246 | C16: COUPON CABLE | D16: 1 | E16: LOT | F16: VALOMADA | G16: BSD120833 | H16: 216/26/MAINT/LOG | I16: 46246 | J16: 148/26-REVLOG | K16: VALOMADA
A17: 46246 | C17: DECHET LAMPE 60X60 | D17: 7 | E17: PCS | F17: VALOMADA | G17: BSD120834 | H17: 217/26/MAINT/LOG | I17: 46246 | J17: 148/26-REVLOG | K17: VALOMADA
A18: 46246 | C18: DECHET LAMPE 1,20M | D18: 9 | E18: PCS | F18: VALOMADA | G18: BSD120835 | H18: 217/26/MAINT/LOG | I18: 46246 | J18: 148/26-REVLOG | K18: VALOMADA
A19: 46246 | C19: DECHET LAMPE E27 | D19: 1 | E19: PIE | F19: VALOMADA | G19: BSD120836 | H19: 217/26/MAINT/LOG | I19: 46246 | J19: 148/26-REVLOG | K19: VALOMADA
A20: 46246 | C20: DECHET SPOT | D20: 5 | E20: PIE | F20: VALOMADA | G20: BSD120837 | H20: 217/26/MAINT/LOG | I20: 46246 | J20: 148/26-REVLOG | K20: VALOMADA
A21: 46255 | B21: TMXTREBD3EGENXXX | C21: CARTE OCB | D21: 102 | E21: PCS | F21: VALOMADA | G21: BSD210826 | H21: 4108/26/DTG/LOG | I21: 46255 | J21: 151/26-REVLOG | K21: VALOMADA
A22: 46255 | B22: TMXTREBD3EGENXXX | C22: ETAGERE RACK+ACCESSOIRE | D22: 156 | E22: PCS | F22: VALOMADA | G22: BSD210826 | H22: 4108/26/DTG/LOG | I22: 46255 | J22: 151/26-REVLOG | K22: VALOMADA
A23: 46269 | B23: TVSTANT24OMRTAMO | C23: ANTENNE 2.4 | D23: 1 | E23: PIE | F23: VALOMADA | G23: BSD040926 | H23: 4029/26/DTG/LOG | I23: 46269 | J23: 153/26-REVLOG | K23: VALOMADA
A24: 46269 | B24: TVSTANT24OMRTAMO | C24: ANTENNE 2.4 | D24: 1 | E24: PIE | F24: VALOMADA | G24: BSD040926 | H24: 4030/26/DTG/LOG | I24: 46269 | J24: 153/26-REVLOG | K24: VALOMADA
A25: 46269 | B25: TVSTANT24OMRTAMO | C25: ANTENNE 2.4 | D25: 1 | E25: PIE | F25: VALOMADA | G25: BSD040926 | H25: 4031/26/DTG/LOG | I25: 46269 | J25: 153/26-REVLOG | K25: VALOMADA
A26: 46269 | B26: TVSTANT24OMRTAMO | C26: ANTENNE 2.4 | D26: 1 | E26: PIE | F26: VALOMADA | G26: BSD040926 | H26: 4036/26/DTG/LOG | I26: 46269 | J26: 153/26-REVLOG | K26: VALOMADA
A27: 46269 | B27: TVSTANT24OMRTAMO | C27: ANTENNE 2.4 | D27: 1 | E27: PIE | F27: VALOMADA | G27: BSD040926 | H27: 4033/26/DTG/LOG | I27: 46269 | J27: 153/26-REVLOG | K27: VALOMADA
A28: 46269 | B28: TVSTANT24OMRTAMO | C28: ANTENNE 2.4 | D28: 1 | E28: PIE | F28: VALOMADA | G28: BSD040926 | H28: 4034/26/DTG/LOG | I28: 46269 | J28: 153/26-REVLOG | K28: VALOMADA
A29: 46269 | B29: TVSTANT24OMRTAMO | C29: ANTENNE 2.4 | D29: 1 | E29: PIE | F29: VALOMADA | G29: BSD040926 | H29: 4035/26/DTG/LOG | I29: 46269 | J29: 153/26-REVLOG | K29: VALOMADA
A30: 46269 | B30: TVSTANT24OMRTAMO | C30: ANTENNE 2.4 | D30: 1 | E30: PIE | F30: VALOMADA | G30: BSD040926 | H30: 4037/26/DTG/LOG | I30: 46269 | J30: 153/26-REVLOG | K30: VALOMADA
A31: 46269 | B31: TVSTANT24OMRTAMO | C31: ANTENNE 2.4 | D31: 1 | E31: PIE | F31: VALOMADA | G31: BSD040926 | H31: 4080/26/DTG/LOG | I31: 46269 | J31: 153/26-REVLOG | K31: VALOMADA
A32: 46269 | B32: TVSTANT24OMRTAMO | C32: ANTENNE 2.4 | D32: 1 | E32: PIE | F32: VALOMADA | G32: BSD040926 | H32: 4081/26/DTG/LOG | I32: 46269 | J32: 153/26-REVLOG | K32: VALOMADA
... A100: 46283 | B100: TMXTREBD3EGENXXX | C100: RACK RBS 6301 | D100: 2 | E100: PIE | F100: VALOMADA | G100: BSD180926 | H100: 4000/26/DTG/LOG | I100: 46283 | J100: 157/26-REVLOG | K100: VALOMADA
A101: 46283 | C101: OVERLING BOX | D101: 3 | E101: PIE | F101: VALOMADA | G101: BSD180926 | H101: 4000/26/DTG/LOG | I101: 46283 | J101: 157/26-REVLOG | K101: VALOMADA
A102: 46283 | C102: RACK SSC02 | D102: 1 | E102: PIE | F102: VALOMADA | G102: BSD180926 | H102: 4000/26/DTG/LOG | I102: 46283 | J102: 157/26-REVLOG | K102: VALOMADA
A103: 46283 | C103: CHAISE | D103: 5 | E103: PIE | F103: VALOMADA | G103: BSD180926 | H103: 002/26/DFG/MAINT | I103: 46283 | J103: 157/26-REVLOG | K103: VALOMADA
A104: 46283 | C104: DETECTEUR FUMEE HS | D104: 28 | E104: PIE | F104: VALOMADA | G104: BSD180926 | H104: 0005/26/DHSSES | I104: 46283 | J104: 157/26-REVLOG | K104: VALOMADA
A105: 46283 | C105: DECLENCHEUR D ALARME HS | D105: 1 | E105: PIE | F105: VALOMADA | G105: BSD180926 | H105: 0005/26/DHSSES | I105: 46283 | J105: 157/26-REVLOG | K105: VALOMADA
A106: 46283 | C106: SAC DE CABLE | D106: 4 | E106: SACS | F106: VALOMADA | G106: BSD180926 | H106: 0005/26/DHSSES | I106: 46283 | J106: 157/26-REVLOG | K106: VALOMADA
A107: 46283 | C107: PORTE IBM | D107: 1 | E107: PIE | F107: VALOMADA | G107: BSD180926 | H107: 4179/26/DTG/LOG | I107: 46283 | J107: 157/26-REVLOG | K107: VALOMADA
A108: 46283 | C108: PORTE ALCATEL | D108: 4 | E108: PIE | F108: VALOMADA | G108: BSD180926 | H108: 4179/26/DTG/LOG | I108: 46283 | J108: 157/26-REVLOG | K108: VALOMADA
A109: 46283 | C109: PORTE HUAWEI | D109: 14 | E109: PIE | F109: VALOMADA | G109: BSD180926 | H109: 4179/26/DTG/LOG | I109: 46283 | J109: 157/26-REVLOG | K109: VALOMADA
A110: 46283 | C110: TAINET MERCURY 3600 | D110: 3 | E110: PIE | F110: VALOMADA | G110: BSD180926 | H110: 4179/26/DTG/LOG | I110: 46283 | J110: 157/26-REVLOG | K110: VALOMADA
A111: 46283 | C111: SERVEUR SUN MICRO SYSTEMS | D111: 5 | E111: PIE | F111: VALOMADA | G111: BSD180926 | H111: 4179/26/DTG/LOG | I111: 46283 | J111: 157/26-REVLOG | K111: VALOMADA
A112: 46283 | C112: TLSF 1016 TP LINK | D112: 1 | E112: PIE | F112: VALOMADA | G112: BSD180926 | H112: 4179/26/DTG/LOG | I112: 46283 | J112: 157/26-REVLOG | K112: VALOMADA
... A126: 46283 | C126: COUPON FIBRE | D126: 2 | E126: CART | F126: VALOMADA | G126: BSD180926 | H126: 245/26/MAINT-LOG | I126: 46283 | J126: 157/26-REVLOG | K126: VALOMADA
A127: 46283 | B127: TMXTRTRR52G5HXXX | C127: RDB52G5HACD2HNDTC WITH ROUTER | D127: 1 | E127: PIE | F127: VALOMADA | G127: BSD180926 | H127: 4145/26/DTG/LOG | I127: 46283 | J127: 157/26-REVLOG | K127: VALOMADA
A128: 46283 | B128: TMXTRTRR52G5HXXX | C128: RDB52G5HACD2HNDTC WITH ROUTER | D128: 1 | E128: PIE | F128: VALOMADA | G128: BSD180926 | H128: 4145/26/DTG/LOG | I128: 46283 | J128: 157/26-REVLOG | K128: VALOMADA
A129: 46283 | B129: TMXTRTRR52G5HXXX | C129: RDB52G5HACD2HNDTC WITH ROUTER | D129: 1 | E129: PIE | F129: VALOMADA | G129: BSD180926 | H129: 4145/26/DTG/LOG | I129: 46283 | J129: 157/26-REVLOG | K129: VALOMADA
A130: 46283 | B130: TMXTRTRR52G5HXXX | C130: RDB52G5HACD2HNDTC WITH ROUTER | D130: 1 | E130: PIE | F130: VALOMADA | G130: BSD180926 | H130: 4145/26/DTG/LOG | I130: 46283 | J130: 157/26-REVLOG | K130: VALOMADA
A131: 46283 | B131: TMXTRTRR52G5HXXX | C131: RDB52G5HACD2HNDTC WITH ROUTER | D131: 1 | E131: PIE | F131: VALOMADA | G131: BSD180926 | H131: 4145/26/DTG/LOG | I131: 46283 | J131: 157/26-REVLOG | K131: VALOMADA
A132: 46283 | B132: TMXTRTRR52G5HXXX | C132: RDB52G5HACD2HNDTC WITH ROUTER | D132: 1 | E132: PIE | F132: VALOMADA | G132: BSD180926 | H132: 4145/26/DTG/LOG | I132: 46283 | J132: 157/26-REVLOG | K132: VALOMADA
A133: 46283 | B133: TMXTRTRR52G5HXXX | C133: RDB52G5HACD2HNDTC WITH ROUTER | D133: 1 | E133: PIE | F133: VALOMADA | G133: BSD180926 | H133: 4145/26/DTG/LOG | I133: 46283 | J133: 157/26-REVLOG | K133: VALOMADA
A134: 46283 | B134: TMXTRTRR52G5HXXX | C134: RDB52G5HACD2HNDTC WITH ROUTER | D134: 1 | E134: PIE | F134: VALOMADA | G134: BSD180926 | H134: 4145/26/DTG/LOG | I134: 46283 | J134: 157/26-REVLOG | K134: VALOMADA
A135: 46283 | B135: TMXTRTRR52G5HXXX | C135: RDB52G5HACD2HNDTC WITH ROUTER | D135: 1 | E135: PIE | F135: VALOMADA | G135: BSD180926 | H135: 4145/26/DTG/LOG | I135: 46283 | J135: 157/26-REVLOG | K135: VALOMADA
A136: 46283 | B136: TMXTRTRR52G5HXXX | C136: RDB52G5HACD2HNDTC WITH ROUTER | D136: 1 | E136: PIE | F136: VALOMADA | G136: BSD180926 | H136: 4145/26/DTG/LOG | I136: 46283 | J136: 157/26-REVLOG | K136: VALOMADA
A137: 46283 | B137: TMXTRTRR52G5HXXX | C137: RDB52G5HACD2HNDTC WITH ROUTER | D137: 1 | E137: PIE | F137: VALOMADA | G137: BSD180926 | H137: 4145/26/DTG/LOG | I137: 46283 | J137: 157/26-REVLOG | K137: VALOMADA
A138: 46283 | B138: TMXTRTRR52G5HXXX | C138: RDB52G5HACD2HNDTC WITH ROUTER | D138: 1 | E138: PIE | F138: VALOMADA | G138: BSD180926 | H138: 4145/26/DTG/LOG | I138: 46283 | J138: 157/26-REVLOG | K138: VALOMADA
... A208: 46283 | B208: ISPTMXTRTROHG10HHAW | C208: HUAWEI ONT HG8010H | D208: 1 | E208: PIE | F208: VALOMADA | G208: BSD180926 | H208: 4145/26/DTG/LOG | I208: 46283 | J208: 157/26-REVLOG | K208: VALOMADA
A209: 46283 | C209: CHAISE BUREAU HS | D209: 1 | E209: PIE | F209: VALOMADA | G209: BSD180926 | H209: 0002/26/PROD | I209: 46283 | J209: 157/26-REVLOG | K209: VALOMADA
A210: 46283 | C210: MODEM VSAT HT2524 | D210: 8 | E210: PIE | F210: VALOMADA | G210: BSD180926 | H210: 4190/26/DTG/LOG | I210: 46283 | J210: 157/26-REVLOG | K210: VALOMADA
A211: 46283 | C211: MODEM VSAT HT2300 | D211: 2 | E211: PIE | F211: VALOMADA | G211: BSD180926 | H211: 4190/26/DTG/LOG | I211: 46283 | J211: 157/26-REVLOG | K211: VALOMADA
A212: 46283 | C212: BUC 5W | D212: 6 | E212: PIE | F212: VALOMADA | G212: BSD180926 | H212: 4190/26/DTG/LOG | I212: 46283 | J212: 157/26-REVLOG | K212: VALOMADA
A213: 46283 | C213: LNB 8530 C BAND | D213: 5 | E213: PIE | F213: VALOMADA | G213: BSD180926 | H213: 4190/26/DTG/LOG | I213: 46283 | J213: 157/26-REVLOG | K213: VALOMADA
A214: 46283 | C214: GENERATEUR DE FREQUENCE AGILENT 53150A | D214: 1 | E214: PIE | F214: VALOMADA | G214: BSD180926 | H214: 4190/26/DTG/LOG | I214: 46283 | J214: 157/26-REVLOG | K214: VALOMADA
A215: 46283 | C215: SPECTRUM ANALYZER HP 377 21A | D215: 1 | E215: PIE | F215: VALOMADA | G215: BSD180926 | H215: 4190/26/DTG/LOG | I215: 46283 | J215: 157/26-REVLOG | K215: VALOMADA
A216: 46283 | C216: CARTE EDCM IGATE 4000 | D216: 1 | E216: PIE | F216: VALOMADA | G216: BSD180926 | H216: 4190/26/DTG/LOG | I216: 46283 | J216: 157/26-REVLOG | K216: VALOMADA
A217: 46283 | C217: CARTE ICHP IGATE 4000 | D217: 1 | E217: PIE | F217: VALOMADA | G217: BSD180926 | H217: 4190/26/DTG/LOG | I217: 46283 | J217: 157/26-REVLOG | K217: VALOMADA
A218: 46283 | C218: CARTE XPSMR1 IGATE 4000 | D218: 1 | E218: PIE | F218: VALOMADA | G218: BSD180926 | H218: 4190/26/DTG/LOG | I218: 46283 | J218: 157/26-REVLOG | K218: VALOMADA
A219: 46283 | C219: CLAVIER | D219: 2 | E219: PIE | F219: VALOMADA | G219: BSD180926 | H219: 4190/26/DTG/LOG | I219: 46283 | J219: 157/26-REVLOG | K219: VALOMADA
A220: 46283 | C220: SOURIS | D220: 1 | E220: PIE | F220: VALOMADA | G220: BSD180926 | H220: 4190/26/DTG/LOG | I220: 46283 | J220: 157/26-REVLOG | K220: VALOMADA
... A224: 46283 | C224: SUPPORT DU DDF | D224: 58 | E224: PIE | F224: VALOMADA | G224: BSD180926 | H224: 4185/26/DTG/LOG | I224: 46283 | J224: 157/26-REVLOG | K224: VALOMADA
A225: 46293 | B225: TMXTREBD3EGENXXX | C225: ANTENNE FH 3.0 | D225: 1 | E225: PIE | F225: VALOMADA | G225: BSD280926 | H225: 3999/26/DTG/LOG | I225: 46293 | J225: 158/26-REVLOG | K225: VALOMADA
A226: 46293 | C226: ANTENNE GSM HS | D226: 3 | E226: PIE | F226: VALOMADA | G226: BSD280926 | H226: 3999/26/DTG/LOG | I226: 46293 | J226: 158/26-REVLOG | K226: VALOMADA
A227: 46293 | C227: ANTENNE FH 0.6 | D227: 2 | E227: PIE | F227: VALOMADA | G227: BSD280926 | H227: 4164/26/DTG/LOG | I227: 46293 | J227: 158/26-REVLOG | K227: VALOMADA
A228: 46293 | C228: ODU NEC | D228: 2 | E228: PIE | F228: VALOMADA | G228: BSD280926 | H228: 4164/26/DTG/LOG | I228: 46293 | J228: 158/26-REVLOG | K228: VALOMADA
A229: 46293 | C229: FAB ALCATEL | D229: 1 | E229: PIE | F229: VALOMADA | G229: BSD280926 | H229: 4165/26/DHSSES | I229: 46293 | J229: 158/26-REVLOG | K229: VALOMADA
A230: 46293 | C230: ODU NEC | D230: 2 | E230: PIE | F230: VALOMADA | G230: BSD280926 | H230: 4165/26/DHSSES | I230: 46293 | J230: 158/26-REVLOG | K230: VALOMADA
A231: 46293 | C231: RACK TNR | D231: 1 | E231: PIE | F231: VALOMADA | G231: BSD280926 | H231: 4000/26/DHSSES | I231: 46293 | J231: 158/26-REVLOG | K231: VALOMADA
A232: 46293 | C232: CABLE FO HS | D232: 1 | E232: LOT | F232: VALOMADA | G232: BSD280926 | H232: 4000/26/DHSSES | I232: 46293 | J232: 158/26-REVLOG | K232: VALOMADA
A233: 46293 | C233: CHUTTE CABLE | D233: 1 | E233: LOT | F233: VALOMADA | G233: BSD280926 | H233: 0012/26 | I233: 46293 | J233: 158/26-REVLOG | K233: VALOMADA
A234: 46293 | C234: COUPON FIBRE | D234: 3 | E234: CART | F234: VALOMADA | G234: BSD280926 | H234: 003/26/DFG/MAINT | I234: 46293 | J234: 158/26-REVLOG | K234: VALOMADA
A235: 46293 | C235: DIVERS EQUIPEMENTS | D235: 1 | E235: LOT | F235: VALOMADA | G235: BSD280926 | H235: 003/26/DFG/MAINT | I235: 46293 | J235: 158/26-REVLOG | K235: VALOMADA
A236: 46293 | C236: CHAISE | D236: 4 | E236: PIE | F236: VALOMADA | G236: BSD280926 | H236: 003/26/DFG/MAINT | I236: 46293 | J236: 158/26-REVLOG | K236: VALOMADA
A237: 46293 | C237: MACHINE MISE SOUS PLI | D237: 1 | E237: PIE | F237: VALOMADA | G237: BSD280926 | H237: 06/26/DSI | I237: 46293 | J237: 158/26-REVLOG | K237: VALOMADA
... A281: 46293 | C281: RACK RESEAU | D281: 7 | E281: PIE | F281: VALOMADA | G281: BSD280926 | H281: 01/26/DSI | I281: 46293 | J281: 158/26-REVLOG | K281: VALOMADA
A282: 46293 | B282: TMXTREBD3EGENXXX | C282: PJ400 PROJECTEUR | D282: 1 | E282: PIE | F282: VALOMADA | G282: BSD280926 | H282: 3837/26/DTG/LOG | I282: 46293 | J282: 158/26-REVLOG | K282: VALOMADA
A283: 46293 | B283: TMXTREBD3EGENXXX | C283: SWITCH CENT CSH 2400 | D283: 1 | E283: PIE | F283: VALOMADA | G283: BSD280926 | H283: 3837/26/DTG/LOG | I283: 46293 | J283: 158/26-REVLOG | K283: VALOMADA
A284: 46293 | B284: TMXTREBD3EGENXXX | C284: ELTEK FLATPACK | D284: 2 | E284: PIE | F284: VALOMADA | G284: BSD280926 | H284: 3837/26/DTG/LOG | I284: 46293 | J284: 158/26-REVLOG | K284: VALOMADA
A285: 46293 | B285: TMXTREBD3EGENXXX | C285: MOOV BOX BEWAN | D285: 1 | E285: PIE | F285: VALOMADA | G285: BSD280926 | H285: 3837/26/DTG/LOG | I285: 46293 | J285: 158/26-REVLOG | K285: VALOMADA
A286: 46293 | B286: TMXTREBD3EGENXXX | C286: UC HP COMPAQ DX2000 | D286: 2 | E286: PIE | F286: VALOMADA | G286: BSD280926 | H286: 3837/26/DTG/LOG | I286: 46293 | J286: 158/26-REVLOG | K286: VALOMADA
A287: 46293 | B287: TMXTREBD3EGENXXX | C287: UC HP COMPAQ KM635 | D287: 4 | E287: PIE | F287: VALOMADA | G287: BSD280926 | H287: 3837/26/DTG/LOG | I287: 46293 | J287: 158/26-REVLOG | K287: VALOMADA
A288: 46293 | B288: TMXTREBD3EGENXXX | C288: UC DELL PRECISION 380 | D288: 1 | E288: PIE | F288: VALOMADA | G288: BSD280926 | H288: 3837/26/DTG/LOG | I288: 46293 | J288: 158/26-REVLOG | K288: VALOMADA
A289: 46293 | B289: TMXTREBD3EGENXXX | C289: DELTA DPR 4000B 48 | D289: 1 | E289: PIE | F289: VALOMADA | G289: BSD280926 | H289: 3837/26/DTG/LOG | I289: 46293 | J289: 158/26-REVLOG | K289: VALOMADA
A290: 46293 | B290: TMXTREBD3EGENXXX | C290: DELTA DPS 480 | D290: 1 | E290: PIE | F290: VALOMADA | G290: BSD280926 | H290: 3837/26/DTG/LOG | I290: 46293 | J290: 158/26-REVLOG | K290: VALOMADA
A291: 46293 | B291: TMXTREBD3EGENXXX | C291: MODEM HUGHES HX200 | D291: 1 | E291: PIE | F291: VALOMADA | G291: BSD280926 | H291: 3837/26/DTG/LOG | I291: 46293 | J291: 158/26-REVLOG | K291: VALOMADA
A292: 46293 | B292: TMXTREBD3EGENXXX | C292: INVERTER SU KAM | D292: 1 | E292: PIE | F292: VALOMADA | G292: BSD280926 | H292: 3837/26/DTG/LOG | I292: 46293 | J292: 158/26-REVLOG | K292: VALOMADA
A293: 46293 | B293: TMXTREBD3EGENXXX | C293: EME 1,SGHZ | D293: 1 | E293: PIE | F293: VALOMADA | G293: BSD280926 | H293: 3837/26/DTG/LOG | I293: 46293 | J293: 158/26-REVLOG | K293: VALOMADA
... A318: 46293 | B318: TMXTREBD3EGENXXX | C318: CONDENSEUR | D318: 4 | E318: PIE | F318: VALOMADA | G318: BSD280926 | H318: 4154/26/DTG/LOG | I318: 46293 | J318: 158/26-REVLOG | K318: VALOMADA
A319: 46297 | C319: SERVEUR IBM X3550 | D319: 22 | E319: PCS | F319: VALOMADA | G319: BSD021026 | H319: 02/26/DSI | I319: 46297 | J319: 160/26-REVLOG | K319: VALOMADA
...
